Workbook

Sheet MAIN
A1: Listing_ID | B1: Raw_Title | C1: Locality_Text | D1: Asset_Type_Raw | E1: Configuration_Raw | F1: Area_Value | G1: Area_Unit | H1: Price_Value | I1: Price_Unit | J1: Price_Frequency | K1: Status | L1: Remarks | M1: Micro_Market | N1: Standard_Asset_Class | O1: Standard_BHK | P1: Vertical | Q1: Price_INR | R1: Area_Sqft | S1: Resale_PPSF | T1: Notes | U1: Micro Market | V1: Asset | W1: Resale N | X1: Median Resale PPSF | Y1: LTR_INR_per_Sqft_Month | Z1: LTR N | AA1: Median LTR INR/sqft/month | AB1: Implied Gross Rental Yield % | AC1: Median STR ADR
A2: K0001 | B2: NA Plot for sale in Central Karjat | C2: Central Karjat | D2: NA Plot | E2: NA | F2: 3139 | G2: sqft | H2: 29.73 | I2: Lakh | J2: One-time | K2: Active | M2: =_xlfn.XLOOKUP(TRIM(C2),MAPPING!A:A,MAPPING!B:B,"CHECK") -> Karjat Town | N2: =_xlfn.XLOOKUP(D2,MAPPING!G:G,MAPPING!H:H,"CHECK") -> Plot | O2: =_xlfn.XLOOKUP(E2,MAPPING!J:J,MAPPING!K:K,"CHECK") -> NA | P2: =_xlfn.XLOOKUP(J2,MAPPING!M:M,MAPPING!N:N,"CHECK") -> Resale | Q2: =IF(I2="INR",H2,IF(I2="Lakh",H2*100000,IF(I2="Crore",H2*10000000,IF(I2="Thousand",H2*1000,"")))) -> 2973000 | R2: =IF(G2="sqft",F2,IF(G2="sqyd",F2*9,IF(G2="acre",F2*43560,IF(G2="guntha",F2*1089,IF(G2="hectare",F2*107639.1,""))))) -> 3139 | S2: =IF(AND(P2="Resale",R2>0),Q2/R2,"") -> 947.11692 | U2: Karjat Town | V2: Villa | W2: =COUNTIFS($M$2:$M$209,U2,$N$2:$N$209,V2,$P$2:$P$209,"Resale") -> 11 | X2: {=IFERROR(MEDIAN(_xlfn._xlws.FILTER($S$2:$S$209,($M$2:$M$209=U2)*($N$2:$N$209=V2)*($P$2:$P$209="Resale")*($S$2:$S$209<>""))),"")} -> 4641.194 | Y2: =IF(AND(P2="Long Term Rental",R2>0),Q2/R2,"") | Z2: =COUNTIFS($M$2:$M$209,U2,$N$2:$N$209,V2,$P$2:$P$209,"Long Term Rental") -> 8 | AA2: {=IF(Z2=0,"",MEDIAN(_xlfn._xlws.FILTER($Y$2:$Y$209,($M$2:$M$209=U2)*($N$2:$N$209=V2)*($P$2:$P$209="Long Term Rental")*($Y$2:$Y$209<>""),"")))} -> 14.651858 | AB2: =IF(AND(V2="Villa",X2<>"",AA2<>""),(AA2*12/X2)*100,"") -> 3.7882987 | AC2: {=IFERROR(MEDIAN(_xlfn._xlws.FILTER($Q$2:$Q$209,($M$2:$M$209=U2)*($P$2:$P$209="Short Term Rental")*($Q$2:$Q$209<>""))),"")} -> 5650
A3: K0002 | B3: 4BHK Bungalow for sale in Karjat | C3: Karjat | D3: Bungalow | E3: 4BHK | F3: 2495 | G3: sqft | I3: Crore | J3: One-time | K3: Price on Request | M3: =_xlfn.XLOOKUP(TRIM(C3),MAPPING!A:A,MAPPING!B:B,"CHECK") -> Karjat Town | N3: =_xlfn.XLOOKUP(D3,MAPPING!G:G,MAPPING!H:H,"CHECK") -> Villa | O3: =_xlfn.XLOOKUP(E3,MAPPING!J:J,MAPPING!K:K,"CHECK") -> 4 BHK | P3: =_xlfn.XLOOKUP(J3,MAPPING!M:M,MAPPING!N:N,"CHECK") -> Resale | Q3: =IF(I3="INR",H3,IF(I3="Lakh",H3*100000,IF(I3="Crore",H3*10000000,IF(I3="Thousand",H3*1000,"")))) -> 0 | R3: =IF(G3="sqft",F3,IF(G3="sqyd",F3*9,IF(G3="acre",F3*43560,IF(G3="guntha",F3*1089,IF(G3="hectare",F3*107639.1,""))))) -> 2495 | S3: =IF(AND(P3="Resale",R3>0),Q3/R3,"") -> 0 | U3: Karjat Town | V3: Plot | W3: =COUNTIFS($M$2:$M$209,U3,$N$2:$N$209,V3,$P$2:$P$209,"Resale") -> 8 | X3: {=IFERROR(MEDIAN(_xlfn._xlws.FILTER($S$2:$S$209,($M$2:$M$209=U3)*($N$2:$N$209=V3)*($P$2:$P$209="Resale")*($S$2:$S$209<>""))),"")} -> 947.11692 | Y3: =IF(AND(P3="Long Term Rental",R3>0),Q3/R3,"") | Z3: =COUNTIFS($M$2:$M$209,U3,$N$2:$N$209,V3,$P$2:$P$209,"Long Term Rental") -> 0 | AA3: {=IF(Z3=0,"",MEDIAN(_xlfn._xlws.FILTER($Y$2:$Y$209,($M$2:$M$209=U3)*($N$2:$N$209=V3)*($P$2:$P$209="Long Term Rental")*($Y$2:$Y$209<>""),"")))} | AB3: =IF(AND(V3="Villa",X3<>"",AA3<>""),(AA3*12/X3)*100,"") | AC3: {=IFERROR(MEDIAN(_xlfn._xlws.FILTER($Q$2:$Q$209,($M$2:$M$209=U3)*($P$2:$P$209="Short Term Rental")*($Q$2:$Q$209<>""))),"")} -> 5650
A4: K0003 | B4: Plot for sale in Karjat Station Road | C4: Karjat Station Road | D4: Plot | E4: NA | F4: 1.17 | G4: acre | H4: 4.18 | I4: Crore | J4: One-time | K4: Sold | M4: =_xlfn.XLOOKUP(TRIM(C4),MAPPING!A:A,MAPPING!B:B,"CHECK") -> Karjat Town | N4: =_xlfn.XLOOKUP(D4,MAPPING!G:G,MAPPING!H:H,"CHECK") -> Plot | O4: =_xlfn.XLOOKUP(E4,MAPPING!J:J,MAPPING!K:K,"CHECK") -> NA | P4: =_xlfn.XLOOKUP(J4,MAPPING!M:M,MAPPING!N:N,"CHECK") -> Resale | Q4: =IF(I4="INR",H4,IF(I4="Lakh",H4*100000,IF(I4="Crore",H4*10000000,IF(I4="Thousand",H4*1000,"")))) -> 41800000 | R4: =IF(G4="sqft",F4,IF(G4="sqyd",F4*9,IF(G4="acre",F4*43560,IF(G4="guntha",F4*1089,IF(G4="hectare",F4*107639.1,""))))) -> 50965.2 | S4: =IF(AND(P4="Resale",R4>0),Q4/R4,"") -> 820.16749 | U4: Karjat Town | V4: Farmland | W4: =COUNTIFS($M$2:$M$209,U4,$N$2:$N$209,V4,$P$2:$P$209,"Resale") -> 5 | X4: {=IFERROR(MEDIAN(_xlfn._xlws.FILTER($S$2:$S$209,($M$2:$M$209=U4)*($N$2:$N$209=V4)*($P$2:$P$209="Resale")*($S$2:$S$209<>""))),"")} -> 148.72041 | Y4: =IF(AND(P4="Long Term Rental",R4>0),Q4/R4,"") | Z4: =COUNTIFS($M$2:$M$209,U4,$N$2:$N$209,V4,$P$2:$P$209,"Long Term Rental") -> 0 | AA4: {=IF(Z4=0,"",MEDIAN(_xlfn._xlws.FILTER($Y$2:$Y$209,($M$2:$M$209=U4)*($N$2:$N$209=V4)*($P$2:$P$209="Long Term Rental")*($Y$2:$Y$209<>""),"")))} | AB4: =IF(AND(V4="Villa",X4<>"",AA4<>""),(AA4*12/X4)*100,"") | AC4: {=IFERROR(MEDIAN(_xlfn._xlws.FILTER($Q$2:$Q$209,($M$2:$M$209=U4)*($P$2:$P$209="Short Term Rental")*($Q$2:$Q$209<>""))),"")} -> 5650
A5: K0004 | B5: Land Parcel for sale in Karjat Town | C5: Karjat Town | D5: Land Parcel | E5: NA | F5: 5.2 | G5: guntha | H5: 55.77 | I5: Lakh | J5: One-time | K5: Active | M5: =_xlfn.XLOOKUP(TRIM(C5),MAPPING!A:A,MAPPING!B:B,"CHECK") -> Karjat Town | N5: =_xlfn.XLOOKUP(D5,MAPPING!G:G,MAPPING!H:H,"CHECK") -> Plot | O5: =_xlfn.XLOOKUP(E5,MAPPING!J:J,MAPPING!K:K,"CHECK") -> NA | P5: =_xlfn.XLOOKUP(J5,MAPPING!M:M,MAPPING!N:N,"CHECK") -> Resale | Q5: =IF(I5="INR",H5,IF(I5="Lakh",H5*100000,IF(I5="Crore",H5*10000000,IF(I5="Thousand",H5*1000,"")))) -> 5577000 | R5: =IF(G5="sqft",F5,IF(G5="sqyd",F5*9,IF(G5="acre",F5*43560,IF(G5="guntha",F5*1089,IF(G5="hectare",F5*107639.1,""))))) -> 5662.8 | S5: =IF(AND(P5="Resale",R5>0),Q5/R5,"") -> 984.84848 | U5: Neral | V5: Villa | W5: =COUNTIFS($M$2:$M$209,U5,$N$2:$N$209,V5,$P$2:$P$209,"Resale") -> 15 | X5: {=IFERROR(MEDIAN(_xlfn._xlws.FILTER($S$2:$S$209,($M$2:$M$209=U5)*($N$2:$N$209=V5)*($P$2:$P$209="Resale")*($S$2:$S$209<>""))),"")} -> 3642.7759 | Y5: =IF(AND(P5="Long Term Rental",R5>0),Q5/R5,"") | Z5: =COUNTIFS($M$2:$M$209,U5,$N$2:$N$209,V5,$P$2:$P$209,"Long Term Rental") -> 9 | AA5: {=IF(Z5=0,"",MEDIAN(_xlfn._xlws.FILTER($Y$2:$Y$209,($M$2:$M$209=U5)*($N$2:$N$209=V5)*($P$2:$P$209="Long Term Rental")*($Y$2:$Y$209<>""),"")))} -> 12.890874 | AB5: =IF(AND(V5="Villa",X5<>"",AA5<>""),(AA5*12/X5)*100,"") -> 4.2465004 | AC5: {=IFERROR(MEDIAN(_xlfn._xlws.FILTER($Q$2:$Q$209,($M$2:$M$209=U5)*($P$2:$P$209="Short Term Rental")*($Q$2:$Q$209<>""))),"")} -> 5000
A6: K0005 | B6: Farm for sale in Karjat West | C6: Karjat West | D6: Farm | E6: NA | F6: 2.3 | G6: acre | H6: 1.49 | I6: Crore | J6: One-time | K6: Active | M6: =_xlfn.XLOOKUP(TRIM(C6),MAPPING!A:A,MAPPING!B:B,"CHECK") -> Karjat Town | N6: =_xlfn.XLOOKUP(D6,MAPPING!G:G,MAPPING!H:H,"CHECK") -> Farmland | O6: =_xlfn.XLOOKUP(E6,MAPPING!J:J,MAPPING!K:K,"CHECK") -> NA | P6: =_xlfn.XLOOKUP(J6,MAPPING!M:M,MAPPING!N:N,"CHECK") -> Resale | Q6: =IF(I6="INR",H6,IF(I6="Lakh",H6*100000,IF(I6="Crore",H6*10000000,IF(I6="Thousand",H6*1000,"")))) -> 14900000 | R6: =IF(G6="sqft",F6,IF(G6="sqyd",F6*9,IF(G6="acre",F6*43560,IF(G6="guntha",F6*1089,IF(G6="hectare",F6*107639.1,""))))) -> 100188 | S6: =IF(AND(P6="Resale",R6>0),Q6/R6,"") -> 148.72041 | U6: Neral | V6: Plot | W6: =COUNTIFS($M$2:$M$209,U6,$N$2:$N$209,V6,$P$2:$P$209,"Resale") -> 5 | X6: {=IFERROR(MEDIAN(_xlfn._xlws.FILTER($S$2:$S$209,($M$2:$M$209=U6)*($N$2:$N$209=V6)*($P$2:$P$209="Resale")*($S$2:$S$209<>""))),"")} -> 861.89985 | Y6: =IF(AND(P6="Long Term Rental",R6>0),Q6/R6,"") | Z6: =COUNTIFS($M$2:$M$209,U6,$N$2:$N$209,V6,$P$2:$P$209,"Long Term Rental") -> 0 | AA6: {=IF(Z6=0,"",MEDIAN(_xlfn._xlws.FILTER($Y$2:$Y$209,($M$2:$M$209=U6)*($N$2:$N$209=V6)*($P$2:$P$209="Long Term Rental")*($Y$2:$Y$209<>""),"")))} | AB6: =IF(AND(V6="Villa",X6<>"",AA6<>""),(AA6*12/X6)*100,"") | AC6: {=IFERROR(MEDIAN(_xlfn._xlws.FILTER($Q$2:$Q$209,($M$2:$M$209=U6)*($P$2:$P$209="Short Term Rental")*($Q$2:$Q$209<>""))),"")} -> 5000
A7: K0006 | B7: 2BHK Independent House for sale in Karjat | C7: Karjat | D7: Independent House | E7: 2BHK | F7: 901 | G7: sqft | H7: 43.87 | I7: Lakh | J7: One-time | K7: Active | M7: =_xlfn.XLOOKUP(TRIM(C7),MAPPING!A:A,MAPPING!B:B,"CHECK") -> Karjat Town | N7: =_xlfn.XLOOKUP(D7,MAPPING!G:G,MAPPING!H:H,"CHECK") -> Villa | O7: =_xlfn.XLOOKUP(E7,MAPPING!J:J,MAPPING!K:K,"CHECK") -> 2 BHK | P7: =_xlfn.XLOOKUP(J7,MAPPING!M:M,MAPPING!N:N,"CHECK") -> Resale | Q7: =IF(I7="INR",H7,IF(I7="Lakh",H7*100000,IF(I7="Crore",H7*10000000,IF(I7="Thousand",H7*1000,"")))) -> 4387000 | R7: =IF(G7="sqft",F7,IF(G7="sqyd",F7*9,IF(G7="acre",F7*43560,IF(G7="guntha",F7*1089,IF(G7="hectare",F7*107639.1,""))))) -> 901 | S7: =IF(AND(P7="Resale",R7>0),Q7/R7,"") -> 4869.0344 | U7: Neral | V7: Farmland | W7: =COUNTIFS($M$2:$M$209,U7,$N$2:$N$209,V7,$P$2:$P$209,"Resale") -> 5 | X7: {=IFERROR(MEDIAN(_xlfn._xlws.FILTER($S$2:$S$209,($M$2:$M$209=U7)*($N$2:$N$209=V7)*($P$2:$P$209="Resale")*($S$2:$S$209<>""))),"")} -> 152.70219 | Y7: =IF(AND(P7="Long Term Rental",R7>0),Q7/R7,"") | Z7: =COUNTIFS($M$2:$M$209,U7,$N$2:$N$209,V7,$P$2:$P$209,"Long Term Rental") -> 0 | AA7: {=IF(Z7=0,"",MEDIAN(_xlfn._xlws.FILTER($Y$2:$Y$209,($M$2:$M$209=U7)*($N$2:$N$209=V7)*($P$2:$P$209="Long Term Rental")*($Y$2:$Y$209<>""),"")))} | AB7: =IF(AND(V7="Villa",X7<>"",AA7<>""),(AA7*12/X7)*100,"") | AC7: {=IFERROR(MEDIAN(_xlfn._xlws.FILTER($Q$2:$Q$209,($M$2:$M$209=U7)*($P$2:$P$209="Short Term Rental")*($Q$2:$Q$209<>""))),"")} -> 5000
A8: K0007 | B8: Two BHK Farmhouse for sale in Karjat Town | C8: Karjat Town | D8: Farmhouse | E8: Two BHK | F8: 1675 | G8: sqft | H8: 77.74 | I8: Lakh | J8: One-time | K8: Active | M8: =_xlfn.XLOOKUP(TRIM(C8),MAPPING!A:A,MAPPING!B:B,"CHECK") -> Karjat Town | N8: =_xlfn.XLOOKUP(D8,MAPPING!G:G,MAPPING!H:H,"CHECK") -> Villa | O8: =_xlfn.XLOOKUP(E8,MAPPING!J:J,MAPPING!K:K,"CHECK") -> 2 BHK | P8: =_xlfn.XLOOKUP(J8,MAPPING!M:M,MAPPING!N:N,"CHECK") -> Resale | Q8: =IF(I8="INR",H8,IF(I8="Lakh",H8*100000,IF(I8="Crore",H8*10000000,IF(I8="Thousand",H8*1000,"")))) -> 7774000 | R8: =IF(G8="sqft",F8,IF(G8="sqyd",F8*9,IF(G8="acre",F8*43560,IF(G8="guntha",F8*1089,IF(G8="hectare",F8*107639.1,""))))) -> 1675 | S8: =IF(AND(P8="Resale",R8>0),Q8/R8,"") -> 4641.194 | U8: Kashele | V8: Villa | W8: =COUNTIFS($M$2:$M$209,U8,$N$2:$N$209,V8,$P$2:$P$209,"Resale") -> 13 | X8: {=IFERROR(MEDIAN(_xlfn._xlws.FILTER($S$2:$S$209,($M$2:$M$209=U8)*($N$2:$N$209=V8)*($P$2:$P$209="Resale")*($S$2:$S$209<>""))),"")} -> 3679.2141 | Y8: =IF(AND(P8="Long Term Rental",R8>0),Q8/R8,"") | Z8: =COUNTIFS($M$2:$M$209,U8,$N$2:$N$209,V8,$P$2:$P$209,"Long Term Rental") -> 9 | AA8: {=IF(Z8=0,"",MEDIAN(_xlfn._xlws.FILTER($Y$2:$Y$209,($M$2:$M$209=U8)*($N$2:$N$209=V8)*($P$2:$P$209="Long Term Rental")*($Y$2:$Y$209<>""),"")))} -> 12.094862 | AB8: =IF(AND(V8="Villa",X8<>"",AA8<>""),(AA8*12/X8)*100,"") -> 3.944819 | AC8: {=IFERROR(MEDIAN(_xlfn._xlws.FILTER($Q$2:$Q$209,($M$2:$M$209=U8)*($P$2:$P$209="Short Term Rental")*($Q$2:$Q$209<>""))),"")} -> 4700
A9: K0008 | B9: Farm Land for sale in Karjat Town | C9: Karjat Town | D9: Farm Land | E9: NA | F9: 0.71 | G9: acre | H9: 51.74 | I9: Lakh | J9: One-time | K9: Active | M9: =_xlfn.XLOOKUP(TRIM(C9),MAPPING!A:A,MAPPING!B:B,"CHECK") -> Karjat Town | N9: =_xlfn.XLOOKUP(D9,MAPPING!G:G,MAPPING!H:H,"CHECK") -> Farmland | O9: =_xlfn.XLOOKUP(E9,MAPPING!J:J,MAPPING!K:K,"CHECK") -> NA | P9: =_xlfn.XLOOKUP(J9,MAPPING!M:M,MAPPING!N:N,"CHECK") -> Resale | Q9: =IF(I9="INR",H9,IF(I9="Lakh",H9*100000,IF(I9="Crore",H9*10000000,IF(I9="Thousand",H9*1000,"")))) -> 5174000 | R9: =IF(G9="sqft",F9,IF(G9="sqyd",F9*9,IF(G9="acre",F9*43560,IF(G9="guntha",F9*1089,IF(G9="hectare",F9*107639.1,""))))) -> 30927.6 | S9: =IF(AND(P9="Resale",R9>0),Q9/R9,"") -> 167.29394 | U9: Kashele | V9: Plot | W9: =COUNTIFS($M$2:$M$209,U9,$N$2:$N$209,V9,$P$2:$P$209,"Resale") -> 9 | X9: {=IFERROR(MEDIAN(_xlfn._xlws.FILTER($S$2:$S$209,($M$2:$M$209=U9)*($N$2:$N$209=V9)*($P$2:$P$209="Resale")*($S$2:$S$209<>""))),"")} -> 796.62616 | Y9: =IF(AND(P9="Long Term Rental",R9>0),Q9/R9,"") | Z9: =COUNTIFS($M$2:$M$209,U9,$N$2:$N$209,V9,$P$2:$P$209,"Long Term Rental") -> 0 | AA9: {=IF(Z9=0,"",MEDIAN(_xlfn._xlws.FILTER($Y$2:$Y$209,($M$2:$M$209=U9)*($N$2:$N$209=V9)*($P$2:$P$209="Long Term Rental")*($Y$2:$Y$209<>""),"")))} | AB9: =IF(AND(V9="Villa",X9<>"",AA9<>""),(AA9*12/X9)*100,"") | AC9: {=IFERROR(MEDIAN(_xlfn._xlws.FILTER($Q$2:$Q$209,($M$2:$M$209=U9)*($P$2:$P$209="Short Term Rental")*($Q$2:$Q$209<>""))),"")} -> 4700
A10: K0009 | B10: Land Parcel for sale in Karjat Town | C10: Karjat Town | D10: Land Parcel | E10: NA | F10: 9.1 | G10: guntha | H10: 91.38 | I10: Lakh | J10: One-time | K10: Active | M10: =_xlfn.XLOOKUP(TRIM(C10),MAPPING!A:A,MAPPING!B:B,"CHECK") -> Karjat Town | N10: =_xlfn.XLOOKUP(D10,MAPPING!G:G,MAPPING!H:H,"CHECK") -> Plot | O10: =_xlfn.XLOOKUP(E10,MAPPING!J:J,MAPPING!K:K,"CHECK") -> NA | P10: =_xlfn.XLOOKUP(J10,MAPPING!M:M,MAPPING!N:N,"CHECK") -> Resale | Q10: =IF(I10="INR",H10,IF(I10="Lakh",H10*100000,IF(I10="Crore",H10*10000000,IF(I10="Thousand",H10*1000,"")))) -> 9138000 | R10: =IF(G10="sqft",F10,IF(G10="sqyd",F10*9,IF(G10="acre",F10*43560,IF(G10="guntha",F10*1089,IF(G10="hectare",F10*107639.1,""))))) -> 9909.9 | S10: =IF(AND(P10="Resale",R10>0),Q10/R10,"") -> 922.10819 | U10: Kashele | V10: Farmland | W10: =COUNTIFS($M$2:$M$209,U10,$N$2:$N$209,V10,$P$2:$P$209,"Resale") -> 5 | X10: {=IFERROR(MEDIAN(_xlfn._xlws.FILTER($S$2:$S$209,($M$2:$M$209=U10)*($N$2:$N$209=V10)*($P$2:$P$209="Resale")*($S$2:$S$209<>""))),"")} -> 126.86675 | Y10: =IF(AND(P10="Long Term Rental",R10>0),Q10/R10,"") | Z10: =COUNTIFS($M$2:$M$209,U10,$N$2:$N$209,V10,$P$2:$P$209,"Long Term Rental") -> 0 | AA10: {=IF(Z10=0,"",MEDIAN(_xlfn._xlws.FILTER($Y$2:$Y$209,($M$2:$M$209=U10)*($N$2:$N$209=V10)*($P$2:$P$209="Long Term Rental")*($Y$2:$Y$209<>""),"")))} | AB10: =IF(AND(V10="Villa",X10<>"",AA10<>""),(AA10*12/X10)*100,"") | AC10: {=IFERROR(MEDIAN(_xlfn._xlws.FILTER($Q$2:$Q$209,($M$2:$M$209=U10)*($P$2:$P$209="Short Term Rental")*($Q$2:$Q$209<>""))),"")} -> 4700
A11: K0010 | B11: 3 BHK Bungalow for sale in Karjat Town | C11: Karjat Town | D11: Bungalow | E11: 3 BHK | F11: 2285 | G11: sqft | H11: 1.16 | I11: Crore | J11: One-time | K11: Price on Request | M11: =_xlfn.XLOOKUP(TRIM(C11),MAPPING!A:A,MAPPING!B:B,"CHECK") -> Karjat Town | N11: =_xlfn.XLOOKUP(D11,MAPPING!G:G,MAPPING!H:H,"CHECK") -> Villa | O11: =_xlfn.XLOOKUP(E11,MAPPING!J:J,MAPPING!K:K,"CHECK") -> 3 BHK | P11: =_xlfn.XLOOKUP(J11,MAPPING!M:M,MAPPING!N:N,"CHECK") -> Resale | Q11: =IF(I11="INR",H11,IF(I11="Lakh",H11*100000,IF(I11="Crore",H11*10000000,IF(I11="Thousand",H11*1000,"")))) -> 11600000 | R11: =IF(G11="sqft",F11,IF(G11="sqyd",F11*9,IF(G11="acre",F11*43560,IF(G11="guntha",F11*1089,IF(G11="hectare",F11*107639.1,""))))) -> 2285 | S11: =IF(AND(P11="Resale",R11>0),Q11/R11,"") -> 5076.5864 | U11: Kondhwal Valley | V11: Villa | W11: =COUNTIFS($M$2:$M$209,U11,$N$2:$N$209,V11,$P$2:$P$209,"Resale") -> 6 | X11: {=IFERROR(MEDIAN(_xlfn._xlws.FILTER($S$2:$S$209,($M$2:$M$209=U11)*($N$2:$N$209=V11)*($P$2:$P$209="Resale")*($S$2:$S$209<>""))),"")} -> 3150.9381 | Y11: =IF(AND(P11="Long Term Rental",R11>0),Q11/R11,"") | Z11: =COUNTIFS($M$2:$M$209,U11,$N$2:$N$209,V11,$P$2:$P$209,"Long Term Rental") -> 9 | AA11: {=IF(Z11=0,"",MEDIAN(_xlfn._xlws.FILTER($Y$2:$Y$209,($M$2:$M$209=U11)*($N$2:$N$209=V11)*($P$2:$P$209="Long Term Rental")*($Y$2:$Y$209<>""),"")))} -> 11.477363 | AB11: =IF(AND(V11="Villa",X11<>"",AA11<>""),(AA11*12/X11)*100,"") -> 4.371027 | AC11: {=IFERROR(MEDIAN(_xlfn._xlws.FILTER($Q$2:$Q$209,($M$2:$M$209=U11)*($P$2:$P$209="Short Term Rental")*($Q$2:$Q$209<>""))),"")} -> 6300
A12: K0011 | B12: Land Parcel for sale in Karjat West | C12: Karjat West | D12: Land Parcel | E12: NA | G12: guntha | H12: 85.96 | I12: Lakh | J12: One-time | K12: Active | M12: =_xlfn.XLOOKUP(TRIM(C12),MAPPING!A:A,MAPPING!B:B,"CHECK") -> Karjat Town | N12: =_xlfn.XLOOKUP(D12,MAPPING!G:G,MAPPING!H:H,"CHECK") -> Plot | O12: =_xlfn.XLOOKUP(E12,MAPPING!J:J,MAPPING!K:K,"CHECK") -> NA | P12: =_xlfn.XLOOKUP(J12,MAPPING!M:M,MAPPING!N:N,"CHECK") -> Resale | Q12: =IF(I12="INR",H12,IF(I12="Lakh",H12*100000,IF(I12="Crore",H12*10000000,IF(I12="Thousand",H12*1000,"")))) -> 8596000 | R12: =IF(G12="sqft",F12,IF(G12="sqyd",F12*9,IF(G12="acre",F12*43560,IF(G12="guntha",F12*1089,IF(G12="hectare",F12*107639.1,""))))) -> 0 | S12: =IF(AND(P12="Resale",R12>0),Q12/R12,"") | U12: Kondhwal Valley | V12: Plot | W12: =COUNTIFS($M$2:$M$209,U12,$N$2:$N$209,V12,$P$2:$P$209,"Resale") -> 8 | X12: {=IFERROR(MEDIAN(_xlfn._xlws.FILTER($S$2:$S$209,($M$2:$M$209=U12)*($N$2:$N$209=V12)*($P$2:$P$209="Resale")*($S$2:$S$209<>""))),"")} -> 767.53507 | Y12: =IF(AND(P12="Long Term Rental",R12>0),Q12/R12,"") | Z12: =COUNTIFS($M$2:$M$209,U12,$N$2:$N$209,V12,$P$2:$P$209,"Long Term Rental") -> 0 | AA12: {=IF(Z12=0,"",MEDIAN(_xlfn._xlws.FILTER($Y$2:$Y$209,($M$2:$M$209=U12)*($N$2:$N$209=V12)*($P$2:$P$209="Long Term Rental")*($Y$2:$Y$209<>""),"")))} | AB12: =IF(AND(V12="Villa",X12<>"",AA12<>""),(AA12*12/X12)*100,"") | AC12: {=IFERROR(MEDIAN(_xlfn._xlws.FILTER($Q$2:$Q$209,($M$2:$M$209=U12)*($P$2:$P$209="Short Term Rental")*($Q$2:$Q$209<>""))),"")} -> 6300
A13: K0012 | B13: 3 BHK Row House for sale in Karjat Station Road | C13: Karjat Station Road | D13: Row House | E13: 3 BHK | F13: 2251 | G13: sqft | H13: 88.17 | I13: Lakh | J13: One-time | K13: Active | M13: =_xlfn.XLOOKUP(TRIM(C13),MAPPING!A:A,MAPPING!B:B,"CHECK") -> Karjat Town | N13: =_xlfn.XLOOKUP(D13,MAPPING!G:G,MAPPING!H:H,"CHECK") -> Villa | O13: =_xlfn.XLOOKUP(E13,MAPPING!J:J,MAPPING!K:K,"CHECK") -> 3 BHK | P13: =_xlfn.XLOOKUP(J13,MAPPING!M:M,MAPPING!N:N,"CHECK") -> Resale | Q13: =IF(I13="INR",H13,IF(I13="Lakh",H13*100000,IF(I13="Crore",H13*10000000,IF(I13="Thousand",H13*1000,"")))) -> 8817000 | R13: =IF(G13="sqft",F13,IF(G13="sqyd",F13*9,IF(G13="acre",F13*43560,IF(G13="guntha",F13*1089,IF(G13="hectare",F13*107639.1,""))))) -> 2251 | S13: =IF(AND(P13="Resale",R13>0),Q13/R13,"") -> 3916.9258 | U13: Kondhwal Valley | V13: Farmland | W13: =COUNTIFS($M$2:$M$209,U13,$N$2:$N$209,V13,$P$2:$P$209,"Resale") -> 5 | X13: {=IFERROR(MEDIAN(_xlfn._xlws.FILTER($S$2:$S$209,($M$2:$M$209=U13)*($N$2:$N$209=V13)*($P$2:$P$209="Resale")*($S$2:$S$209<>""))),"")} -> 123.37368 | Y13: =IF(AND(P13="Long Term Rental",R13>0),Q13/R13,"") | Z13: =COUNTIFS($M$2:$M$209,U13,$N$2:$N$209,V13,$P$2:$P$209,"Long Term Rental") -> 0 | AA13: {=IF(Z13=0,"",MEDIAN(_xlfn._xlws.FILTER($Y$2:$Y$209,($M$2:$M$209=U13)*($N$2:$N$209=V13)*($P$2:$P$209="Long Term Rental")*($Y$2:$Y$209<>""),"")))} | AB13: =IF(AND(V13="Villa",X13<>"",AA13<>""),(AA13*12/X13)*100,"") | AC13: {=IFERROR(MEDIAN(_xlfn._xlws.FILTER($Q$2:$Q$209,($M$2:$M$209=U13)*($P$2:$P$209="Short Term Rental")*($Q$2:$Q$209<>""))),"")} -> 6300
A14: K0013 | B14: Farm Land for sale in Karjat Town | C14: Karjat Town | D14: Farm Land | E14: NA | F14: 7642 | G14: sqft | H14: 10.8 | I14: Lakh | J14: One-time | K14: Active | M14: =_xlfn.XLOOKUP(TRIM(C14),MAPPING!A:A,MAPPING!B:B,"CHECK") -> Karjat Town | N14: =_xlfn.XLOOKUP(D14,MAPPING!G:G,MAPPING!H:H,"CHECK") -> Farmland | O14: =_xlfn.XLOOKUP(E14,MAPPING!J:J,MAPPING!K:K,"CHECK") -> NA | P14: =_xlfn.XLOOKUP(J14,MAPPING!M:M,MAPPING!N:N,"CHECK") -> Resale | Q14: =IF(I14="INR",H14,IF(I14="Lakh",H14*100000,IF(I14="Crore",H14*10000000,IF(I14="Thousand",H14*1000,"")))) -> 1080000 | R14: =IF(G14="sqft",F14,IF(G14="sqyd",F14*9,IF(G14="acre",F14*43560,IF(G14="guntha",F14*1089,IF(G14="hectare",F14*107639.1,""))))) -> 7642 | S14: =IF(AND(P14="Resale",R14>0),Q14/R14,"") -> 141.32426 | U14: Matheran Road | V14: Villa | W14: =COUNTIFS($M$2:$M$209,U14,$N$2:$N$209,V14,$P$2:$P$209,"Resale") -> 10 | X14: {=IFERROR(MEDIAN(_xlfn._xlws.FILTER($S$2:$S$209,($M$2:$M$209=U14)*($N$2:$N$209=V14)*($P$2:$P$209="Resale")*($S$2:$S$209<>""))),"")} -> 5034.6152 | Y14: =IF(AND(P14="Long Term Rental",R14>0),Q14/R14,"") | Z14: =COUNTIFS($M$2:$M$209,U14,$N$2:$N$209,V14,$P$2:$P$209,"Long Term Rental") -> 8 | AA14: {=IF(Z14=0,"",MEDIAN(_xlfn._xlws.FILTER($Y$2:$Y$209,($M$2:$M$209=U14)*($N$2:$N$209=V14)*($P$2:$P$209="Long Term Rental")*($Y$2:$Y$209<>""),"")))} -> 15.937632 | AB14: =IF(AND(V14="Villa",X14<>"",AA14<>""),(AA14*12/X14)*100,"") -> 3.7987328 | AC14: {=IFERROR(MEDIAN(_xlfn._xlws.FILTER($Q$2:$Q$209,($M$2:$M$209=U14)*($P$2:$P$209="Short Term Rental")*($Q$2:$Q$209<>""))),"")} -> 5800
A15: K0014 | B15: 3BHK Villa for sale in Karjat Station Road | C15: Karjat Station Road | D15: Villa | E15: 3BHK | F15: 2521 | G15: sqft | H15: 1.02 | I15: Crore | J15: One-time | K15: Price on Request | M15: =_xlfn.XLOOKUP(TRIM(C15),MAPPING!A:A,MAPPING!B:B,"CHECK") -> Karjat Town | N15: =_xlfn.XLOOKUP(D15,MAPPING!G:G,MAPPING!H:H,"CHECK") -> Villa | O15: =_xlfn.XLOOKUP(E15,MAPPING!J:J,MAPPING!K:K,"CHECK") -> 3 BHK | P15: =_xlfn.XLOOKUP(J15,MAPPING!M:M,MAPPING!N:N,"CHECK") -> Resale | Q15: =IF(I15="INR",H15,IF(I15="Lakh",H15*100000,IF(I15="Crore",H15*10000000,IF(I15="Thousand",H15*1000,"")))) -> 10200000 | R15: =IF(G15="sqft",F15,IF(G15="sqyd",F15*9,IF(G15="acre",F15*43560,IF(G15="guntha",F15*1089,IF(G15="hectare",F15*107639.1,""))))) -> 2521 | S15: =IF(AND(P15="Resale",R15>0),Q15/R15,"") -> 4046.0135 | U15: Matheran Road | V15: Plot | W15: =COUNTIFS($M$2:$M$209,U15,$N$2:$N$209,V15,$P$2:$P$209,"Resale") -> 6 | X15: {=IFERROR(MEDIAN(_xlfn._xlws.FILTER($S$2:$S$209,($M$2:$M$209=U15)*($N$2:$N$209=V15)*($P$2:$P$209="Resale")*($S$2:$S$209<>""))),"")} -> 939.08438 | Y15: =IF(AND(P15="Long Term Rental",R15>0),Q15/R15,"") | Z15: =COUNTIFS($M$2:$M$209,U15,$N$2:$N$209,V15,$P$2:$P$209,"Long Term Rental") -> 0 | AA15: {=IF(Z15=0,"",MEDIAN(_xlfn._xlws.FILTER($Y$2:$Y$209,($M$2:$M$209=U15)*($N$2:$N$209=V15)*($P$2:$P$209="Long Term Rental")*($Y$2:$Y$209<>""),"")))} | AB15: =IF(AND(V15="Villa",X15<>"",AA15<>""),(AA15*12/X15)*100,"") | AC15: {=IFERROR(MEDIAN(_xlfn._xlws.FILTER($Q$2:$Q$209,($M$2:$M$209=U15)*($P$2:$P$209="Short Term Rental")*($Q$2:$Q$209<>""))),"")} -> 5800
A16: K0015 | B16: 2 BHK Villa for sale in Karjat Town | C16: Karjat Town | D16: Villa | E16: 2 BHK | F16: 2403 | G16: sqft | H16: 1.05 | I16: Crore | J16: One-time | K16: Active | M16: =_xlfn.XLOOKUP(TRIM(C16),MAPPING!A:A,MAPPING!B:B,"CHECK") -> Karjat Town | N16: =_xlfn.XLOOKUP(D16,MAPPING!G:G,MAPPING!H:H,"CHECK") -> Villa | O16: =_xlfn.XLOOKUP(E16,MAPPING!J:J,MAPPING!K:K,"CHECK") -> 2 BHK | P16: =_xlfn.XLOOKUP(J16,MAPPING!M:M,MAPPING!N:N,"CHECK") -> Resale | Q16: =IF(I16="INR",H16,IF(I16="Lakh",H16*100000,IF(I16="Crore",H16*10000000,IF(I16="Thousand",H16*1000,"")))) -> 10500000 | R16: =IF(G16="sqft",F16,IF(G16="sqyd",F16*9,IF(G16="acre",F16*43560,IF(G16="guntha",F16*1089,IF(G16="hectare",F16*107639.1,""))))) -> 2403 | S16: =IF(AND(P16="Resale",R16>0),Q16/R16,"") -> 4369.5381 | U16: Matheran Road | V16: Farmland | W16: =COUNTIFS($M$2:$M$209,U16,$N$2:$N$209,V16,$P$2:$P$209,"Resale") -> 10 | X16: {=IFERROR(MEDIAN(_xlfn._xlws.FILTER($S$2:$S$209,($M$2:$M$209=U16)*($N$2:$N$209=V16)*($P$2:$P$209="Resale")*($S$2:$S$209<>""))),"")} -> 167.44766 | Y16: =IF(AND(P16="Long Term Rental",R16>0),Q16/R16,"") | Z16: =COUNTIFS($M$2:$M$209,U16,$N$2:$N$209,V16,$P$2:$P$209,"Long Term Rental") -> 0 | AA16: {=IF(Z16=0,"",MEDIAN(_xlfn._xlws.FILTER($Y$2:$Y$209,($M$2:$M$209=U16)*($N$2:$N$209=V16)*($P$2:$P$209="Long Term Rental")*($Y$2:$Y$209<>""),"")))} | AB16: =IF(AND(V16="Villa",X16<>"",AA16<>""),(AA16*12/X16)*100,"") | AC16: {=IFERROR(MEDIAN(_xlfn._xlws.FILTER($Q$2:$Q$209,($M$2:$M$209=U16)*($P$2:$P$209="Short Term Rental")*($Q$2:$Q$209<>""))),"")} -> 5800
A17: K0016 | B17: NA Plot for sale in Central Karjat | C17: Central Karjat | D17: NA Plot | E17: NA | F17: 0.66 | G17: acre | H17: 2.67 | I17: Crore | J17: One-time | K17: Active | M17: =_xlfn.XLOOKUP(TRIM(C17),MAPPING!A:A,MAPPING!B:B,"CHECK") -> Karjat Town | N17: =_xlfn.XLOOKUP(D17,MAPPING!G:G,MAPPING!H:H,"CHECK") -> Plot | O17: =_xlfn.XLOOKUP(E17,MAPPING!J:J,MAPPING!K:K,"CHECK") -> NA | P17: =_xlfn.XLOOKUP(J17,MAPPING!M:M,MAPPING!N:N,"CHECK") -> Resale | Q17: =IF(I17="INR",H17,IF(I17="Lakh",H17*100000,IF(I17="Crore",H17*10000000,IF(I17="Thousand",H17*1000,"")))) -> 26700000 | R17: =IF(G17="sqft",F17,IF(G17="sqyd",F17*9,IF(G17="acre",F17*43560,IF(G17="guntha",F17*1089,IF(G17="hectare",F17*107639.1,""))))) -> 28749.6 | S17: =IF(AND(P17="Resale",R17>0),Q17/R17,"") -> 928.70857 | W17: =COUNTIFS($M$2:$M$209,U17,$N$2:$N$209,V17,$P$2:$P$209,"Resale") -> 0 | X17: {=IFERROR(MEDIAN(_xlfn._xlws.FILTER($S$2:$S$209,($M$2:$M$209=U17)*($N$2:$N$209=V17)*($P$2:$P$209="Resale")*($S$2:$S$209<>""))),"")} | Y17: =IF(AND(P17="Long Term Rental",R17>0),Q17/R17,"") | Z17: =COUNTIFS($M$2:$M$209,U17,$P$2:$P$209,"Long Term Rental") -> 0 | AA17: {=IF(Z17=0,"",MEDIAN(_xlfn._xlws.FILTER($Y$2:$Y$209,($M$2:$M$209=U17)*($N$2:$N$209=V17)*($P$2:$P$209="Long Term Rental")*($Y$2:$Y$209<>""),"")))} | AB17: =IF(AND(V17="Villa",X17<>"",AA17<>""),(AA17*12/X17)*100,"") | AC17: {=IFERROR(MEDIAN(_xlfn._xlws.FILTER($Q$2:$Q$209,($M$2:$M$209=U17)*($P$2:$P$209="Short Term Rental")*($Q$2:$Q$209<>""))),"")}
A18: K0017 | B18: 3BR Independent House for sale in Karjat West | C18: Karjat West | D18: Independent House | E18: 3BR | F18: 2100 | G18: sqft | H18: 99.08 | I18: Lakh | J18: One-time | K18: Price on Request | M18: =_xlfn.XLOOKUP(TRIM(C18),MAPPING!A:A,MAPPING!B:B,"CHECK") -> Karjat Town | N18: =_xlfn.XLOOKUP(D18,MAPPING!G:G,MAPPING!H:H,"CHECK") -> Villa | O18: =_xlfn.XLOOKUP(E18,MAPPING!J:J,MAPPING!K:K,"CHECK") -> 3 BHK | P18: =_xlfn.XLOOKUP(J18,MAPPING!M:M,MAPPING!N:N,"CHECK") -> Resale | Q18: =IF(I18="INR",H18,IF(I18="Lakh",H18*100000,IF(I18="Crore",H18*10000000,IF(I18="Thousand",H18*1000,"")))) -> 9908000 | R18: =IF(G18="sqft",F18,IF(G18="sqyd",F18*9,IF(G18="acre",F18*43560,IF(G18="guntha",F18*1089,IF(G18="hectare",F18*107639.1,""))))) -> 2100 | S18: =IF(AND(P18="Resale",R18>0),Q18/R18,"") -> 4718.0952 | W18: =COUNTIFS($M$2:$M$209,U18,$N$2:$N$209,V18,$P$2:$P$209,"Resale") -> 0 | X18: {=IFERROR(MEDIAN(_xlfn._xlws.FILTER($S$2:$S$209,($M$2:$M$209=U18)*($N$2:$N$209=V18)*($P$2:$P$209="Resale")*($S$2:$S$209<>""))),"")} | Y18: =IF(AND(P18="Long Term Rental",R18>0),Q18/R18,"") | Z18: =COUNTIFS($M$2:$M$209,U18,$P$2:$P$209,"Long Term Rental") -> 0 | AA18: {=IF(Z18=0,"",MEDIAN(_xlfn._xlws.FILTER($Y$2:$Y$209,($M$2:$M$209=U18)*($N$2:$N$209=V18)*($P$2:$P$209="Long Term Rental")*($Y$2:$Y$209<>""),"")))} | AB18: =IF(AND(V18="Villa",X18<>"",AA18<>""),(AA18*12/X18)*100,"") | AC18: {=IFERROR(MEDIAN(_xlfn._xlws.FILTER($Q$2:$Q$209,($M$2:$M$209=U18)*($P$2:$P$209="Short Term Rental")*($Q$2:$Q$209<>""))),"")}
A19: K0018 | B19: Agricultural Land for sale in Karjat | C19: Karjat | D19: Agricultural Land | E19: NA | F19: 2449 | G19: sqft | H19: 3.3 | I19: Lakh | J19: One-time | K19: Active | M19: =_xlfn.XLOOKUP(TRIM(C19),MAPPING!A:A,MAPPING!B:B,"CHECK") -> Karjat Town | N19: =_xlfn.XLOOKUP(D19,MAPPING!G:G,MAPPING!H:H,"CHECK") -> Farmland | O19: =_xlfn.XLOOKUP(E19,MAPPING!J:J,MAPPING!K:K,"CHECK") -> NA | P19: =_xlfn.XLOOKUP(J19,MAPPING!M:M,MAPPING!N:N,"CHECK") -> Resale | Q19: =IF(I19="INR",H19,IF(I19="Lakh",H19*100000,IF(I19="Crore",H19*10000000,IF(I19="Thousand",H19*1000,"")))) -> 330000 | R19: =IF(G19="sqft",F19,IF(G19="sqyd",F19*9,IF(G19="acre",F19*43560,IF(G19="guntha",F19*1089,IF(G19="hectare",F19*107639.1,""))))) -> 2449 | S19: =IF(AND(P19="Resale",R19>0),Q19/R19,"") -> 134.74888 | W19: =COUNTIFS($M$2:$M$209,U19,$N$2:$N$209,V19,$P$2:$P$209,"Resale") -> 0 | X19: {=IFERROR(MEDIAN(_xlfn._xlws.FILTER($S$2:$S$209,($M$2:$M$209=U19)*($N$2:$N$209=V19)*($P$2:$P$209="Resale")*($S$2:$S$209<>""))),"")} | Y19: =IF(AND(P19="Long Term Rental",R19>0),Q19/R19,"") | Z19: =COUNTIFS($M$2:$M$209,U19,$P$2:$P$209,"Long Term Rental") -> 0 | AA19: {=IF(Z19=0,"",MEDIAN(_xlfn._xlws.FILTER($Y$2:$Y$209,($M$2:$M$209=U19)*($N$2:$N$209=V19)*($P$2:$P$209="Long Term Rental")*($Y$2:$Y$209<>""),"")))} | AB19: =IF(AND(V19="Villa",X19<>"",AA19<>""),(AA19*12/X19)*100,"") | AC19: {=IFERROR(MEDIAN(_xlfn._xlws.FILTER($Q$2:$Q$209,($M$2:$M$209=U19)*($P$2:$P$209="Short Term Rental")*($Q$2:$Q$209<>""))),"")}
A20: K0019 | B20: 3BR Row House for sale in Karjat | C20: Karjat | D20: Row House | E20: 3BR | F20: 1198 | G20: sqft | H20: 56.59 | I20: Lakh | J20: One-time | K20: Active | M20: =_xlfn.XLOOKUP(TRIM(C20),MAPPING!A:A,MAPPING!B:B,"CHECK") -> Karjat Town | N20: =_xlfn.XLOOKUP(D20,MAPPING!G:G,MAPPING!H:H,"CHECK") -> Villa | O20: =_xlfn.XLOOKUP(E20,MAPPING!J:J,MAPPING!K:K,"CHECK") -> 3 BHK | P20: =_xlfn.XLOOKUP(J20,MAPPING!M:M,MAPPING!N:N,"CHECK") -> Resale | Q20: =IF(I20="INR",H20,IF(I20="Lakh",H20*100000,IF(I20="Crore",H20*10000000,IF(I20="Thousand",H20*1000,"")))) -> 5659000 | R20: =IF(G20="sqft",F20,IF(G20="sqyd",F20*9,IF(G20="acre",F20*43560,IF(G20="guntha",F20*1089,IF(G20="hectare",F20*107639.1,""))))) -> 1198 | S20: =IF(AND(P20="Resale",R20>0),Q20/R20,"") -> 4723.7062 | W20: =COUNTIFS($M$2:$M$209,U20,$N$2:$N$209,V20,$P$2:$P$209,"Resale") -> 0 | X20: {=IFERROR(MEDIAN(_xlfn._xlws.FILTER($S$2:$S$209,($M$2:$M$209=U20)*($N$2:$N$209=V20)*($P$2:$P$209="Resale")*($S$2:$S$209<>""))),"")} | Y20: =IF(AND(P20="Long Term Rental",R20>0),Q20/R20,"") | Z20: =COUNTIFS($M$2:$M$209,U20,$P$2:$P$209,"Long Term Rental") -> 0 | AA20: {=IF(Z20=0,"",MEDIAN(_xlfn._xlws.FILTER($Y$2:$Y$209,($M$2:$M$209=U20)*($N$2:$N$209=V20)*($P$2:$P$209="Long Term Rental")*($Y$2:$Y$209<>""),"")))} | AB20: =IF(AND(V20="Villa",X20<>"",AA20<>""),(AA20*12/X20)*100,"") | AC20: {=IFERROR(MEDIAN(_xlfn._xlws.FILTER($Q$2:$Q$209,($M$2:$M$209=U20)*($P$2:$P$209="Short Term Rental")*($Q$2:$Q$209<>""))),"")}
A21: K0020 | B21: Farm Land for sale in Central Karjat | C21: Central Karjat | D21: Farm Land | E21: NA | F21: 5974 | G21: sqft | H21: 9.61 | I21: Lakh | J21: One-time | K21: Active | M21: =_xlfn.XLOOKUP(TRIM(C21),MAPPING!A:A,MAPPING!B:B,"CHECK") -> Karjat Town | N21: =_xlfn.XLOOKUP(D21,MAPPING!G:G,MAPPING!H:H,"CHECK") -> Farmland | O21: =_xlfn.XLOOKUP(E21,MAPPING!J:J,MAPPING!K:K,"CHECK") -> NA | P21: =_xlfn.XLOOKUP(J21,MAPPING!M:M,MAPPING!N:N,"CHECK") -> Resale | Q21: =IF(I21="INR",H21,IF(I21="Lakh",H21*100000,IF(I21="Crore",H21*10000000,IF(I21="Thousand",H21*1000,"")))) -> 961000 | R21: =IF(G21="sqft",F21,IF(G21="sqyd",F21*9,IF(G21="acre",F21*43560,IF(G21="guntha",F21*1089,IF(G21="hectare",F21*107639.1,""))))) -> 5974 | S21: =IF(AND(P21="Resale",R21>0),Q21/R21,"") -> 160.86374 | W21: =COUNTIFS($M$2:$M$209,U21,$N$2:$N$209,V21,$P$2:$P$209,"Resale") -> 0 | X21: {=IFERROR(MEDIAN(_xlfn._xlws.FILTER($S$2:$S$209,($M$2:$M$209=U21)*($N$2:$N$209=V21)*($P$2:$P$209="Resale")*($S$2:$S$209<>""))),"")} | Y21: =IF(AND(P21="Long Term Rental",R21>0),Q21/R21,"") | Z21: =COUNTIFS($M$2:$M$209,U21,$P$2:$P$209,"Long Term Rental") -> 0 | AA21: {=IF(Z21=0,"",MEDIAN(_xlfn._xlws.FILTER($Y$2:$Y$209,($M$2:$M$209=U21)*($N$2:$N$209=V21)*($P$2:$P$209="Long Term Rental")*($Y$2:$Y$209<>""),"")))} | AB21: =IF(AND(V21="Villa",X21<>"",AA21<>""),(AA21*12/X21)*100,"") | AC21: {=IFERROR(MEDIAN(_xlfn._xlws.FILTER($Q$2:$Q$209,($M$2:$M$209=U21)*($P$2:$P$209="Short Term Rental")*($Q$2:$Q$209<>""))),"")}
A22: K0021 | B22: 3BR Row House for sale in Central Karjat | C22: Central Karjat | D22: Row House | E22: 3BR | F22: 3049 | G22: sqft | H22: 1.28 | I22: Crore | J22: One-time | K22: Sold | M22: =_xlfn.XLOOKUP(TRIM(C22),MAPPING!A:A,MAPPING!B:B,"CHECK") -> Karjat Town | N22: =_xlfn.XLOOKUP(D22,MAPPING!G:G,MAPPING!H:H,"CHECK") -> Villa | O22: =_xlfn.XLOOKUP(E22,MAPPING!J:J,MAPPING!K:K,"CHECK") -> 3 BHK | P22: =_xlfn.XLOOKUP(J22,MAPPING!M:M,MAPPING!N:N,"CHECK") -> Resale | Q22: =IF(I22="INR",H22,IF(I22="Lakh",H22*100000,IF(I22="Crore",H22*10000000,IF(I22="Thousand",H22*1000,"")))) -> 12800000 | R22: =IF(G22="sqft",F22,IF(G22="sqyd",F22*9,IF(G22="acre",F22*43560,IF(G22="guntha",F22*1089,IF(G22="hectare",F22*107639.1,""))))) -> 3049 | S22: =IF(AND(P22="Resale",R22>0),Q22/R22,"") -> 4198.0977 | W22: =COUNTIFS($M$2:$M$209,U22,$N$2:$N$209,V22,$P$2:$P$209,"Resale") -> 0 | X22: {=IFERROR(MEDIAN(_xlfn._xlws.FILTER($S$2:$S$209,($M$2:$M$209=U22)*($N$2:$N$209=V22)*($P$2:$P$209="Resale")*($S$2:$S$209<>""))),"")} | Y22: =IF(AND(P22="Long Term Rental",R22>0),Q22/R22,"") | Z22: =COUNTIFS($M$2:$M$209,U22,$P$2:$P$209,"Long Term Rental") -> 0 | AA22: {=IF(Z22=0,"",MEDIAN(_xlfn._xlws.FILTER($Y$2:$Y$209,($M$2:$M$209=U22)*($N$2:$N$209=V22)*($P$2:$P$209="Long Term Rental")*($Y$2:$Y$209<>""),"")))} | AB22: =IF(AND(V22="Villa",X22<>"",AA22<>""),(AA22*12/X22)*100,"") | AC22: {=IFERROR(MEDIAN(_xlfn._xlws.FILTER($Q$2:$Q$209,($M$2:$M$209=U22)*($P$2:$P$209="Short Term Rental")*($Q$2:$Q$209<>""))),"")}
A23: K0022 | B23: Plot for sale in Karjat West | C23: Karjat West | D23: Plot | E23: NA | F23: 5.8 | G23: guntha | H23: 61.5 | I23: Lakh | J23: One-time | K23: Active | M23: =_xlfn.XLOOKUP(TRIM(C23),MAPPING!A:A,MAPPING!B:B,"CHECK") -> Karjat Town | N23: =_xlfn.XLOOKUP(D23,MAPPING!G:G,MAPPING!H:H,"CHECK") -> Plot | O23: =_xlfn.XLOOKUP(E23,MAPPING!J:J,MAPPING!K:K,"CHECK") -> NA | P23: =_xlfn.XLOOKUP(J23,MAPPING!M:M,MAPPING!N:N,"CHECK") -> Resale | Q23: =IF(I23="INR",H23,IF(I23="Lakh",H23*100000,IF(I23="Crore",H23*10000000,IF(I23="Thousand",H23*1000,"")))) -> 6150000 | R23: =IF(G23="sqft",F23,IF(G23="sqyd",F23*9,IF(G23="acre",F23*43560,IF(G23="guntha",F23*1089,IF(G23="hectare",F23*107639.1,""))))) -> 6316.2 | S23: =IF(AND(P23="Resale",R23>0),Q23/R23,"") -> 973.68671 | W23: =COUNTIFS($M$2:$M$209,U23,$N$2:$N$209,V23,$P$2:$P$209,"Resale") -> 0 | X23: {=IFERROR(MEDIAN(_xlfn._xlws.FILTER($S$2:$S$209,($M$2:$M$209=U23)*($N$2:$N$209=V23)*($P$2:$P$209="Resale")*($S$2:$S$209<>""))),"")} | Y23: =IF(AND(P23="Long Term Rental",R23>0),Q23/R23,"") | Z23: =COUNTIFS($M$2:$M$209,U23,$P$2:$P$209,"Long Term Rental") -> 0 | AA23: {=IF(Z23=0,"",MEDIAN(_xlfn._xlws.FILTER($Y$2:$Y$209,($M$2:$M$209=U23)*($N$2:$N$209=V23)*($P$2:$P$209="Long Term Rental")*($Y$2:$Y$209<>""),"")))} | AB23: =IF(AND(V23="Villa",X23<>"",AA23<>""),(AA23*12/X23)*100,"") | AC23: {=IFERROR(MEDIAN(_xlfn._xlws.FILTER($Q$2:$Q$209,($M$2:$M$209=U23)*($P$2:$P$209="Short Term Rental")*($Q$2:$Q$209<>""))),"")}
A24: K0023 | B24: 2 BHK Row House for sale in Karjat West | C24: Karjat West | D24: Row House | E24: 2 BHK | F24: 1366 | G24: sqft | H24: 63.46 | I24: Lakh | J24: One-time | K24: Active | M24: =_xlfn.XLOOKUP(TRIM(C24),MAPPING!A:A,MAPPING!B:B,"CHECK") -> Karjat Town | N24: =_xlfn.XLOOKUP(D24,MAPPING!G:G,MAPPING!H:H,"CHECK") -> Villa | O24: =_xlfn.XLOOKUP(E24,MAPPING!J:J,MAPPING!K:K,"CHECK") -> 2 BHK | P24: =_xlfn.XLOOKUP(J24,MAPPING!M:M,MAPPING!N:N,"CHECK") -> Resale | Q24: =IF(I24="INR",H24,IF(I24="Lakh",H24*100000,IF(I24="Crore",H24*10000000,IF(I24="Thousand",H24*1000,"")))) -> 6346000 | R24: =IF(G24="sqft",F24,IF(G24="sqyd",F24*9,IF(G24="acre",F24*43560,IF(G24="guntha",F24*1089,IF(G24="hectare",F24*107639.1,""))))) -> 1366 | S24: =IF(AND(P24="Resale",R24>0),Q24/R24,"") -> 4645.6808 | W24: =COUNTIFS($M$2:$M$209,U24,$N$2:$N$209,V24,$P$2:$P$209,"Resale") -> 0 | X24: {=IFERROR(MEDIAN(_xlfn._xlws.FILTER($S$2:$S$209,($M$2:$M$209=U24)*($N$2:$N$209=V24)*($P$2:$P$209="Resale")*($S$2:$S$209<>""))),"")} | Y24: =IF(AND(P24="Long Term Rental",R24>0),Q24/R24,"") | Z24: =COUNTIFS($M$2:$M$209,U24,$P$2:$P$209,"Long Term Rental") -> 0 | AA24: {=IF(Z24=0,"",MEDIAN(_xlfn._xlws.FILTER($Y$2:$Y$209,($M$2:$M$209=U24)*($N$2:$N$209=V24)*($P$2:$P$209="Long Term Rental")*($Y$2:$Y$209<>""),"")))} | AB24: =IF(AND(V24="Villa",X24<>"",AA24<>""),(AA24*12/X24)*100,"") | AC24: {=IFERROR(MEDIAN(_xlfn._xlws.FILTER($Q$2:$Q$209,($M$2:$M$209=U24)*($P$2:$P$209="Short Term Rental")*($Q$2:$Q$209<>""))),"")}
A25: K0024 | B25: NA Plot for sale in Central Karjat | C25: Central Karjat | D25: NA Plot | E25: NA | F25: 2.72 | G25: acre | H25: 11.75 | I25: Crore | J25: One-time | K25: Active | M25: =_xlfn.XLOOKUP(TRIM(C25),MAPPING!A:A,MAPPING!B:B,"CHECK") -> Karjat Town | N25: =_xlfn.XLOOKUP(D25,MAPPING!G:G,MAPPING!H:H,"CHECK") -> Plot | O25: =_xlfn.XLOOKUP(E25,MAPPING!J:J,MAPPING!K:K,"CHECK") -> NA | P25: =_xlfn.XLOOKUP(J25,MAPPING!M:M,MAPPING!N:N,"CHECK") -> Resale | Q25: =IF(I25="INR",H25,IF(I25="Lakh",H25*100000,IF(I25="Crore",H25*10000000,IF(I25="Thousand",H25*1000,"")))) -> 117500000 | R25: =IF(G25="sqft",F25,IF(G25="sqyd",F25*9,IF(G25="acre",F25*43560,IF(G25="guntha",F25*1089,IF(G25="hectare",F25*107639.1,""))))) -> 118483.2 | S25: =IF(AND(P25="Resale",R25>0),Q25/R25,"") -> 991.70178 | W25: =COUNTIFS($M$2:$M$209,U25,$N$2:$N$209,V25,$P$2:$P$209,"Resale") -> 0 | X25: {=IFERROR(MEDIAN(_xlfn._xlws.FILTER($S$2:$S$209,($M$2:$M$209=U25)*($N$2:$N$209=V25)*($P$2:$P$209="Resale")*($S$2:$S$209<>""))),"")} | Y25: =IF(AND(P25="Long Term Rental",R25>0),Q25/R25,"") | Z25: =COUNTIFS($M$2:$M$209,U25,$P$2:$P$209,"Long Term Rental") -> 0 | AA25: {=IF(Z25=0,"",MEDIAN(_xlfn._xlws.FILTER($Y$2:$Y$209,($M$2:$M$209=U25)*($N$2:$N$209=V25)*($P$2:$P$209="Long Term Rental")*($Y$2:$Y$209<>""),"")))} | AB25: =IF(AND(V25="Villa",X25<>"",AA25<>""),(AA25*12/X25)*100,"") | AC25: {=IFERROR(MEDIAN(_xlfn._xlws.FILTER($Q$2:$Q$209,($M$2:$M$209=U25)*($P$2:$P$209="Short Term Rental")*($Q$2:$Q$209<>""))),"")}
A26: K0025 | B26: 2 BHK Bungalow for rent in Karjat Town | C26: Karjat Town | D26: Bungalow | E26: 2 BHK | F26: 1794 | G26: sqft | H26: 28100 | I26: INR | J26: Monthly | K26: Active | M26: =_xlfn.XLOOKUP(TRIM(C26),MAPPING!A:A,MAPPING!B:B,"CHECK") -> Karjat Town | N26: =_xlfn.XLOOKUP(D26,MAPPING!G:G,MAPPING!H:H,"CHECK") -> Villa | O26: =_xlfn.XLOOKUP(E26,MAPPING!J:J,MAPPING!K:K,"CHECK") -> 2 BHK | P26: =_xlfn.XLOOKUP(J26,MAPPING!M:M,MAPPING!N:N,"CHECK") -> Long Term Rental | Q26: =IF(I26="INR",H26,IF(I26="Lakh",H26*100000,IF(I26="Crore",H26*10000000,IF(I26="Thousand",H26*1000,"")))) -> 28100 | R26: =IF(G26="sqft",F26,IF(G26="sqyd",F26*9,IF(G26="acre",F26*43560,IF(G26="guntha",F26*1089,IF(G26="hectare",F26*107639.1,""))))) -> 1794 | S26: =IF(AND(P26="Resale",R26>0),Q26/R26,"") | W26: =COUNTIFS($M$2:$M$209,U26,$N$2:$N$209,V26,$P$2:$P$209,"Resale") -> 0 | X26: {=IFERROR(MEDIAN(_xlfn._xlws.FILTER($S$2:$S$209,($M$2:$M$209=U26)*($N$2:$N$209=V26)*($P$2:$P$209="Resale")*($S$2:$S$209<>""))),"")} | Y26: =IF(AND(P26="Long Term Rental",R26>0),Q26/R26,"") -> 15.663322 | Z26: =COUNTIFS($M$2:$M$209,U26,$P$2:$P$209,"Long Term Rental") -> 0 | AA26: {=IF(Z26=0,"",MEDIAN(_xlfn._xlws.FILTER($Y$2:$Y$209,($M$2:$M$209=U26)*($N$2:$N$209=V26)*($P$2:$P$209="Long Term Rental")*($Y$2:$Y$209<>""),"")))} | AB26: =IF(AND(V26="Villa",X26<>"",AA26<>""),(AA26*12/X26)*100,"") | AC26: {=IFERROR(MEDIAN(_xlfn._xlws.FILTER($Q$2:$Q$209,($M$2:$M$209=U26)*($P$2:$P$209="Short Term Rental")*($Q$2:$Q$209<>""))),"")}
A27: K0026 | B27: 3 BHK Villa for rent in Central Karjat | C27: Central Karjat | D27: Villa | E27: 3 BHK | F27: 1440 | G27: sqft | H27: 20000 | I27: INR | J27: Monthly | K27: Active | M27: =_xlfn.XLOOKUP(TRIM(C27),MAPPING!A:A,MAPPING!B:B,"CHECK") -> Karjat Town | N27: =_xlfn.XLOOKUP(D27,MAPPING!G:G,MAPPING!H:H,"CHECK") -> Villa | O27: =_xlfn.XLOOKUP(E27,MAPPING!J:J,MAPPING!K:K,"CHECK") -> 3 BHK | P27: =_xlfn.XLOOKUP(J27,MAPPING!M:M,MAPPING!N:N,"CHECK") -> Long Term Rental | Q27: =IF(I27="INR",H27,IF(I27="Lakh",H27*100000,IF(I27="Crore",H27*10000000,IF(I27="Thousand",H27*1000,"")))) -> 20000 | R27: =IF(G27="sqft",F27,IF(G27="sqyd",F27*9,IF(G27="acre",F27*43560,IF(G27="guntha",F27*1089,IF(G27="hectare",F27*107639.1,""))))) -> 1440 | S27: =IF(AND(P27="Resale",R27>0),Q27/R27,"") | W27: =COUNTIFS($M$2:$M$209,U27,$N$2:$N$209,V27,$P$2:$P$209,"Resale") -> 0 | X27: {=IFERROR(MEDIAN(_xlfn._xlws.FILTER($S$2:$S$209,($M$2:$M$209=U27)*($N$2:$N$209=V27)*($P$2:$P$209="Resale")*($S$2:$S$209<>""))),"")} | Y27: =IF(AND(P27="Long Term Rental",R27>0),Q27/R27,"") -> 13.888889 | Z27: =COUNTIFS($M$2:$M$209,U27,$P$2:$P$209,"Long Term Rental") -> 0 | AA27: {=IF(Z27=0,"",MEDIAN(_xlfn._xlws.FILTER($Y$2:$Y$209,($M$2:$M$209=U27)*($N$2:$N$209=V27)*($P$2:$P$209="Long Term Rental")*($Y$2:$Y$209<>""),"")))} | AB27: =IF(AND(V27="Villa",X27<>"",AA27<>""),(AA27*12/X27)*100,"") | AC27: {=IFERROR(MEDIAN(_xlfn._xlws.FILTER($Q$2:$Q$209,($M$2:$M$209=U27)*($P$2:$P$209="Short Term Rental")*($Q$2:$Q$209<>""))),"")}
A28: K0027 | B28: 3 BHK Row House for rent in Karjat Station Road | C28: Karjat Station Road | D28: Row House | E28: 3 BHK | F28: 1513 | G28: sqft | H28: 23700 | I28: INR | J28: Monthly | K28: Active | M28: =_xlfn.XLOOKUP(TRIM(C28),MAPPING!A:A,MAPPING!B:B,"CHECK") -> Karjat Town | N28: =_xlfn.XLOOKUP(D28,MAPPING!G:G,MAPPING!H:H,"CHECK") -> Villa | O28: =_xlfn.XLOOKUP(E28,MAPPING!J:J,MAPPING!K:K,"CHECK") -> 3 BHK | P28: =_xlfn.XLOOKUP(J28,MAPPING!M:M,MAPPING!N:N,"CHECK") -> Long Term Rental | Q28: =IF(I28="INR",H28,IF(I28="Lakh",H28*100000,IF(I28="Crore",H28*10000000,IF(I28="Thousand",H28*1000,"")))) -> 23700 | R28: =IF(G28="sqft",F28,IF(G28="sqyd",F28*9,IF(G28="acre",F28*43560,IF(G28="guntha",F28*1089,IF(G28="hectare",F28*107639.1,""))))) -> 1513 | S28: =IF(AND(P28="Resale",R28>0),Q28/R28,"") | W28: =COUNTIFS($M$2:$M$209,U28,$N$2:$N$209,V28,$P$2:$P$209,"Resale") -> 0 | X28: {=IFERROR(MEDIAN(_xlfn._xlws.FILTER($S$2:$S$209,($M$2:$M$209=U28)*($N$2:$N$209=V28)*($P$2:$P$209="Resale")*($S$2:$S$209<>""))),"")} | Y28: =IF(AND(P28="Long Term Rental",R28>0),Q28/R28,"") -> 15.664243 | Z28: =COUNTIFS($M$2:$M$209,U28,$P$2:$P$209,"Long Term Rental") -> 0 | AA28: {=IF(Z28=0,"",MEDIAN(_xlfn._xlws.FILTER($Y$2:$Y$209,($M$2:$M$209=U28)*($N$2:$N$209=V28)*($P$2:$P$209="Long Term Rental")*($Y$2:$Y$209<>""),"")))} | AB28: =IF(AND(V28="Villa",X28<>"",AA28<>""),(AA28*12/X28)*100,"") | AC28: {=IFERROR(MEDIAN(_xlfn._xlws.FILTER($Q$2:$Q$209,($M$2:$M$209=U28)*($P$2:$P$209="Short Term Rental")*($Q$2:$Q$209<>""))),"")}
... A34: K0033 | B34: 3BR Villa for rent in Central Karjat | C34: Central Karjat | D34: Villa | E34: 3BR | F34: 1621 | G34: sqft | H34: 23600 | I34: INR | J34: Monthly | K34: Active | M34: =_xlfn.XLOOKUP(TRIM(C34),MAPPING!A:A,MAPPING!B:B,"CHECK") -> Karjat Town | N34: =_xlfn.XLOOKUP(D34,MAPPING!G:G,MAPPING!H:H,"CHECK") -> Villa | O34: =_xlfn.XLOOKUP(E34,MAPPING!J:J,MAPPING!K:K,"CHECK") -> 3 BHK | P34: =_xlfn.XLOOKUP(J34,MAPPING!M:M,MAPPING!N:N,"CHECK") -> Long Term Rental | Q34: =IF(I34="INR",H34,IF(I34="Lakh",H34*100000,IF(I34="Crore",H34*10000000,IF(I34="Thousand",H34*1000,"")))) -> 23600 | R34: =IF(G34="sqft",F34,IF(G34="sqyd",F34*9,IF(G34="acre",F34*43560,IF(G34="guntha",F34*1089,IF(G34="hectare",F34*107639.1,""))))) -> 1621 | S34: =IF(AND(P34="Resale",R34>0),Q34/R34,"") | W34: =COUNTIFS($M$2:$M$209,U34,$N$2:$N$209,V34,$P$2:$P$209,"Resale") -> 0 | X34: {=IFERROR(MEDIAN(_xlfn._xlws.FILTER($S$2:$S$209,($M$2:$M$209=U34)*($N$2:$N$209=V34)*($P$2:$P$209="Resale")*($S$2:$S$209<>""))),"")} | Y34: =IF(AND(P34="Long Term Rental",R34>0),Q34/R34,"") -> 14.558914 | Z34: =COUNTIFS($M$2:$M$209,U34,$P$2:$P$209,"Long Term Rental") -> 0 | AA34: {=IF(Z34=0,"",MEDIAN(_xlfn._xlws.FILTER($Y$2:$Y$209,($M$2:$M$209=U34)*($N$2:$N$209=V34)*($P$2:$P$209="Long Term Rental")*($Y$2:$Y$209<>""),"")))} | AB34: =IF(AND(V34="Villa",X34<>"",AA34<>""),(AA34*12/X34)*100,"") | AC34: {=IFERROR(MEDIAN(_xlfn._xlws.FILTER($Q$2:$Q$209,($M$2:$M$209=U34)*($P$2:$P$209="Short Term Rental")*($Q$2:$Q$209<>""))),"")}
A35: K0034 | B35: 3BR Bungalow for weekend stay near Karjat Station Road | C35: Karjat Station Road | D35: Bungalow | E35: 3BR | H35: 8300 | I35: INR | J35: Per Night | K35: Active | L35: Forward 60-day availability calendar; not a confirmed-stay record. | M35: =_xlfn.XLOOKUP(TRIM(C35),MAPPING!A:A,MAPPING!B:B,"CHECK") -> Karjat Town | N35: =_xlfn.XLOOKUP(D35,MAPPING!G:G,MAPPING!H:H,"CHECK") -> Villa | O35: =_xlfn.XLOOKUP(E35,MAPPING!J:J,MAPPING!K:K,"CHECK") -> 3 BHK | P35: =_xlfn.XLOOKUP(J35,MAPPING!M:M,MAPPING!N:N,"CHECK") -> Short Term Rental | Q35: =IF(I35="INR",H35,IF(I35="Lakh",H35*100000,IF(I35="Crore",H35*10000000,IF(I35="Thousand",H35*1000,"")))) -> 8300 | R35: =IF(G35="sqft",F35,IF(G35="sqyd",F35*9,IF(G35="acre",F35*43560,IF(G35="guntha",F35*1089,IF(G35="hectare",F35*107639.1,""))))) | S35: =IF(AND(P35="Resale",R35>0),Q35/R35,"") | W35: =COUNTIFS($M$2:$M$209,U35,$N$2:$N$209,V35,$P$2:$P$209,"Resale") -> 0 | X35: {=IFERROR(MEDIAN(_xlfn._xlws.FILTER($S$2:$S$209,($M$2:$M$209=U35)*($N$2:$N$209=V35)*($P$2:$P$209="Resale")*($S$2:$S$209<>""))),"")} | Y35: =IF(AND(P35="Long Term Rental",R35>0),Q35/R35,"") | Z35: =COUNTIFS($M$2:$M$209,U35,$P$2:$P$209,"Long Term Rental") -> 0 | AA35: {=IF(Z35=0,"",MEDIAN(_xlfn._xlws.FILTER($Y$2:$Y$209,($M$2:$M$209=U35)*($N$2:$N$209=V35)*($P$2:$P$209="Long Term Rental")*($Y$2:$Y$209<>""),"")))} | AB35: =IF(AND(V35="Villa",X35<>"",AA35<>""),(AA35*12/X35)*100,"") | AC35: {=IFERROR(MEDIAN(_xlfn._xlws.FILTER($Q$2:$Q$209,($M$2:$M$209=U35)*($P$2:$P$209="Short Term Rental")*($Q$2:$Q$209<>""))),"")}
A36: K0035 | B36: 2BHK Bungalow for weekend stay near Karjat Town | C36: Karjat Town | D36: Bungalow | E36: 2BHK | H36: 7500 | I36: INR | J36: Per Night | K36: Active | L36: Forward 60-day availability calendar; not a confirmed-stay record. | M36: =_xlfn.XLOOKUP(TRIM(C36),MAPPING!A:A,MAPPING!B:B,"CHECK") -> Karjat Town | N36: =_xlfn.XLOOKUP(D36,MAPPING!G:G,MAPPING!H:H,"CHECK") -> Villa | O36: =_xlfn.XLOOKUP(E36,MAPPING!J:J,MAPPING!K:K,"CHECK") -> 2 BHK | P36: =_xlfn.XLOOKUP(J36,MAPPING!M:M,MAPPING!N:N,"CHECK") -> Short Term Rental | Q36: =IF(I36="INR",H36,IF(I36="Lakh",H36*100000,IF(I36="Crore",H36*10000000,IF(I36="Thousand",H36*1000,"")))) -> 7500 | R36: =IF(G36="sqft",F36,IF(G36="sqyd",F36*9,IF(G36="acre",F36*43560,IF(G36="guntha",F36*1089,IF(G36="hectare",F36*107639.1,""))))) | S36: =IF(AND(P36="Resale",R36>0),Q36/R36,"") | W36: =COUNTIFS($M$2:$M$209,U36,$N$2:$N$209,V36,$P$2:$P$209,"Resale") -> 0 | X36: {=IFERROR(MEDIAN(_xlfn._xlws.FILTER($S$2:$S$209,($M$2:$M$209=U36)*($N$2:$N$209=V36)*($P$2:$P$209="Resale")*($S$2:$S$209<>""))),"")} | Y36: =IF(AND(P36="Long Term Rental",R36>0),Q36/R36,"") | Z36: =COUNTIFS($M$2:$M$209,U36,$P$2:$P$209,"Long Term Rental") -> 0 | AA36: {=IF(Z36=0,"",MEDIAN(_xlfn._xlws.FILTER($Y$2:$Y$209,($M$2:$M$209=U36)*($N$2:$N$209=V36)*($P$2:$P$209="Long Term Rental")*($Y$2:$Y$209<>""),"")))} | AB36: =IF(AND(V36="Villa",X36<>"",AA36<>""),(AA36*12/X36)*100,"") | AC36: {=IFERROR(MEDIAN(_xlfn._xlws.FILTER($Q$2:$Q$209,($M$2:$M$209=U36)*($P$2:$P$209="Short Term Rental")*($Q$2:$Q$209<>""))),"")}
A37: K0036 | B37: 3 BHK Villa for weekend stay near Karjat Town | C37: Karjat Town | D37: Villa | E37: 3 BHK | H37: 8900 | I37: INR | J37: Per Night | K37: Active | L37: Forward 60-day availability calendar; not a confirmed-stay record. | M37: =_xlfn.XLOOKUP(TRIM(C37),MAPPING!A:A,MAPPING!B:B,"CHECK") -> Karjat Town | N37: =_xlfn.XLOOKUP(D37,MAPPING!G:G,MAPPING!H:H,"CHECK") -> Villa | O37: =_xlfn.XLOOKUP(E37,MAPPING!J:J,MAPPING!K:K,"CHECK") -> 3 BHK | P37: =_xlfn.XLOOKUP(J37,MAPPING!M:M,MAPPING!N:N,"CHECK") -> Short Term Rental | Q37: =IF(I37="INR",H37,IF(I37="Lakh",H37*100000,IF(I37="Crore",H37*10000000,IF(I37="Thousand",H37*1000,"")))) -> 8900 | R37: =IF(G37="sqft",F37,IF(G37="sqyd",F37*9,IF(G37="acre",F37*43560,IF(G37="guntha",F37*1089,IF(G37="hectare",F37*107639.1,""))))) | S37: =IF(AND(P37="Resale",R37>0),Q37/R37,"") | W37: =COUNTIFS($M$2:$M$209,U37,$N$2:$N$209,V37,$P$2:$P$209,"Resale") -> 0 | X37: {=IFERROR(MEDIAN(_xlfn._xlws.FILTER($S$2:$S$209,($M$2:$M$209=U37)*($N$2:$N$209=V37)*($P$2:$P$209="Resale")*($S$2:$S$209<>""))),"")} | Y37: =IF(AND(P37="Long Term Rental",R37>0),Q37/R37,"") | Z37: =COUNTIFS($M$2:$M$209,U37,$P$2:$P$209,"Long Term Rental") -> 0 | AA37: {=IF(Z37=0,"",MEDIAN(_xlfn._xlws.FILTER($Y$2:$Y$209,($M$2:$M$209=U37)*($N$2:$N$209=V37)*($P$2:$P$209="Long Term Rental")*($Y$2:$Y$209<>""),"")))} | AB37: =IF(AND(V37="Villa",X37<>"",AA37<>""),(AA37*12/X37)*100,"") | AC37: {=IFERROR(MEDIAN(_xlfn._xlws.FILTER($Q$2:$Q$209,($M$2:$M$209=U37)*($P$2:$P$209="Short Term Rental")*($Q$2:$Q$209<>""))),"")}
A38: K0037 | B38: 3BHK Farmhouse for weekend stay near Karjat | C38: Karjat | D38: Farmhouse | E38: 3BHK | H38: 6300 | I38: INR | J38: Per Night | K38: Active | L38: Forward 60-day availability calendar; not a confirmed-stay record. | M38: =_xlfn.XLOOKUP(TRIM(C38),MAPPING!A:A,MAPPING!B:B,"CHECK") -> Karjat Town | N38: =_xlfn.XLOOKUP(D38,MAPPING!G:G,MAPPING!H:H,"CHECK") -> Villa | O38: =_xlfn.XLOOKUP(E38,MAPPING!J:J,MAPPING!K:K,"CHECK") -> 3 BHK | P38: =_xlfn.XLOOKUP(J38,MAPPING!M:M,MAPPING!N:N,"CHECK") -> Short Term Rental | Q38: =IF(I38="INR",H38,IF(I38="Lakh",H38*100000,IF(I38="Crore",H38*10000000,IF(I38="Thousand",H38*1000,"")))) -> 6300 | R38: =IF(G38="sqft",F38,IF(G38="sqyd",F38*9,IF(G38="acre",F38*43560,IF(G38="guntha",F38*1089,IF(G38="hectare",F38*107639.1,""))))) | S38: =IF(AND(P38="Resale",R38>0),Q38/R38,"") | W38: =COUNTIFS($M$2:$M$209,U38,$N$2:$N$209,V38,$P$2:$P$209,"Resale") -> 0 | X38: {=IFERROR(MEDIAN(_xlfn._xlws.FILTER($S$2:$S$209,($M$2:$M$209=U38)*($N$2:$N$209=V38)*($P$2:$P$209="Resale")*($S$2:$S$209<>""))),"")} | Y38: =IF(AND(P38="Long Term Rental",R38>0),Q38/R38,"") | Z38: =COUNTIFS($M$2:$M$209,U38,$P$2:$P$209,"Long Term Rental") -> 0 | AA38: {=IF(Z38=0,"",MEDIAN(_xlfn._xlws.FILTER($Y$2:$Y$209,($M$2:$M$209=U38)*($N$2:$N$209=V38)*($P$2:$P$209="Long Term Rental")*($Y$2:$Y$209<>""),"")))} | AB38: =IF(AND(V38="Villa",X38<>"",AA38<>""),(AA38*12/X38)*100,"") | AC38: {=IFERROR(MEDIAN(_xlfn._xlws.FILTER($Q$2:$Q$209,($M$2:$M$209=U38)*($P$2:$P$209="Short Term Rental")*($Q$2:$Q$209<>""))),"")}
A39: K0038 | B39: Two BHK Bungalow for weekend stay near Central Karjat | C39: Central Karjat | D39: Bungalow | E39: Two BHK | H39: 5000 | I39: INR | J39: Per Night | K39: Active | L39: Forward 60-day availability calendar; not a confirmed-stay record. | M39: =_xlfn.XLOOKUP(TRIM(C39),MAPPING!A:A,MAPPING!B:B,"CHECK") -> Karjat Town | N39: =_xlfn.XLOOKUP(D39,MAPPING!G:G,MAPPING!H:H,"CHECK") -> Villa | O39: =_xlfn.XLOOKUP(E39,MAPPING!J:J,MAPPING!K:K,"CHECK") -> 2 BHK | P39: =_xlfn.XLOOKUP(J39,MAPPING!M:M,MAPPING!N:N,"CHECK") -> Short Term Rental | Q39: =IF(I39="INR",H39,IF(I39="Lakh",H39*100000,IF(I39="Crore",H39*10000000,IF(I39="Thousand",H39*1000,"")))) -> 5000 | R39: =IF(G39="sqft",F39,IF(G39="sqyd",F39*9,IF(G39="acre",F39*43560,IF(G39="guntha",F39*1089,IF(G39="hectare",F39*107639.1,""))))) | S39: =IF(AND(P39="Resale",R39>0),Q39/R39,"") | W39: =COUNTIFS($M$2:$M$209,U39,$N$2:$N$209,V39,$P$2:$P$209,"Resale") -> 0 | X39: {=IFERROR(MEDIAN(_xlfn._xlws.FILTER($S$2:$S$209,($M$2:$M$209=U39)*($N$2:$N$209=V39)*($P$2:$P$209="Resale")*($S$2:$S$209<>""))),"")} | Y39: =IF(AND(P39="Long Term Rental",R39>0),Q39/R39,"") | Z39: =COUNTIFS($M$2:$M$209,U39,$P$2:$P$209,"Long Term Rental") -> 0 | AA39: {=IF(Z39=0,"",MEDIAN(_xlfn._xlws.FILTER($Y$2:$Y$209,($M$2:$M$209=U39)*($N$2:$N$209=V39)*($P$2:$P$209="Long Term Rental")*($Y$2:$Y$209<>""),"")))} | AB39: =IF(AND(V39="Villa",X39<>"",AA39<>""),(AA39*12/X39)*100,"") | AC39: {=IFERROR(MEDIAN(_xlfn._xlws.FILTER($Q$2:$Q$209,($M$2:$M$209=U39)*($P$2:$P$209="Short Term Rental")*($Q$2:$Q$209<>""))),"")}
A40: K0039 | B40: Two BHK Villa for weekend stay near Central Karjat | C40: Central Karjat | D40: Villa | E40: Two BHK | H40: 3700 | I40: INR | J40: Per Night | K40: Active | L40: Forward 60-day availability calendar; not a confirmed-stay record. | M40: =_xlfn.XLOOKUP(TRIM(C40),MAPPING!A:A,MAPPING!B:B,"CHECK") -> Karjat Town | N40: =_xlfn.XLOOKUP(D40,MAPPING!G:G,MAPPING!H:H,"CHECK") -> Villa | O40: =_xlfn.XLOOKUP(E40,MAPPING!J:J,MAPPING!K:K,"CHECK") -> 2 BHK | P40: =_xlfn.XLOOKUP(J40,MAPPING!M:M,MAPPING!N:N,"CHECK") -> Short Term Rental | Q40: =IF(I40="INR",H40,IF(I40="Lakh",H40*100000,IF(I40="Crore",H40*10000000,IF(I40="Thousand",H40*1000,"")))) -> 3700 | R40: =IF(G40="sqft",F40,IF(G40="sqyd",F40*9,IF(G40="acre",F40*43560,IF(G40="guntha",F40*1089,IF(G40="hectare",F40*107639.1,""))))) | S40: =IF(AND(P40="Resale",R40>0),Q40/R40,"") | W40: =COUNTIFS($M$2:$M$209,U40,$N$2:$N$209,V40,$P$2:$P$209,"Resale") -> 0 | X40: {=IFERROR(MEDIAN(_xlfn._xlws.FILTER($S$2:$S$209,($M$2:$M$209=U40)*($N$2:$N$209=V40)*($P$2:$P$209="Resale")*($S$2:$S$209<>""))),"")} | Y40: =IF(AND(P40="Long Term Rental",R40>0),Q40/R40,"") | Z40: =COUNTIFS($M$2:$M$209,U40,$P$2:$P$209,"Long Term Rental") -> 0 | AA40: {=IF(Z40=0,"",MEDIAN(_xlfn._xlws.FILTER($Y$2:$Y$209,($M$2:$M$209=U40)*($N$2:$N$209=V40)*($P$2:$P$209="Long Term Rental")*($Y$2:$Y$209<>""),"")))} | AB40: =IF(AND(V40="Villa",X40<>"",AA40<>""),(AA40*12/X40)*100,"") | AC40: {=IFERROR(MEDIAN(_xlfn._xlws.FILTER($Q$2:$Q$209,($M$2:$M$209=U40)*($P$2:$P$209="Short Term Rental")*($Q$2:$Q$209<>""))),"")}
A41: K0040 | B41: 3 BHK Bungalow for weekend stay near Karjat Town | C41: Karjat Town | D41: Bungalow | E41: 3 BHK | H41: 4300 | I41: INR | J41: Per Night | K41: Active | L41: Forward 60-day availability calendar; not a confirmed-stay record. | M41: =_xlfn.XLOOKUP(TRIM(C41),MAPPING!A:A,MAPPING!B:B,"CHECK") -> Karjat Town | N41: =_xlfn.XLOOKUP(D41,MAPPING!G:G,MAPPING!H:H,"CHECK") -> Villa | O41: =_xlfn.XLOOKUP(E41,MAPPING!J:J,MAPPING!K:K,"CHECK") -> 3 BHK | P41: =_xlfn.XLOOKUP(J41,MAPPING!M:M,MAPPING!N:N,"CHECK") -> Short Term Rental | Q41: =IF(I41="INR",H41,IF(I41="Lakh",H41*100000,IF(I41="Crore",H41*10000000,IF(I41="Thousand",H41*1000,"")))) -> 4300 | R41: =IF(G41="sqft",F41,IF(G41="sqyd",F41*9,IF(G41="acre",F41*43560,IF(G41="guntha",F41*1089,IF(G41="hectare",F41*107639.1,""))))) | S41: =IF(AND(P41="Resale",R41>0),Q41/R41,"") | W41: =COUNTIFS($M$2:$M$209,U41,$N$2:$N$209,V41,$P$2:$P$209,"Resale") -> 0 | X41: {=IFERROR(MEDIAN(_xlfn._xlws.FILTER($S$2:$S$209,($M$2:$M$209=U41)*($N$2:$N$209=V41)*($P$2:$P$209="Resale")*($S$2:$S$209<>""))),"")} | Y41: =IF(AND(P41="Long Term Rental",R41>0),Q41/R41,"") | Z41: =COUNTIFS($M$2:$M$209,U41,$P$2:$P$209,"Long Term Rental") -> 0 | AA41: {=IF(Z41=0,"",MEDIAN(_xlfn._xlws.FILTER($Y$2:$Y$209,($M$2:$M$209=U41)*($N$2:$N$209=V41)*($P$2:$P$209="Long Term Rental")*($Y$2:$Y$209<>""),"")))} | AB41: =IF(AND(V41="Villa",X41<>"",AA41<>""),(AA41*12/X41)*100,"") | AC41: {=IFERROR(MEDIAN(_xlfn._xlws.FILTER($Q$2:$Q$209,($M$2:$M$209=U41)*($P$2:$P$209="Short Term Rental")*($Q$2:$Q$209<>""))),"")}
A42: K0041 | B42: Two BHK Bungalow for weekend stay near Karjat | C42: Karjat | D42: Bungalow | E42: Two BHK | H42: 4700 | I42: INR | J42: Per Night | K42: Active | L42: Forward 60-day availability calendar; not a confirmed-stay record. | M42: =_xlfn.XLOOKUP(TRIM(C42),MAPPING!A:A,MAPPING!B:B,"CHECK") -> Karjat Town | N42: =_xlfn.XLOOKUP(D42,MAPPING!G:G,MAPPING!H:H,"CHECK") -> Villa | O42: =_xlfn.XLOOKUP(E42,MAPPING!J:J,MAPPING!K:K,"CHECK") -> 2 BHK | P42: =_xlfn.XLOOKUP(J42,MAPPING!M:M,MAPPING!N:N,"CHECK") -> Short Term Rental | Q42: =IF(I42="INR",H42,IF(I42="Lakh",H42*100000,IF(I42="Crore",H42*10000000,IF(I42="Thousand",H42*1000,"")))) -> 4700 | R42: =IF(G42="sqft",F42,IF(G42="sqyd",F42*9,IF(G42="acre",F42*43560,IF(G42="guntha",F42*1089,IF(G42="hectare",F42*107639.1,""))))) | S42: =IF(AND(P42="Resale",R42>0),Q42/R42,"") | W42: =COUNTIFS($M$2:$M$209,U42,$N$2:$N$209,V42,$P$2:$P$209,"Resale") -> 0 | X42: {=IFERROR(MEDIAN(_xlfn._xlws.FILTER($S$2:$S$209,($M$2:$M$209=U42)*($N$2:$N$209=V42)*($P$2:$P$209="Resale")*($S$2:$S$209<>""))),"")} | Y42: =IF(AND(P42="Long Term Rental",R42>0),Q42/R42,"") | Z42: =COUNTIFS($M$2:$M$209,U42,$P$2:$P$209,"Long Term Rental") -> 0 | AA42: {=IF(Z42=0,"",MEDIAN(_xlfn._xlws.FILTER($Y$2:$Y$209,($M$2:$M$209=U42)*($N$2:$N$209=V42)*($P$2:$P$209="Long Term Rental")*($Y$2:$Y$209<>""),"")))} | AB42: =IF(AND(V42="Villa",X42<>"",AA42<>""),(AA42*12/X42)*100,"") | AC42: {=IFERROR(MEDIAN(_xlfn._xlws.FILTER($Q$2:$Q$209,($M$2:$M$209=U42)*($P$2:$P$209="Short Term Rental")*($Q$2:$Q$209<>""))),"")}
A43: K0042 | B43: 3BR Bungalow for weekend stay near Karjat Station Road | C43: Karjat Station Road | D43: Bungalow | E43: 3BR | H43: 4400 | I43: INR | J43: Per Night | K43: Active | L43: Forward 60-day availability calendar; not a confirmed-stay record. | M43: =_xlfn.XLOOKUP(TRIM(C43),MAPPING!A:A,MAPPING!B:B,"CHECK") -> Karjat Town | N43: =_xlfn.XLOOKUP(D43,MAPPING!G:G,MAPPING!H:H,"CHECK") -> Villa | O43: =_xlfn.XLOOKUP(E43,MAPPING!J:J,MAPPING!K:K,"CHECK") -> 3 BHK | P43: =_xlfn.XLOOKUP(J43,MAPPING!M:M,MAPPING!N:N,"CHECK") -> Short Term Rental | Q43: =IF(I43="INR",H43,IF(I43="Lakh",H43*100000,IF(I43="Crore",H43*10000000,IF(I43="Thousand",H43*1000,"")))) -> 4400 | R43: =IF(G43="sqft",F43,IF(G43="sqyd",F43*9,IF(G43="acre",F43*43560,IF(G43="guntha",F43*1089,IF(G43="hectare",F43*107639.1,""))))) | S43: =IF(AND(P43="Resale",R43>0),Q43/R43,"") | W43: =COUNTIFS($M$2:$M$209,U43,$N$2:$N$209,V43,$P$2:$P$209,"Resale") -> 0 | X43: {=IFERROR(MEDIAN(_xlfn._xlws.FILTER($S$2:$S$209,($M$2:$M$209=U43)*($N$2:$N$209=V43)*($P$2:$P$209="Resale")*($S$2:$S$209<>""))),"")} | Y43: =IF(AND(P43="Long Term Rental",R43>0),Q43/R43,"") | Z43: =COUNTIFS($M$2:$M$209,U43,$P$2:$P$209,"Long Term Rental") -> 0 | AA43: {=IF(Z43=0,"",MEDIAN(_xlfn._xlws.FILTER($Y$2:$Y$209,($M$2:$M$209=U43)*($N$2:$N$209=V43)*($P$2:$P$209="Long Term Rental")*($Y$2:$Y$209<>""),"")))} | AB43: =IF(AND(V43="Villa",X43<>"",AA43<>""),(AA43*12/X43)*100,"") | AC43: {=IFERROR(MEDIAN(_xlfn._xlws.FILTER($Q$2:$Q$209,($M$2:$M$209=U43)*($P$2:$P$209="Short Term Rental")*($Q$2:$Q$209<>""))),"")}
A44: K0043 | B44: 3BHK Farmhouse for sale in Neral Rd | C44: Neral Rd | D44: Farmhouse | E44: 3BHK | F44: 3127 | G44: sqft | H44: 1.38 | I44: Crore | J44: One-time | K44: Active | M44: =_xlfn.XLOOKUP(TRIM(C44),MAPPING!A:A,MAPPING!B:B,"CHECK") -> Neral | N44: =_xlfn.XLOOKUP(D44,MAPPING!G:G,MAPPING!H:H,"CHECK") -> Villa | O44: =_xlfn.XLOOKUP(E44,MAPPING!J:J,MAPPING!K:K,"CHECK") -> 3 BHK | P44: =_xlfn.XLOOKUP(J44,MAPPING!M:M,MAPPING!N:N,"CHECK") -> Resale | Q44: =IF(I44="INR",H44,IF(I44="Lakh",H44*100000,IF(I44="Crore",H44*10000000,IF(I44="Thousand",H44*1000,"")))) -> 13800000 | R44: =IF(G44="sqft",F44,IF(G44="sqyd",F44*9,IF(G44="acre",F44*43560,IF(G44="guntha",F44*1089,IF(G44="hectare",F44*107639.1,""))))) -> 3127 | S44: =IF(AND(P44="Resale",R44>0),Q44/R44,"") -> 4413.1756 | W44: =COUNTIFS($M$2:$M$209,U44,$N$2:$N$209,V44,$P$2:$P$209,"Resale") -> 0 | X44: {=IFERROR(MEDIAN(_xlfn._xlws.FILTER($S$2:$S$209,($M$2:$M$209=U44)*($N$2:$N$209=V44)*($P$2:$P$209="Resale")*($S$2:$S$209<>""))),"")} | Y44: =IF(AND(P44="Long Term Rental",R44>0),Q44/R44,"") | Z44: =COUNTIFS($M$2:$M$209,U44,$P$2:$P$209,"Long Term Rental") -> 0 | AA44: {=IF(Z44=0,"",MEDIAN(_xlfn._xlws.FILTER($Y$2:$Y$209,($M$2:$M$209=U44)*($N$2:$N$209=V44)*($P$2:$P$209="Long Term Rental")*($Y$2:$Y$209<>""),"")))} | AB44: =IF(AND(V44="Villa",X44<>"",AA44<>""),(AA44*12/X44)*100,"") | AC44: {=IFERROR(MEDIAN(_xlfn._xlws.FILTER($Q$2:$Q$209,($M$2:$M$209=U44)*($P$2:$P$209="Short Term Rental")*($Q$2:$Q$209<>""))),"")}
A45: K0044 | B45: 4BHK Farmhouse for sale in Neral | C45: Neral | D45: Farmhouse | E45: 4BHK | F45: 2138 | G45: sqft | H45: 82.16 | I45: Lakh | J45: One-time | K45: Sold | M45: =_xlfn.XLOOKUP(TRIM(C45),MAPPING!A:A,MAPPING!B:B,"CHECK") -> Neral | N45: =_xlfn.XLOOKUP(D45,MAPPING!G:G,MAPPING!H:H,"CHECK") -> Villa | O45: =_xlfn.XLOOKUP(E45,MAPPING!J:J,MAPPING!K:K,"CHECK") -> 4 BHK | P45: =_xlfn.XLOOKUP(J45,MAPPING!M:M,MAPPING!N:N,"CHECK") -> Resale | Q45: =IF(I45="INR",H45,IF(I45="Lakh",H45*100000,IF(I45="Crore",H45*10000000,IF(I45="Thousand",H45*1000,"")))) -> 8216000 | R45: =IF(G45="sqft",F45,IF(G45="sqyd",F45*9,IF(G45="acre",F45*43560,IF(G45="guntha",F45*1089,IF(G45="hectare",F45*107639.1,""))))) -> 2138 | S45: =IF(AND(P45="Resale",R45>0),Q45/R45,"") -> 3842.8438 | W45: =COUNTIFS($M$2:$M$209,U45,$N$2:$N$209,V45,$P$2:$P$209,"Resale") -> 0 | X45: {=IFERROR(MEDIAN(_xlfn._xlws.FILTER($S$2:$S$209,($M$2:$M$209=U45)*($N$2:$N$209=V45)*($P$2:$P$209="Resale")*($S$2:$S$209<>""))),"")} | Y45: =IF(AND(P45="Long Term Rental",R45>0),Q45/R45,"") | Z45: =COUNTIFS($M$2:$M$209,U45,$P$2:$P$209,"Long Term Rental") -> 0 | AA45: {=IF(Z45=0,"",MEDIAN(_xlfn._xlws.FILTER($Y$2:$Y$209,($M$2:$M$209=U45)*($N$2:$N$209=V45)*($P$2:$P$209="Long Term Rental")*($Y$2:$Y$209<>""),"")))} | AB45: =IF(AND(V45="Villa",X45<>"",AA45<>""),(AA45*12/X45)*100,"") | AC45: {=IFERROR(MEDIAN(_xlfn._xlws.FILTER($Q$2:$Q$209,($M$2:$M$209=U45)*($P$2:$P$209="Short Term Rental")*($Q$2:$Q$209<>""))),"")}
A46: K0045 | B46: 4BHK Bungalow for sale in Neral | C46: Neral | D46: Bungalow | E46: 4BHK | F46: 3018 | G46: sqft | H46: 1.19 | I46: Crore | J46: One-time | K46: Active | M46: =_xlfn.XLOOKUP(TRIM(C46),MAPPING!A:A,MAPPING!B:B,"CHECK") -> Neral | N46: =_xlfn.XLOOKUP(D46,MAPPING!G:G,MAPPING!H:H,"CHECK") -> Villa | O46: =_xlfn.XLOOKUP(E46,MAPPING!J:J,MAPPING!K:K,"CHECK") -> 4 BHK | P46: =_xlfn.XLOOKUP(J46,MAPPING!M:M,MAPPING!N:N,"CHECK") -> Resale | Q46: =IF(I46="INR",H46,IF(I46="Lakh",H46*100000,IF(I46="Crore",H46*10000000,IF(I46="Thousand",H46*1000,"")))) -> 11900000 | R46: =IF(G46="sqft",F46,IF(G46="sqyd",F46*9,IF(G46="acre",F46*43560,IF(G46="guntha",F46*1089,IF(G46="hectare",F46*107639.1,""))))) -> 3018 | S46: =IF(AND(P46="Resale",R46>0),Q46/R46,"") -> 3943.0086 | W46: =COUNTIFS($M$2:$M$209,U46,$N$2:$N$209,V46,$P$2:$P$209,"Resale") -> 0 | X46: {=IFERROR(MEDIAN(_xlfn._xlws.FILTER($S$2:$S$209,($M$2:$M$209=U46)*($N$2:$N$209=V46)*($P$2:$P$209="Resale")*($S$2:$S$209<>""))),"")} | Y46: =IF(AND(P46="Long Term Rental",R46>0),Q46/R46,"") | Z46: =COUNTIFS($M$2:$M$209,U46,$P$2:$P$209,"Long Term Rental") -> 0 | AA46: {=IF(Z46=0,"",MEDIAN(_xlfn._xlws.FILTER($Y$2:$Y$209,($M$2:$M$209=U46)*($N$2:$N$209=V46)*($P$2:$P$209="Long Term Rental")*($Y$2:$Y$209<>""),"")))} | AB46: =IF(AND(V46="Villa",X46<>"",AA46<>""),(AA46*12/X46)*100,"") | AC46: {=IFERROR(MEDIAN(_xlfn._xlws.FILTER($Q$2:$Q$209,($M$2:$M$209=U46)*($P$2:$P$209="Short Term Rental")*($Q$2:$Q$209<>""))),"")}
A47: K0046 | B47: 2BHK Independent House for sale in Near Neral Station | C47: Near Neral Station | D47: Independent House | E47: 2BHK | F47: 2321 | G47: sqft | H47: 84.04 | I47: Lakh | J47: One-time | K47: Active | M47: =_xlfn.XLOOKUP(TRIM(C47),MAPPING!A:A,MAPPING!B:B,"CHECK") -> Neral | N47: =_xlfn.XLOOKUP(D47,MAPPING!G:G,MAPPING!H:H,"CHECK") -> Villa | O47: =_xlfn.XLOOKUP(E47,MAPPING!J:J,MAPPING!K:K,"CHECK") -> 2 BHK | P47: =_xlfn.XLOOKUP(J47,MAPPING!M:M,MAPPING!N:N,"CHECK") -> Resale | Q47: =IF(I47="INR",H47,IF(I47="Lakh",H47*100000,IF(I47="Crore",H47*10000000,IF(I47="Thousand",H47*1000,"")))) -> 8404000 | R47: =IF(G47="sqft",F47,IF(G47="sqyd",F47*9,IF(G47="acre",F47*43560,IF(G47="guntha",F47*1089,IF(G47="hectare",F47*107639.1,""))))) -> 2321 | S47: =IF(AND(P47="Resale",R47>0),Q47/R47,"") -> 3620.8531 | W47: =COUNTIFS($M$2:$M$209,U47,$N$2:$N$209,V47,$P$2:$P$209,"Resale") -> 0 | X47: {=IFERROR(MEDIAN(_xlfn._xlws.FILTER($S$2:$S$209,($M$2:$M$209=U47)*($N$2:$N$209=V47)*($P$2:$P$209="Resale")*($S$2:$S$209<>""))),"")} | Y47: =IF(AND(P47="Long Term Rental",R47>0),Q47/R47,"") | Z47: =COUNTIFS($M$2:$M$209,U47,$P$2:$P$209,"Long Term Rental") -> 0 | AA47: {=IF(Z47=0,"",MEDIAN(_xlfn._xlws.FILTER($Y$2:$Y$209,($M$2:$M$209=U47)*($N$2:$N$209=V47)*($P$2:$P$209="Long Term Rental")*($Y$2:$Y$209<>""),"")))} | AB47: =IF(AND(V47="Villa",X47<>"",AA47<>""),(AA47*12/X47)*100,"") | AC47: {=IFERROR(MEDIAN(_xlfn._xlws.FILTER($Q$2:$Q$209,($M$2:$M$209=U47)*($P$2:$P$209="Short Term Rental")*($Q$2:$Q$209<>""))),"")}
A48: K0047 | B48: 3BR Bungalow for sale in Neral | C48: Neral | D48: Bungalow | E48: 3BR | F48: 2564 | G48: sqft | H48: 95.68 | I48: Lakh | J48: One-time | K48: Active | M48: =_xlfn.XLOOKUP(TRIM(C48),MAPPING!A:A,MAPPING!B:B,"CHECK") -> Neral | N48: =_xlfn.XLOOKUP(D48,MAPPING!G:G,MAPPING!H:H,"CHECK") -> Villa | O48: =_xlfn.XLOOKUP(E48,MAPPING!J:J,MAPPING!K:K,"CHECK") -> 3 BHK | P48: =_xlfn.XLOOKUP(J48,MAPPING!M:M,MAPPING!N:N,"CHECK") -> Resale | Q48: =IF(I48="INR",H48,IF(I48="Lakh",H48*100000,IF(I48="Crore",H48*10000000,IF(I48="Thousand",H48*1000,"")))) -> 9568000 | R48: =IF(G48="sqft",F48,IF(G48="sqyd",F48*9,IF(G48="acre",F48*43560,IF(G48="guntha",F48*1089,IF(G48="hectare",F48*107639.1,""))))) -> 2564 | S48: =IF(AND(P48="Resale",R48>0),Q48/R48,"") -> 3731.6693 | W48: =COUNTIFS($M$2:$M$209,U48,$N$2:$N$209,V48,$P$2:$P$209,"Resale") -> 0 | X48: {=IFERROR(MEDIAN(_xlfn._xlws.FILTER($S$2:$S$209,($M$2:$M$209=U48)*($N$2:$N$209=V48)*($P$2:$P$209="Resale")*($S$2:$S$209<>""))),"")} | Y48: =IF(AND(P48="Long Term Rental",R48>0),Q48/R48,"") | Z48: =COUNTIFS($M$2:$M$209,U48,$P$2:$P$209,"Long Term Rental") -> 0 | AA48: {=IF(Z48=0,"",MEDIAN(_xlfn._xlws.FILTER($Y$2:$Y$209,($M$2:$M$209=U48)*($N$2:$N$209=V48)*($P$2:$P$209="Long Term Rental")*($Y$2:$Y$209<>""),"")))} | AB48: =IF(AND(V48="Villa",X48<>"",AA48<>""),(AA48*12/X48)*100,"") | AC48: {=IFERROR(MEDIAN(_xlfn._xlws.FILTER($Q$2:$Q$209,($M$2:$M$209=U48)*($P$2:$P$209="Short Term Rental")*($Q$2:$Q$209<>""))),"")}
A49: K0048 | B49: 3BR Farmhouse for sale in Near Neral Station | C49: Near Neral Station | D49: Farmhouse | E49: 3BR | F49: 2120 | G49: sqft | H49: 76.92 | I49: Lakh | J49: One-time | K49: Active | M49: =_xlfn.XLOOKUP(TRIM(C49),MAPPING!A:A,MAPPING!B:B,"CHECK") -> Neral | N49: =_xlfn.XLOOKUP(D49,MAPPING!G:G,MAPPING!H:H,"CHECK") -> Villa | O49: =_xlfn.XLOOKUP(E49,MAPPING!J:J,MAPPING!K:K,"CHECK") -> 3 BHK | P49: =_xlfn.XLOOKUP(J49,MAPPING!M:M,MAPPING!N:N,"CHECK") -> Resale | Q49: =IF(I49="INR",H49,IF(I49="Lakh",H49*100000,IF(I49="Crore",H49*10000000,IF(I49="Thousand",H49*1000,"")))) -> 7692000 | R49: =IF(G49="sqft",F49,IF(G49="sqyd",F49*9,IF(G49="acre",F49*43560,IF(G49="guntha",F49*1089,IF(G49="hectare",F49*107639.1,""))))) -> 2120 | S49: =IF(AND(P49="Resale",R49>0),Q49/R49,"") -> 3628.3019 | W49: =COUNTIFS($M$2:$M$209,U49,$N$2:$N$209,V49,$P$2:$P$209,"Resale") -> 0 | X49: {=IFERROR(MEDIAN(_xlfn._xlws.FILTER($S$2:$S$209,($M$2:$M$209=U49)*($N$2:$N$209=V49)*($P$2:$P$209="Resale")*($S$2:$S$209<>""))),"")} | Y49: =IF(AND(P49="Long Term Rental",R49>0),Q49/R49,"") | Z49: =COUNTIFS($M$2:$M$209,U49,$P$2:$P$209,"Long Term Rental") -> 0 | AA49: {=IF(Z49=0,"",MEDIAN(_xlfn._xlws.FILTER($Y$2:$Y$209,($M$2:$M$209=U49)*($N$2:$N$209=V49)*($P$2:$P$209="Long Term Rental")*($Y$2:$Y$209<>""),"")))} | AB49: =IF(AND(V49="Villa",X49<>"",AA49<>""),(AA49*12/X49)*100,"") | AC49: {=IFERROR(MEDIAN(_xlfn._xlws.FILTER($Q$2:$Q$209,($M$2:$M$209=U49)*($P$2:$P$209="Short Term Rental")*($Q$2:$Q$209<>""))),"")}
A50: K0049 | B50: Farm Land for sale in Neral Rd | C50: Neral Rd | D50: Farm Land | E50: NA | F50: 5831 | G50: sqft | H50: 9.22 | I50: Lakh | J50: One-time | K50: Sold | M50: =_xlfn.XLOOKUP(TRIM(C50),MAPPING!A:A,MAPPING!B:B,"CHECK") -> Neral | N50: =_xlfn.XLOOKUP(D50,MAPPING!G:G,MAPPING!H:H,"CHECK") -> Farmland | O50: =_xlfn.XLOOKUP(E50,MAPPING!J:J,MAPPING!K:K,"CHECK") -> NA | P50: =_xlfn.XLOOKUP(J50,MAPPING!M:M,MAPPING!N:N,"CHECK") -> Resale | Q50: =IF(I50="INR",H50,IF(I50="Lakh",H50*100000,IF(I50="Crore",H50*10000000,IF(I50="Thousand",H50*1000,"")))) -> 922000 | R50: =IF(G50="sqft",F50,IF(G50="sqyd",F50*9,IF(G50="acre",F50*43560,IF(G50="guntha",F50*1089,IF(G50="hectare",F50*107639.1,""))))) -> 5831 | S50: =IF(AND(P50="Resale",R50>0),Q50/R50,"") -> 158.12039 | W50: =COUNTIFS($M$2:$M$209,U50,$N$2:$N$209,V50,$P$2:$P$209,"Resale") -> 0 | X50: {=IFERROR(MEDIAN(_xlfn._xlws.FILTER($S$2:$S$209,($M$2:$M$209=U50)*($N$2:$N$209=V50)*($P$2:$P$209="Resale")*($S$2:$S$209<>""))),"")} | Y50: =IF(AND(P50="Long Term Rental",R50>0),Q50/R50,"") | Z50: =COUNTIFS($M$2:$M$209,U50,$P$2:$P$209,"Long Term Rental") -> 0 | AA50: {=IF(Z50=0,"",MEDIAN(_xlfn._xlws.FILTER($Y$2:$Y$209,($M$2:$M$209=U50)*($N$2:$N$209=V50)*($P$2:$P$209="Long Term Rental")*($Y$2:$Y$209<>""),"")))} | AB50: =IF(AND(V50="Villa",X50<>"",AA50<>""),(AA50*12/X50)*100,"") | AC50: {=IFERROR(MEDIAN(_xlfn._xlws.FILTER($Q$2:$Q$209,($M$2:$M$209=U50)*($P$2:$P$209="Short Term Rental")*($Q$2:$Q$209<>""))),"")}
A51: K0050 | B51: Plot for sale in Near Neral Station | C51: Near Neral Station | D51: Plot | E51: NA | F51: 26.1 | G51: guntha | H51: 2.72 | I51: Crore | J51: One-time | K51: Sold | M51: =_xlfn.XLOOKUP(TRIM(C51),MAPPING!A:A,MAPPING!B:B,"CHECK") -> Neral | N51: =_xlfn.XLOOKUP(D51,MAPPING!G:G,MAPPING!H:H,"CHECK") -> Plot | O51: =_xlfn.XLOOKUP(E51,MAPPING!J:J,MAPPING!K:K,"CHECK") -> NA | P51: =_xlfn.XLOOKUP(J51,MAPPING!M:M,MAPPING!N:N,"CHECK") -> Resale | Q51: =IF(I51="INR",H51,IF(I51="Lakh",H51*100000,IF(I51="Crore",H51*10000000,IF(I51="Thousand",H51*1000,"")))) -> 27200000 | R51: =IF(G51="sqft",F51,IF(G51="sqyd",F51*9,IF(G51="acre",F51*43560,IF(G51="guntha",F51*1089,IF(G51="hectare",F51*107639.1,""))))) -> 28422.9 | S51: =IF(AND(P51="Resale",R51>0),Q51/R51,"") -> 956.97483 | W51: =COUNTIFS($M$2:$M$209,U51,$N$2:$N$209,V51,$P$2:$P$209,"Resale") -> 0 | X51: {=IFERROR(MEDIAN(_xlfn._xlws.FILTER($S$2:$S$209,($M$2:$M$209=U51)*($N$2:$N$209=V51)*($P$2:$P$209="Resale")*($S$2:$S$209<>""))),"")} | Y51: =IF(AND(P51="Long Term Rental",R51>0),Q51/R51,"") | Z51: =COUNTIFS($M$2:$M$209,U51,$P$2:$P$209,"Long Term Rental") -> 0 | AA51: {=IF(Z51=0,"",MEDIAN(_xlfn._xlws.FILTER($Y$2:$Y$209,($M$2:$M$209=U51)*($N$2:$N$209=V51)*($P$2:$P$209="Long Term Rental")*($Y$2:$Y$209<>""),"")))} | AB51: =IF(AND(V51="Villa",X51<>"",AA51<>""),(AA51*12/X51)*100,"") | AC51: {=IFERROR(MEDIAN(_xlfn._xlws.FILTER($Q$2:$Q$209,($M$2:$M$209=U51)*($P$2:$P$209="Short Term Rental")*($Q$2:$Q$209<>""))),"")}
A52: K0051 | B52: Farm Land for sale in Neral Rd | C52: Neral Rd | D52: Farm Land | E52: NA | F52: 18.6 | G52: guntha | H52: 30.83 | I52: Lakh | J52: One-time | K52: Sold | M52: =_xlfn.XLOOKUP(TRIM(C52),MAPPING!A:A,MAPPING!B:B,"CHECK") -> Neral | N52: =_xlfn.XLOOKUP(D52,MAPPING!G:G,MAPPING!H:H,"CHECK") -> Farmland | O52: =_xlfn.XLOOKUP(E52,MAPPING!J:J,MAPPING!K:K,"CHECK") -> NA | P52: =_xlfn.XLOOKUP(J52,MAPPING!M:M,MAPPING!N:N,"CHECK") -> Resale | Q52: =IF(I52="INR",H52,IF(I52="Lakh",H52*100000,IF(I52="Crore",H52*10000000,IF(I52="Thousand",H52*1000,"")))) -> 3083000 | R52: =IF(G52="sqft",F52,IF(G52="sqyd",F52*9,IF(G52="acre",F52*43560,IF(G52="guntha",F52*1089,IF(G52="hectare",F52*107639.1,""))))) -> 20255.4 | S52: =IF(AND(P52="Resale",R52>0),Q52/R52,"") -> 152.20633 | W52: =COUNTIFS($M$2:$M$209,U52,$N$2:$N$209,V52,$P$2:$P$209,"Resale") -> 0 | X52: {=IFERROR(MEDIAN(_xlfn._xlws.FILTER($S$2:$S$209,($M$2:$M$209=U52)*($N$2:$N$209=V52)*($P$2:$P$209="Resale")*($S$2:$S$209<>""))),"")} | Y52: =IF(AND(P52="Long Term Rental",R52>0),Q52/R52,"") | Z52: =COUNTIFS($M$2:$M$209,U52,$P$2:$P$209,"Long Term Rental") -> 0 | AA52: {=IF(Z52=0,"",MEDIAN(_xlfn._xlws.FILTER($Y$2:$Y$209,($M$2:$M$209=U52)*($N$2:$N$209=V52)*($P$2:$P$209="Long Term Rental")*($Y$2:$Y$209<>""),"")))} | AB52: =IF(AND(V52="Villa",X52<>"",AA52<>""),(AA52*12/X52)*100,"") | AC52: {=IFERROR(MEDIAN(_xlfn._xlws.FILTER($Q$2:$Q$209,($M$2:$M$209=U52)*($P$2:$P$209="Short Term Rental")*($Q$2:$Q$209<>""))),"")}
A53: K0052 | B53: 2 BHK Villa for sale in Neral | C53: Neral | D53: Villa | E53: 2 BHK | F53: 1722 | G53: sqft | H53: 70.15 | I53: Lakh | J53: One-time | K53: Active | M53: =_xlfn.XLOOKUP(TRIM(C53),MAPPING!A:A,MAPPING!B:B,"CHECK") -> Neral | N53: =_xlfn.XLOOKUP(D53,MAPPING!G:G,MAPPING!H:H,"CHECK") -> Villa | O53: =_xlfn.XLOOKUP(E53,MAPPING!J:J,MAPPING!K:K,"CHECK") -> 2 BHK | P53: =_xlfn.XLOOKUP(J53,MAPPING!M:M,MAPPING!N:N,"CHECK") -> Resale | Q53: =IF(I53="INR",H53,IF(I53="Lakh",H53*100000,IF(I53="Crore",H53*10000000,IF(I53="Thousand",H53*1000,"")))) -> 7015000 | R53: =IF(G53="sqft",F53,IF(G53="sqyd",F53*9,IF(G53="acre",F53*43560,IF(G53="guntha",F53*1089,IF(G53="hectare",F53*107639.1,""))))) -> 1722 | S53: =IF(AND(P53="Resale",R53>0),Q53/R53,"") -> 4073.7515 | W53: =COUNTIFS($M$2:$M$209,U53,$N$2:$N$209,V53,$P$2:$P$209,"Resale") -> 0 | X53: {=IFERROR(MEDIAN(_xlfn._xlws.FILTER($S$2:$S$209,($M$2:$M$209=U53)*($N$2:$N$209=V53)*($P$2:$P$209="Resale")*($S$2:$S$209<>""))),"")} | Y53: =IF(AND(P53="Long Term Rental",R53>0),Q53/R53,"") | Z53: =COUNTIFS($M$2:$M$209,U53,$P$2:$P$209,"Long Term Rental") -> 0 | AA53: {=IF(Z53=0,"",MEDIAN(_xlfn._xlws.FILTER($Y$2:$Y$209,($M$2:$M$209=U53)*($N$2:$N$209=V53)*($P$2:$P$209="Long Term Rental")*($Y$2:$Y$209<>""),"")))} | AB53: =IF(AND(V53="Villa",X53<>"",AA53<>""),(AA53*12/X53)*100,"") | AC53: {=IFERROR(MEDIAN(_xlfn._xlws.FILTER($Q$2:$Q$209,($M$2:$M$209=U53)*($P$2:$P$209="Short Term Rental")*($Q$2:$Q$209<>""))),"")}
A54: K0053 | B54: Farm for sale in Neral Rd | C54: Neral Rd | D54: Farm | E54: NA | F54: 8.7 | G54: guntha | H54: 14.73 | I54: Lakh | J54: One-time | K54: Active | M54: =_xlfn.XLOOKUP(TRIM(C54),MAPPING!A:A,MAPPING!B:B,"CHECK") -> Neral | N54: =_xlfn.XLOOKUP(D54,MAPPING!G:G,MAPPING!H:H,"CHECK") -> Farmland | O54: =_xlfn.XLOOKUP(E54,MAPPING!J:J,MAPPING!K:K,"CHECK") -> NA | P54: =_xlfn.XLOOKUP(J54,MAPPING!M:M,MAPPING!N:N,"CHECK") -> Resale | Q54: =IF(I54="INR",H54,IF(I54="Lakh",H54*100000,IF(I54="Crore",H54*10000000,IF(I54="Thousand",H54*1000,"")))) -> 1473000 | R54: =IF(G54="sqft",F54,IF(G54="sqyd",F54*9,IF(G54="acre",F54*43560,IF(G54="guntha",F54*1089,IF(G54="hectare",F54*107639.1,""))))) -> 9474.3 | S54: =IF(AND(P54="Resale",R54>0),Q54/R54,"") -> 155.47323 | W54: =COUNTIFS($M$2:$M$209,U54,$N$2:$N$209,V54,$P$2:$P$209,"Resale") -> 0 | X54: {=IFERROR(MEDIAN(_xlfn._xlws.FILTER($S$2:$S$209,($M$2:$M$209=U54)*($N$2:$N$209=V54)*($P$2:$P$209="Resale")*($S$2:$S$209<>""))),"")} | Y54: =IF(AND(P54="Long Term Rental",R54>0),Q54/R54,"") | Z54: =COUNTIFS($M$2:$M$209,U54,$P$2:$P$209,"Long Term Rental") -> 0 | AA54: {=IF(Z54=0,"",MEDIAN(_xlfn._xlws.FILTER($Y$2:$Y$209,($M$2:$M$209=U54)*($N$2:$N$209=V54)*($P$2:$P$209="Long Term Rental")*($Y$2:$Y$209<>""),"")))} | AB54: =IF(AND(V54="Villa",X54<>"",AA54<>""),(AA54*12/X54)*100,"") | AC54: {=IFERROR(MEDIAN(_xlfn._xlws.FILTER($Q$2:$Q$209,($M$2:$M$209=U54)*($P$2:$P$209="Short Term Rental")*($Q$2:$Q$209<>""))),"")}
A55: K0054 | B55: 4BHK Row House for sale in Neral | C55: Neral | D55: Row House | E55: 4BHK | F55: 3088 | G55: sqft | H55: 1.07 | I55: Crore | J55: One-time | K55: Sold | M55: =_xlfn.XLOOKUP(TRIM(C55),MAPPING!A:A,MAPPING!B:B,"CHECK") -> Neral | N55: =_xlfn.XLOOKUP(D55,MAPPING!G:G,MAPPING!H:H,"CHECK") -> Villa | O55: =_xlfn.XLOOKUP(E55,MAPPING!J:J,MAPPING!K:K,"CHECK") -> 4 BHK | P55: =_xlfn.XLOOKUP(J55,MAPPING!M:M,MAPPING!N:N,"CHECK") -> Resale | Q55: =IF(I55="INR",H55,IF(I55="Lakh",H55*100000,IF(I55="Crore",H55*10000000,IF(I55="Thousand",H55*1000,"")))) -> 10700000 | R55: =IF(G55="sqft",F55,IF(G55="sqyd",F55*9,IF(G55="acre",F55*43560,IF(G55="guntha",F55*1089,IF(G55="hectare",F55*107639.1,""))))) -> 3088 | S55: =IF(AND(P55="Resale",R55>0),Q55/R55,"") -> 3465.0259 | W55: =COUNTIFS($M$2:$M$209,U55,$N$2:$N$209,V55,$P$2:$P$209,"Resale") -> 0 | X55: {=IFERROR(MEDIAN(_xlfn._xlws.FILTER($S$2:$S$209,($M$2:$M$209=U55)*($N$2:$N$209=V55)*($P$2:$P$209="Resale")*($S$2:$S$209<>""))),"")} | Y55: =IF(AND(P55="Long Term Rental",R55>0),Q55/R55,"") | Z55: =COUNTIFS($M$2:$M$209,U55,$P$2:$P$209,"Long Term Rental") -> 0 | AA55: {=IF(Z55=0,"",MEDIAN(_xlfn._xlws.FILTER($Y$2:$Y$209,($M$2:$M$209=U55)*($N$2:$N$209=V55)*($P$2:$P$209="Long Term Rental")*($Y$2:$Y$209<>""),"")))} | AB55: =IF(AND(V55="Villa",X55<>"",AA55<>""),(AA55*12/X55)*100,"") | AC55: {=IFERROR(MEDIAN(_xlfn._xlws.FILTER($Q$2:$Q$209,($M$2:$M$209=U55)*($P$2:$P$209="Short Term Rental")*($Q$2:$Q$209<>""))),"")}
... A65: K0064 | B65: NA Plot for sale in Near Neral Station | C65: Near Neral Station | D65: NA Plot | E65: NA | F65: 3874 | G65: sqft | H65: 33.39 | I65: Lakh | J65: One-time | K65: Active | M65: =_xlfn.XLOOKUP(TRIM(C65),MAPPING!A:A,MAPPING!B:B,"CHECK") -> Neral | N65: =_xlfn.XLOOKUP(D65,MAPPING!G:G,MAPPING!H:H,"CHECK") -> Plot | O65: =_xlfn.XLOOKUP(E65,MAPPING!J:J,MAPPING!K:K,"CHECK") -> NA | P65: =_xlfn.XLOOKUP(J65,MAPPING!M:M,MAPPING!N:N,"CHECK") -> Resale | Q65: =IF(I65="INR",H65,IF(I65="Lakh",H65*100000,IF(I65="Crore",H65*10000000,IF(I65="Thousand",H65*1000,"")))) -> 3339000 | R65: =IF(G65="sqft",F65,IF(G65="sqyd",F65*9,IF(G65="acre",F65*43560,IF(G65="guntha",F65*1089,IF(G65="hectare",F65*107639.1,""))))) -> 3874 | S65: =IF(AND(P65="Resale",R65>0),Q65/R65,"") -> 861.89985 | W65: =COUNTIFS($M$2:$M$209,U65,$N$2:$N$209,V65,$P$2:$P$209,"Resale") -> 0 | X65: {=IFERROR(MEDIAN(_xlfn._xlws.FILTER($S$2:$S$209,($M$2:$M$209=U65)*($N$2:$N$209=V65)*($P$2:$P$209="Resale")*($S$2:$S$209<>""))),"")} | Y65: =IF(AND(P65="Long Term Rental",R65>0),Q65/R65,"") | Z65: =COUNTIFS($M$2:$M$209,U65,$P$2:$P$209,"Long Term Rental") -> 0 | AA65: {=IF(Z65=0,"",MEDIAN(_xlfn._xlws.FILTER($Y$2:$Y$209,($M$2:$M$209=U65)*($N$2:$N$209=V65)*($P$2:$P$209="Long Term Rental")*($Y$2:$Y$209<>""),"")))} | AB65: =IF(AND(V65="Villa",X65<>"",AA65<>""),(AA65*12/X65)*100,"") | AC65: {=IFERROR(MEDIAN(_xlfn._xlws.FILTER($Q$2:$Q$209,($M$2:$M$209=U65)*($P$2:$P$209="Short Term Rental")*($Q$2:$Q$209<>""))),"")}
A66: K0065 | B66: Land Parcel for sale in Near Neral Station | C66: Near Neral Station | D66: Land Parcel | E66: NA | F66: 2.55 | G66: acre | I66: Crore | J66: One-time | K66: Price on Request | M66: =_xlfn.XLOOKUP(TRIM(C66),MAPPING!A:A,MAPPING!B:B,"CHECK") -> Neral | N66: =_xlfn.XLOOKUP(D66,MAPPING!G:G,MAPPING!H:H,"CHECK") -> Plot | O66: =_xlfn.XLOOKUP(E66,MAPPING!J:J,MAPPING!K:K,"CHECK") -> NA | P66: =_xlfn.XLOOKUP(J66,MAPPING!M:M,MAPPING!N:N,"CHECK") -> Resale | Q66: =IF(I66="INR",H66,IF(I66="Lakh",H66*100000,IF(I66="Crore",H66*10000000,IF(I66="Thousand",H66*1000,"")))) -> 0 | R66: =IF(G66="sqft",F66,IF(G66="sqyd",F66*9,IF(G66="acre",F66*43560,IF(G66="guntha",F66*1089,IF(G66="hectare",F66*107639.1,""))))) -> 111078 | S66: =IF(AND(P66="Resale",R66>0),Q66/R66,"") -> 0 | W66: =COUNTIFS($M$2:$M$209,U66,$N$2:$N$209,V66,$P$2:$P$209,"Resale") -> 0 | X66: {=IFERROR(MEDIAN(_xlfn._xlws.FILTER($S$2:$S$209,($M$2:$M$209=U66)*($N$2:$N$209=V66)*($P$2:$P$209="Resale")*($S$2:$S$209<>""))),"")} | Y66: =IF(AND(P66="Long Term Rental",R66>0),Q66/R66,"") | Z66: =COUNTIFS($M$2:$M$209,U66,$P$2:$P$209,"Long Term Rental") -> 0 | AA66: {=IF(Z66=0,"",MEDIAN(_xlfn._xlws.FILTER($Y$2:$Y$209,($M$2:$M$209=U66)*($N$2:$N$209=V66)*($P$2:$P$209="Long Term Rental")*($Y$2:$Y$209<>""),"")))} | AB66: =IF(AND(V66="Villa",X66<>"",AA66<>""),(AA66*12/X66)*100,"") | AC66: {=IFERROR(MEDIAN(_xlfn._xlws.FILTER($Q$2:$Q$209,($M$2:$M$209=U66)*($P$2:$P$209="Short Term Rental")*($Q$2:$Q$209<>""))),"")}
A67: K0066 | B67: Agricultural Land for sale in Neral | C67: Neral | D67: Agricultural Land | E67: NA | F67: 7667 | G67: sqft | H67: 11.19 | I67: Lakh | J67: One-time | K67: Active | M67: =_xlfn.XLOOKUP(TRIM(C67),MAPPING!A:A,MAPPING!B:B,"CHECK") -> Neral | N67: =_xlfn.XLOOKUP(D67,MAPPING!G:G,MAPPING!H:H,"CHECK") -> Farmland | O67: =_xlfn.XLOOKUP(E67,MAPPING!J:J,MAPPING!K:K,"CHECK") -> NA | P67: =_xlfn.XLOOKUP(J67,MAPPING!M:M,MAPPING!N:N,"CHECK") -> Resale | Q67: =IF(I67="INR",H67,IF(I67="Lakh",H67*100000,IF(I67="Crore",H67*10000000,IF(I67="Thousand",H67*1000,"")))) -> 1119000 | R67: =IF(G67="sqft",F67,IF(G67="sqyd",F67*9,IF(G67="acre",F67*43560,IF(G67="guntha",F67*1089,IF(G67="hectare",F67*107639.1,""))))) -> 7667 | S67: =IF(AND(P67="Resale",R67>0),Q67/R67,"") -> 145.95018 | W67: =COUNTIFS($M$2:$M$209,U67,$N$2:$N$209,V67,$P$2:$P$209,"Resale") -> 0 | X67: {=IFERROR(MEDIAN(_xlfn._xlws.FILTER($S$2:$S$209,($M$2:$M$209=U67)*($N$2:$N$209=V67)*($P$2:$P$209="Resale")*($S$2:$S$209<>""))),"")} | Y67: =IF(AND(P67="Long Term Rental",R67>0),Q67/R67,"") | Z67: =COUNTIFS($M$2:$M$209,U67,$P$2:$P$209,"Long Term Rental") -> 0 | AA67: {=IF(Z67=0,"",MEDIAN(_xlfn._xlws.FILTER($Y$2:$Y$209,($M$2:$M$209=U67)*($N$2:$N$209=V67)*($P$2:$P$209="Long Term Rental")*($Y$2:$Y$209<>""),"")))} | AB67: =IF(AND(V67="Villa",X67<>"",AA67<>""),(AA67*12/X67)*100,"") | AC67: {=IFERROR(MEDIAN(_xlfn._xlws.FILTER($Q$2:$Q$209,($M$2:$M$209=U67)*($P$2:$P$209="Short Term Rental")*($Q$2:$Q$209<>""))),"")}
A68: K0067 | B68: 4BHK Bungalow for rent in Neral | C68: Neral | D68: Bungalow | E68: 4BHK | F68: 1158 | G68: sqft | H68: 16400 | I68: INR | J68: Monthly | K68: Active | M68: =_xlfn.XLOOKUP(TRIM(C68),MAPPING!A:A,MAPPING!B:B,"CHECK") -> Neral | N68: =_xlfn.XLOOKUP(D68,MAPPING!G:G,MAPPING!H:H,"CHECK") -> Villa | O68: =_xlfn.XLOOKUP(E68,MAPPING!J:J,MAPPING!K:K,"CHECK") -> 4 BHK | P68: =_xlfn.XLOOKUP(J68,MAPPING!M:M,MAPPING!N:N,"CHECK") -> Long Term Rental | Q68: =IF(I68="INR",H68,IF(I68="Lakh",H68*100000,IF(I68="Crore",H68*10000000,IF(I68="Thousand",H68*1000,"")))) -> 16400 | R68: =IF(G68="sqft",F68,IF(G68="sqyd",F68*9,IF(G68="acre",F68*43560,IF(G68="guntha",F68*1089,IF(G68="hectare",F68*107639.1,""))))) -> 1158 | S68: =IF(AND(P68="Resale",R68>0),Q68/R68,"") | W68: =COUNTIFS($M$2:$M$209,U68,$N$2:$N$209,V68,$P$2:$P$209,"Resale") -> 0 | X68: {=IFERROR(MEDIAN(_xlfn._xlws.FILTER($S$2:$S$209,($M$2:$M$209=U68)*($N$2:$N$209=V68)*($P$2:$P$209="Resale")*($S$2:$S$209<>""))),"")} | Y68: =IF(AND(P68="Long Term Rental",R68>0),Q68/R68,"") -> 14.162349 | Z68: =COUNTIFS($M$2:$M$209,U68,$P$2:$P$209,"Long Term Rental") -> 0 | AA68: {=IF(Z68=0,"",MEDIAN(_xlfn._xlws.FILTER($Y$2:$Y$209,($M$2:$M$209=U68)*($N$2:$N$209=V68)*($P$2:$P$209="Long Term Rental")*($Y$2:$Y$209<>""),"")))} | AB68: =IF(AND(V68="Villa",X68<>"",AA68<>""),(AA68*12/X68)*100,"") | AC68: {=IFERROR(MEDIAN(_xlfn._xlws.FILTER($Q$2:$Q$209,($M$2:$M$209=U68)*($P$2:$P$209="Short Term Rental")*($Q$2:$Q$209<>""))),"")}
A69: K0068 | B69: 4BHK Villa for rent in Neral | C69: Neral | D69: Villa | E69: 4BHK | F69: 1667 | G69: sqft | H69: 20500 | I69: INR | J69: Monthly | K69: Active | M69: =_xlfn.XLOOKUP(TRIM(C69),MAPPING!A:A,MAPPING!B:B,"CHECK") -> Neral | N69: =_xlfn.XLOOKUP(D69,MAPPING!G:G,MAPPING!H:H,"CHECK") -> Villa | O69: =_xlfn.XLOOKUP(E69,MAPPING!J:J,MAPPING!K:K,"CHECK") -> 4 BHK | P69: =_xlfn.XLOOKUP(J69,MAPPING!M:M,MAPPING!N:N,"CHECK") -> Long Term Rental | Q69: =IF(I69="INR",H69,IF(I69="Lakh",H69*100000,IF(I69="Crore",H69*10000000,IF(I69="Thousand",H69*1000,"")))) -> 20500 | R69: =IF(G69="sqft",F69,IF(G69="sqyd",F69*9,IF(G69="acre",F69*43560,IF(G69="guntha",F69*1089,IF(G69="hectare",F69*107639.1,""))))) -> 1667 | S69: =IF(AND(P69="Resale",R69>0),Q69/R69,"") | W69: =COUNTIFS($M$2:$M$209,U69,$N$2:$N$209,V69,$P$2:$P$209,"Resale") -> 0 | X69: {=IFERROR(MEDIAN(_xlfn._xlws.FILTER($S$2:$S$209,($M$2:$M$209=U69)*($N$2:$N$209=V69)*($P$2:$P$209="Resale")*($S$2:$S$209<>""))),"")} | Y69: =IF(AND(P69="Long Term Rental",R69>0),Q69/R69,"") -> 12.29754 | Z69: =COUNTIFS($M$2:$M$209,U69,$P$2:$P$209,"Long Term Rental") -> 0 | AA69: {=IF(Z69=0,"",MEDIAN(_xlfn._xlws.FILTER($Y$2:$Y$209,($M$2:$M$209=U69)*($N$2:$N$209=V69)*($P$2:$P$209="Long Term Rental")*($Y$2:$Y$209<>""),"")))} | AB69: =IF(AND(V69="Villa",X69<>"",AA69<>""),(AA69*12/X69)*100,"") | AC69: {=IFERROR(MEDIAN(_xlfn._xlws.FILTER($Q$2:$Q$209,($M$2:$M$209=U69)*($P$2:$P$209="Short Term Rental")*($Q$2:$Q$209<>""))),"")}
A70: K0069 | B70: 3 BHK Villa for rent in Near Neral Station | C70: Near Neral Station | D70: Villa | E70: 3 BHK | F70: 1224 | G70: sqft | H70: 16000 | I70: INR | J70: Monthly | K70: Active | M70: =_xlfn.XLOOKUP(TRIM(C70),MAPPING!A:A,MAPPING!B:B,"CHECK") -> Neral | N70: =_xlfn.XLOOKUP(D70,MAPPING!G:G,MAPPING!H:H,"CHECK") -> Villa | O70: =_xlfn.XLOOKUP(E70,MAPPING!J:J,MAPPING!K:K,"CHECK") -> 3 BHK | P70: =_xlfn.XLOOKUP(J70,MAPPING!M:M,MAPPING!N:N,"CHECK") -> Long Term Rental | Q70: =IF(I70="INR",H70,IF(I70="Lakh",H70*100000,IF(I70="Crore",H70*10000000,IF(I70="Thousand",H70*1000,"")))) -> 16000 | R70: =IF(G70="sqft",F70,IF(G70="sqyd",F70*9,IF(G70="acre",F70*43560,IF(G70="guntha",F70*1089,IF(G70="hectare",F70*107639.1,""))))) -> 1224 | S70: =IF(AND(P70="Resale",R70>0),Q70/R70,"") | W70: =COUNTIFS($M$2:$M$209,U70,$N$2:$N$209,V70,$P$2:$P$209,"Resale") -> 0 | X70: {=IFERROR(MEDIAN(_xlfn._xlws.FILTER($S$2:$S$209,($M$2:$M$209=U70)*($N$2:$N$209=V70)*($P$2:$P$209="Resale")*($S$2:$S$209<>""))),"")} | Y70: =IF(AND(P70="Long Term Rental",R70>0),Q70/R70,"") -> 13.071895 | Z70: =COUNTIFS($M$2:$M$209,U70,$P$2:$P$209,"Long Term Rental") -> 0 | AA70: {=IF(Z70=0,"",MEDIAN(_xlfn._xlws.FILTER($Y$2:$Y$209,($M$2:$M$209=U70)*($N$2:$N$209=V70)*($P$2:$P$209="Long Term Rental")*($Y$2:$Y$209<>""),"")))} | AB70: =IF(AND(V70="Villa",X70<>"",AA70<>""),(AA70*12/X70)*100,"") | AC70: {=IFERROR(MEDIAN(_xlfn._xlws.FILTER($Q$2:$Q$209,($M$2:$M$209=U70)*($P$2:$P$209="Short Term Rental")*($Q$2:$Q$209<>""))),"")}
A71: K0070 | B71: 3BR Bungalow for rent in Near Neral Station | C71: Near Neral Station | D71: Bungalow | E71: 3BR | F71: 1206 | G71: sqft | H71: 16000 | I71: INR | J71: Monthly | K71: Active | M71: =_xlfn.XLOOKUP(TRIM(C71),MAPPING!A:A,MAPPING!B:B,"CHECK") -> Neral | N71: =_xlfn.XLOOKUP(D71,MAPPING!G:G,MAPPING!H:H,"CHECK") -> Villa | O71: =_xlfn.XLOOKUP(E71,MAPPING!J:J,MAPPING!K:K,"CHECK") -> 3 BHK | P71: =_xlfn.XLOOKUP(J71,MAPPING!M:M,MAPPING!N:N,"CHECK") -> Long Term Rental | Q71: =IF(I71="INR",H71,IF(I71="Lakh",H71*100000,IF(I71="Crore",H71*10000000,IF(I71="Thousand",H71*1000,"")))) -> 16000 | R71: =IF(G71="sqft",F71,IF(G71="sqyd",F71*9,IF(G71="acre",F71*43560,IF(G71="guntha",F71*1089,IF(G71="hectare",F71*107639.1,""))))) -> 1206 | S71: =IF(AND(P71="Resale",R71>0),Q71/R71,"") | W71: =COUNTIFS($M$2:$M$209,U71,$N$2:$N$209,V71,$P$2:$P$209,"Resale") -> 0 | X71: {=IFERROR(MEDIAN(_xlfn._xlws.FILTER($S$2:$S$209,($M$2:$M$209=U71)*($N$2:$N$209=V71)*($P$2:$P$209="Resale")*($S$2:$S$209<>""))),"")} | Y71: =IF(AND(P71="Long Term Rental",R71>0),Q71/R71,"") -> 13.266998 | Z71: =COUNTIFS($M$2:$M$209,U71,$P$2:$P$209,"Long Term Rental") -> 0 | AA71: {=IF(Z71=0,"",MEDIAN(_xlfn._xlws.FILTER($Y$2:$Y$209,($M$2:$M$209=U71)*($N$2:$N$209=V71)*($P$2:$P$209="Long Term Rental")*($Y$2:$Y$209<>""),"")))} | AB71: =IF(AND(V71="Villa",X71<>"",AA71<>""),(AA71*12/X71)*100,"") | AC71: {=IFERROR(MEDIAN(_xlfn._xlws.FILTER($Q$2:$Q$209,($M$2:$M$209=U71)*($P$2:$P$209="Short Term Rental")*($Q$2:$Q$209<>""))),"")}
A72: K0071 | B72: 3BHK Row House for rent in Near Neral Station | C72: Near Neral Station | D72: Row House | E72: 3BHK | F72: 1976 | G72: sqft | H72: 27500 | I72: INR | J72: Monthly | K72: Active | M72: =_xlfn.XLOOKUP(TRIM(C72),MAPPING!A:A,MAPPING!B:B,"CHECK") -> Neral | N72: =_xlfn.XLOOKUP(D72,MAPPING!G:G,MAPPING!H:H,"CHECK") -> Villa | O72: =_xlfn.XLOOKUP(E72,MAPPING!J:J,MAPPING!K:K,"CHECK") -> 3 BHK | P72: =_xlfn.XLOOKUP(J72,MAPPING!M:M,MAPPING!N:N,"CHECK") -> Long Term Rental | Q72: =IF(I72="INR",H72,IF(I72="Lakh",H72*100000,IF(I72="Crore",H72*10000000,IF(I72="Thousand",H72*1000,"")))) -> 27500 | R72: =IF(G72="sqft",F72,IF(G72="sqyd",F72*9,IF(G72="acre",F72*43560,IF(G72="guntha",F72*1089,IF(G72="hectare",F72*107639.1,""))))) -> 1976 | S72: =IF(AND(P72="Resale",R72>0),Q72/R72,"") | W72: =COUNTIFS($M$2:$M$209,U72,$N$2:$N$209,V72,$P$2:$P$209,"Resale") -> 0 | X72: {=IFERROR(MEDIAN(_xlfn._xlws.FILTER($S$2:$S$209,($M$2:$M$209=U72)*($N$2:$N$209=V72)*($P$2:$P$209="Resale")*($S$2:$S$209<>""))),"")} | Y72: =IF(AND(P72="Long Term Rental",R72>0),Q72/R72,"") -> 13.917004 | Z72: =COUNTIFS($M$2:$M$209,U72,$P$2:$P$209,"Long Term Rental") -> 0 | AA72: {=IF(Z72=0,"",MEDIAN(_xlfn._xlws.FILTER($Y$2:$Y$209,($M$2:$M$209=U72)*($N$2:$N$209=V72)*($P$2:$P$209="Long Term Rental")*($Y$2:$Y$209<>""),"")))} | AB72: =IF(AND(V72="Villa",X72<>"",AA72<>""),(AA72*12/X72)*100,"") | AC72: {=IFERROR(MEDIAN(_xlfn._xlws.FILTER($Q$2:$Q$209,($M$2:$M$209=U72)*($P$2:$P$209="Short Term Rental")*($Q$2:$Q$209<>""))),"")}
A73: K0072 | B73: 3BR Bungalow for rent in Neral Rd | C73: Neral Rd | D73: Bungalow | E73: 3BR | F73: 1063 | G73: sqft | H73: 12900 | I73: INR | J73: Monthly | K73: Active | M73: =_xlfn.XLOOKUP(TRIM(C73),MAPPING!A:A,MAPPING!B:B,"CHECK") -> Neral | N73: =_xlfn.XLOOKUP(D73,MAPPING!G:G,MAPPING!H:H,"CHECK") -> Villa | O73: =_xlfn.XLOOKUP(E73,MAPPING!J:J,MAPPING!K:K,"CHECK") -> 3 BHK | P73: =_xlfn.XLOOKUP(J73,MAPPING!M:M,MAPPING!N:N,"CHECK") -> Long Term Rental | Q73: =IF(I73="INR",H73,IF(I73="Lakh",H73*100000,IF(I73="Crore",H73*10000000,IF(I73="Thousand",H73*1000,"")))) -> 12900 | R73: =IF(G73="sqft",F73,IF(G73="sqyd",F73*9,IF(G73="acre",F73*43560,IF(G73="guntha",F73*1089,IF(G73="hectare",F73*107639.1,""))))) -> 1063 | S73: =IF(AND(P73="Resale",R73>0),Q73/R73,"") | W73: =COUNTIFS($M$2:$M$209,U73,$N$2:$N$209,V73,$P$2:$P$209,"Resale") -> 0 | X73: {=IFERROR(MEDIAN(_xlfn._xlws.FILTER($S$2:$S$209,($M$2:$M$209=U73)*($N$2:$N$209=V73)*($P$2:$P$209="Resale")*($S$2:$S$209<>""))),"")} | Y73: =IF(AND(P73="Long Term Rental",R73>0),Q73/R73,"") -> 12.135466 | Z73: =COUNTIFS($M$2:$M$209,U73,$P$2:$P$209,"Long Term Rental") -> 0 | AA73: {=IF(Z73=0,"",MEDIAN(_xlfn._xlws.FILTER($Y$2:$Y$209,($M$2:$M$209=U73)*($N$2:$N$209=V73)*($P$2:$P$209="Long Term Rental")*($Y$2:$Y$209<>""),"")))} | AB73: =IF(AND(V73="Villa",X73<>"",AA73<>""),(AA73*12/X73)*100,"") | AC73: {=IFERROR(MEDIAN(_xlfn._xlws.FILTER($Q$2:$Q$209,($M$2:$M$209=U73)*($P$2:$P$209="Short Term Rental")*($Q$2:$Q$209<>""))),"")}
A74: K0073 | B74: 2BHK Farmhouse for rent in Neral | C74: Neral | D74: Farmhouse | E74: 2BHK | F74: 1356 | G74: sqft | H74: 17200 | I74: INR | J74: Monthly | K74: Active | M74: =_xlfn.XLOOKUP(TRIM(C74),MAPPING!A:A,MAPPING!B:B,"CHECK") -> Neral | N74: =_xlfn.XLOOKUP(D74,MAPPING!G:G,MAPPING!H:H,"CHECK") -> Villa | O74: =_xlfn.XLOOKUP(E74,MAPPING!J:J,MAPPING!K:K,"CHECK") -> 2 BHK | P74: =_xlfn.XLOOKUP(J74,MAPPING!M:M,MAPPING!N:N,"CHECK") -> Long Term Rental | Q74: =IF(I74="INR",H74,IF(I74="Lakh",H74*100000,IF(I74="Crore",H74*10000000,IF(I74="Thousand",H74*1000,"")))) -> 17200 | R74: =IF(G74="sqft",F74,IF(G74="sqyd",F74*9,IF(G74="acre",F74*43560,IF(G74="guntha",F74*1089,IF(G74="hectare",F74*107639.1,""))))) -> 1356 | S74: =IF(AND(P74="Resale",R74>0),Q74/R74,"") | W74: =COUNTIFS($M$2:$M$209,U74,$N$2:$N$209,V74,$P$2:$P$209,"Resale") -> 0 | X74: {=IFERROR(MEDIAN(_xlfn._xlws.FILTER($S$2:$S$209,($M$2:$M$209=U74)*($N$2:$N$209=V74)*($P$2:$P$209="Resale")*($S$2:$S$209<>""))),"")} | Y74: =IF(AND(P74="Long Term Rental",R74>0),Q74/R74,"") -> 12.684366 | Z74: =COUNTIFS($M$2:$M$209,U74,$P$2:$P$209,"Long Term Rental") -> 0 | AA74: {=IF(Z74=0,"",MEDIAN(_xlfn._xlws.FILTER($Y$2:$Y$209,($M$2:$M$209=U74)*($N$2:$N$209=V74)*($P$2:$P$209="Long Term Rental")*($Y$2:$Y$209<>""),"")))} | AB74: =IF(AND(V74="Villa",X74<>"",AA74<>""),(AA74*12/X74)*100,"") | AC74: {=IFERROR(MEDIAN(_xlfn._xlws.FILTER($Q$2:$Q$209,($M$2:$M$209=U74)*($P$2:$P$209="Short Term Rental")*($Q$2:$Q$209<>""))),"")}
A75: K0074 | B75: 3 BHK Row House for rent in Neral Village | C75: Neral Village | D75: Row House | E75: 3 BHK | F75: 1567 | G75: sqft | H75: 20200 | I75: INR | J75: Monthly | K75: Active | M75: =_xlfn.XLOOKUP(TRIM(C75),MAPPING!A:A,MAPPING!B:B,"CHECK") -> Neral | N75: =_xlfn.XLOOKUP(D75,MAPPING!G:G,MAPPING!H:H,"CHECK") -> Villa | O75: =_xlfn.XLOOKUP(E75,MAPPING!J:J,MAPPING!K:K,"CHECK") -> 3 BHK | P75: =_xlfn.XLOOKUP(J75,MAPPING!M:M,MAPPING!N:N,"CHECK") -> Long Term Rental | Q75: =IF(I75="INR",H75,IF(I75="Lakh",H75*100000,IF(I75="Crore",H75*10000000,IF(I75="Thousand",H75*1000,"")))) -> 20200 | R75: =IF(G75="sqft",F75,IF(G75="sqyd",F75*9,IF(G75="acre",F75*43560,IF(G75="guntha",F75*1089,IF(G75="hectare",F75*107639.1,""))))) -> 1567 | S75: =IF(AND(P75="Resale",R75>0),Q75/R75,"") | W75: =COUNTIFS($M$2:$M$209,U75,$N$2:$N$209,V75,$P$2:$P$209,"Resale") -> 0 | X75: {=IFERROR(MEDIAN(_xlfn._xlws.FILTER($S$2:$S$209,($M$2:$M$209=U75)*($N$2:$N$209=V75)*($P$2:$P$209="Resale")*($S$2:$S$209<>""))),"")} | Y75: =IF(AND(P75="Long Term Rental",R75>0),Q75/R75,"") -> 12.890874 | Z75: =COUNTIFS($M$2:$M$209,U75,$P$2:$P$209,"Long Term Rental") -> 0 | AA75: {=IF(Z75=0,"",MEDIAN(_xlfn._xlws.FILTER($Y$2:$Y$209,($M$2:$M$209=U75)*($N$2:$N$209=V75)*($P$2:$P$209="Long Term Rental")*($Y$2:$Y$209<>""),"")))} | AB75: =IF(AND(V75="Villa",X75<>"",AA75<>""),(AA75*12/X75)*100,"") | AC75: {=IFERROR(MEDIAN(_xlfn._xlws.FILTER($Q$2:$Q$209,($M$2:$M$209=U75)*($P$2:$P$209="Short Term Rental")*($Q$2:$Q$209<>""))),"")}
A76: K0075 | B76: 3 BHK Independent House for rent in Neral Rd | C76: Neral Rd | D76: Independent House | E76: 3 BHK | F76: 1679 | G76: sqft | H76: 21300 | I76: INR | J76: Monthly | K76: Active | M76: =_xlfn.XLOOKUP(TRIM(C76),MAPPING!A:A,MAPPING!B:B,"CHECK") -> Neral | N76: =_xlfn.XLOOKUP(D76,MAPPING!G:G,MAPPING!H:H,"CHECK") -> Villa | O76: =_xlfn.XLOOKUP(E76,MAPPING!J:J,MAPPING!K:K,"CHECK") -> 3 BHK | P76: =_xlfn.XLOOKUP(J76,MAPPING!M:M,MAPPING!N:N,"CHECK") -> Long Term Rental | Q76: =IF(I76="INR",H76,IF(I76="Lakh",H76*100000,IF(I76="Crore",H76*10000000,IF(I76="Thousand",H76*1000,"")))) -> 21300 | R76: =IF(G76="sqft",F76,IF(G76="sqyd",F76*9,IF(G76="acre",F76*43560,IF(G76="guntha",F76*1089,IF(G76="hectare",F76*107639.1,""))))) -> 1679 | S76: =IF(AND(P76="Resale",R76>0),Q76/R76,"") | W76: =COUNTIFS($M$2:$M$209,U76,$N$2:$N$209,V76,$P$2:$P$209,"Resale") -> 0 | X76: {=IFERROR(MEDIAN(_xlfn._xlws.FILTER($S$2:$S$209,($M$2:$M$209=U76)*($N$2:$N$209=V76)*($P$2:$P$209="Resale")*($S$2:$S$209<>""))),"")} | Y76: =IF(AND(P76="Long Term Rental",R76>0),Q76/R76,"") -> 12.686123 | Z76: =COUNTIFS($M$2:$M$209,U76,$P$2:$P$209,"Long Term Rental") -> 0 | AA76: {=IF(Z76=0,"",MEDIAN(_xlfn._xlws.FILTER($Y$2:$Y$209,($M$2:$M$209=U76)*($N$2:$N$209=V76)*($P$2:$P$209="Long Term Rental")*($Y$2:$Y$209<>""),"")))} | AB76: =IF(AND(V76="Villa",X76<>"",AA76<>""),(AA76*12/X76)*100,"") | AC76: {=IFERROR(MEDIAN(_xlfn._xlws.FILTER($Q$2:$Q$209,($M$2:$M$209=U76)*($P$2:$P$209="Short Term Rental")*($Q$2:$Q$209<>""))),"")}
A77: K0076 | B77: 3BHK Bungalow for weekend stay near Near Neral Station | C77: Near Neral Station | D77: Bungalow | E77: 3BHK | H77: 5900 | I77: INR | J77: Per Night | K77: Active | L77: Forward 60-day availability calendar; not a confirmed-stay record. | M77: =_xlfn.XLOOKUP(TRIM(C77),MAPPING!A:A,MAPPING!B:B,"CHECK") -> Neral | N77: =_xlfn.XLOOKUP(D77,MAPPING!G:G,MAPPING!H:H,"CHECK") -> Villa | O77: =_xlfn.XLOOKUP(E77,MAPPING!J:J,MAPPING!K:K,"CHECK") -> 3 BHK | P77: =_xlfn.XLOOKUP(J77,MAPPING!M:M,MAPPING!N:N,"CHECK") -> Short Term Rental | Q77: =IF(I77="INR",H77,IF(I77="Lakh",H77*100000,IF(I77="Crore",H77*10000000,IF(I77="Thousand",H77*1000,"")))) -> 5900 | R77: =IF(G77="sqft",F77,IF(G77="sqyd",F77*9,IF(G77="acre",F77*43560,IF(G77="guntha",F77*1089,IF(G77="hectare",F77*107639.1,""))))) | S77: =IF(AND(P77="Resale",R77>0),Q77/R77,"") | W77: =COUNTIFS($M$2:$M$209,U77,$N$2:$N$209,V77,$P$2:$P$209,"Resale") -> 0 | X77: {=IFERROR(MEDIAN(_xlfn._xlws.FILTER($S$2:$S$209,($M$2:$M$209=U77)*($N$2:$N$209=V77)*($P$2:$P$209="Resale")*($S$2:$S$209<>""))),"")} | Y77: =IF(AND(P77="Long Term Rental",R77>0),Q77/R77,"") | Z77: =COUNTIFS($M$2:$M$209,U77,$P$2:$P$209,"Long Term Rental") -> 0 | AA77: {=IF(Z77=0,"",MEDIAN(_xlfn._xlws.FILTER($Y$2:$Y$209,($M$2:$M$209=U77)*($N$2:$N$209=V77)*($P$2:$P$209="Long Term Rental")*($Y$2:$Y$209<>""),"")))} | AB77: =IF(AND(V77="Villa",X77<>"",AA77<>""),(AA77*12/X77)*100,"") | AC77: {=IFERROR(MEDIAN(_xlfn._xlws.FILTER($Q$2:$Q$209,($M$2:$M$209=U77)*($P$2:$P$209="Short Term Rental")*($Q$2:$Q$209<>""))),"")}
A78: K0077 | B78: 4BHK Farmhouse for weekend stay near Near Neral Station | C78: Near Neral Station | D78: Farmhouse | E78: 4BHK | H78: 3600 | I78: INR | J78: Per Night | K78: Active | L78: Forward 60-day availability calendar; not a confirmed-stay record. | M78: =_xlfn.XLOOKUP(TRIM(C78),MAPPING!A:A,MAPPING!B:B,"CHECK") -> Neral | N78: =_xlfn.XLOOKUP(D78,MAPPING!G:G,MAPPING!H:H,"CHECK") -> Villa | O78: =_xlfn.XLOOKUP(E78,MAPPING!J:J,MAPPING!K:K,"CHECK") -> 4 BHK | P78: =_xlfn.XLOOKUP(J78,MAPPING!M:M,MAPPING!N:N,"CHECK") -> Short Term Rental | Q78: =IF(I78="INR",H78,IF(I78="Lakh",H78*100000,IF(I78="Crore",H78*10000000,IF(I78="Thousand",H78*1000,"")))) -> 3600 | R78: =IF(G78="sqft",F78,IF(G78="sqyd",F78*9,IF(G78="acre",F78*43560,IF(G78="guntha",F78*1089,IF(G78="hectare",F78*107639.1,""))))) | S78: =IF(AND(P78="Resale",R78>0),Q78/R78,"") | W78: =COUNTIFS($M$2:$M$209,U78,$N$2:$N$209,V78,$P$2:$P$209,"Resale") -> 0 | X78: {=IFERROR(MEDIAN(_xlfn._xlws.FILTER($S$2:$S$209,($M$2:$M$209=U78)*($N$2:$N$209=V78)*($P$2:$P$209="Resale")*($S$2:$S$209<>""))),"")} | Y78: =IF(AND(P78="Long Term Rental",R78>0),Q78/R78,"") | Z78: =COUNTIFS($M$2:$M$209,U78,$P$2:$P$209,"Long Term Rental") -> 0 | AA78: {=IF(Z78=0,"",MEDIAN(_xlfn._xlws.FILTER($Y$2:$Y$209,($M$2:$M$209=U78)*($N$2:$N$209=V78)*($P$2:$P$209="Long Term Rental")*($Y$2:$Y$209<>""),"")))} | AB78: =IF(AND(V78="Villa",X78<>"",AA78<>""),(AA78*12/X78)*100,"") | AC78: {=IFERROR(MEDIAN(_xlfn._xlws.FILTER($Q$2:$Q$209,($M$2:$M$209=U78)*($P$2:$P$209="Short Term Rental")*($Q$2:$Q$209<>""))),"")}
A79: K0078 | B79: 3 BHK Bungalow for weekend stay near Neral | C79: Neral | D79: Bungalow | E79: 3 BHK | H79: 5900 | I79: INR | J79: Per Night | K79: Active | L79: Forward 60-day availability calendar; not a confirmed-stay record. | M79: =_xlfn.XLOOKUP(TRIM(C79),MAPPING!A:A,MAPPING!B:B,"CHECK") -> Neral | N79: =_xlfn.XLOOKUP(D79,MAPPING!G:G,MAPPING!H:H,"CHECK") -> Villa | O79: =_xlfn.XLOOKUP(E79,MAPPING!J:J,MAPPING!K:K,"CHECK") -> 3 BHK | P79: =_xlfn.XLOOKUP(J79,MAPPING!M:M,MAPPING!N:N,"CHECK") -> Short Term Rental | Q79: =IF(I79="INR",H79,IF(I79="Lakh",H79*100000,IF(I79="Crore",H79*10000000,IF(I79="Thousand",H79*1000,"")))) -> 5900 | R79: =IF(G79="sqft",F79,IF(G79="sqyd",F79*9,IF(G79="acre",F79*43560,IF(G79="guntha",F79*1089,IF(G79="hectare",F79*107639.1,""))))) | S79: =IF(AND(P79="Resale",R79>0),Q79/R79,"") | W79: =COUNTIFS($M$2:$M$209,U79,$N$2:$N$209,V79,$P$2:$P$209,"Resale") -> 0 | X79: {=IFERROR(MEDIAN(_xlfn._xlws.FILTER($S$2:$S$209,($M$2:$M$209=U79)*($N$2:$N$209=V79)*($P$2:$P$209="Resale")*($S$2:$S$209<>""))),"")} | Y79: =IF(AND(P79="Long Term Rental",R79>0),Q79/R79,"") | Z79: =COUNTIFS($M$2:$M$209,U79,$P$2:$P$209,"Long Term Rental") -> 0 | AA79: {=IF(Z79=0,"",MEDIAN(_xlfn._xlws.FILTER($Y$2:$Y$209,($M$2:$M$209=U79)*($N$2:$N$209=V79)*($P$2:$P$209="Long Term Rental")*($Y$2:$Y$209<>""),"")))} | AB79: =IF(AND(V79="Villa",X79<>"",AA79<>""),(AA79*12/X79)*100,"") | AC79: {=IFERROR(MEDIAN(_xlfn._xlws.FILTER($Q$2:$Q$209,($M$2:$M$209=U79)*($P$2:$P$209="Short Term Rental")*($Q$2:$Q$209<>""))),"")}
A80: K0079 | B80: 3BHK Villa for weekend stay near Neral | C80: Neral | D80: Villa | E80: 3BHK | H80: 4200 | I80: INR | J80: Per Night | K80: Active | L80: Forward 60-day availability calendar; not a confirmed-stay record. | M80: =_xlfn.XLOOKUP(TRIM(C80),MAPPING!A:A,MAPPING!B:B,"CHECK") -> Neral | N80: =_xlfn.XLOOKUP(D80,MAPPING!G:G,MAPPING!H:H,"CHECK") -> Villa | O80: =_xlfn.XLOOKUP(E80,MAPPING!J:J,MAPPING!K:K,"CHECK") -> 3 BHK | P80: =_xlfn.XLOOKUP(J80,MAPPING!M:M,MAPPING!N:N,"CHECK") -> Short Term Rental | Q80: =IF(I80="INR",H80,IF(I80="Lakh",H80*100000,IF(I80="Crore",H80*10000000,IF(I80="Thousand",H80*1000,"")))) -> 4200 | R80: =IF(G80="sqft",F80,IF(G80="sqyd",F80*9,IF(G80="acre",F80*43560,IF(G80="guntha",F80*1089,IF(G80="hectare",F80*107639.1,""))))) | S80: =IF(AND(P80="Resale",R80>0),Q80/R80,"") | W80: =COUNTIFS($M$2:$M$209,U80,$N$2:$N$209,V80,$P$2:$P$209,"Resale") -> 0 | X80: {=IFERROR(MEDIAN(_xlfn._xlws.FILTER($S$2:$S$209,($M$2:$M$209=U80)*($N$2:$N$209=V80)*($P$2:$P$209="Resale")*($S$2:$S$209<>""))),"")} | Y80: =IF(AND(P80="Long Term Rental",R80>0),Q80/R80,"") | Z80: =COUNTIFS($M$2:$M$209,U80,$P$2:$P$209,"Long Term Rental") -> 0 | AA80: {=IF(Z80=0,"",MEDIAN(_xlfn._xlws.FILTER($Y$2:$Y$209,($M$2:$M$209=U80)*($N$2:$N$209=V80)*($P$2:$P$209="Long Term Rental")*($Y$2:$Y$209<>""),"")))} | AB80: =IF(AND(V80="Villa",X80<>"",AA80<>""),(AA80*12/X80)*100,"") | AC80: {=IFERROR(MEDIAN(_xlfn._xlws.FILTER($Q$2:$Q$209,($M$2:$M$209=U80)*($P$2:$P$209="Short Term Rental")*($Q$2:$Q$209<>""))),"")}
A81: K0080 | B81: 3 BHK Bungalow for weekend stay near Near Neral Station | C81: Near Neral Station | D81: Bungalow | E81: 3 BHK | H81: 6700 | I81: INR | J81: Per Night | K81: Active | L81: Forward 60-day availability calendar; not a confirmed-stay record. | M81: =_xlfn.XLOOKUP(TRIM(C81),MAPPING!A:A,MAPPING!B:B,"CHECK") -> Neral | N81: =_xlfn.XLOOKUP(D81,MAPPING!G:G,MAPPING!H:H,"CHECK") -> Villa | O81: =_xlfn.XLOOKUP(E81,MAPPING!J:J,MAPPING!K:K,"CHECK") -> 3 BHK | P81: =_xlfn.XLOOKUP(J81,MAPPING!M:M,MAPPING!N:N,"CHECK") -> Short Term Rental | Q81: =IF(I81="INR",H81,IF(I81="Lakh",H81*100000,IF(I81="Crore",H81*10000000,IF(I81="Thousand",H81*1000,"")))) -> 6700 | R81: =IF(G81="sqft",F81,IF(G81="sqyd",F81*9,IF(G81="acre",F81*43560,IF(G81="guntha",F81*1089,IF(G81="hectare",F81*107639.1,""))))) | S81: =IF(AND(P81="Resale",R81>0),Q81/R81,"") | W81: =COUNTIFS($M$2:$M$209,U81,$N$2:$N$209,V81,$P$2:$P$209,"Resale") -> 0 | X81: {=IFERROR(MEDIAN(_xlfn._xlws.FILTER($S$2:$S$209,($M$2:$M$209=U81)*($N$2:$N$209=V81)*($P$2:$P$209="Resale")*($S$2:$S$209<>""))),"")} | Y81: =IF(AND(P81="Long Term Rental",R81>0),Q81/R81,"") | Z81: =COUNTIFS($M$2:$M$209,U81,$P$2:$P$209,"Long Term Rental") -> 0 | AA81: {=IF(Z81=0,"",MEDIAN(_xlfn._xlws.FILTER($Y$2:$Y$209,($M$2:$M$209=U81)*($N$2:$N$209=V81)*($P$2:$P$209="Long Term Rental")*($Y$2:$Y$209<>""),"")))} | AB81: =IF(AND(V81="Villa",X81<>"",AA81<>""),(AA81*12/X81)*100,"") | AC81: {=IFERROR(MEDIAN(_xlfn._xlws.FILTER($Q$2:$Q$209,($M$2:$M$209=U81)*($P$2:$P$209="Short Term Rental")*($Q$2:$Q$209<>""))),"")}
A82: K0081 | B82: 2 BHK Farmhouse for weekend stay near Neral Rd | C82: Neral Rd | D82: Farmhouse | E82: 2 BHK | H82: 4900 | I82: INR | J82: Per Night | K82: Active | L82: Forward 60-day availability calendar; not a confirmed-stay record. | M82: =_xlfn.XLOOKUP(TRIM(C82),MAPPING!A:A,MAPPING!B:B,"CHECK") -> Neral | N82: =_xlfn.XLOOKUP(D82,MAPPING!G:G,MAPPING!H:H,"CHECK") -> Villa | O82: =_xlfn.XLOOKUP(E82,MAPPING!J:J,MAPPING!K:K,"CHECK") -> 2 BHK | P82: =_xlfn.XLOOKUP(J82,MAPPING!M:M,MAPPING!N:N,"CHECK") -> Short Term Rental | Q82: =IF(I82="INR",H82,IF(I82="Lakh",H82*100000,IF(I82="Crore",H82*10000000,IF(I82="Thousand",H82*1000,"")))) -> 4900 | R82: =IF(G82="sqft",F82,IF(G82="sqyd",F82*9,IF(G82="acre",F82*43560,IF(G82="guntha",F82*1089,IF(G82="hectare",F82*107639.1,""))))) | S82: =IF(AND(P82="Resale",R82>0),Q82/R82,"") | W82: =COUNTIFS($M$2:$M$209,U82,$N$2:$N$209,V82,$P$2:$P$209,"Resale") -> 0 | X82: {=IFERROR(MEDIAN(_xlfn._xlws.FILTER($S$2:$S$209,($M$2:$M$209=U82)*($N$2:$N$209=V82)*($P$2:$P$209="Resale")*($S$2:$S$209<>""))),"")} | Y82: =IF(AND(P82="Long Term Rental",R82>0),Q82/R82,"") | Z82: =COUNTIFS($M$2:$M$209,U82,$P$2:$P$209,"Long Term Rental") -> 0 | AA82: {=IF(Z82=0,"",MEDIAN(_xlfn._xlws.FILTER($Y$2:$Y$209,($M$2:$M$209=U82)*($N$2:$N$209=V82)*($P$2:$P$209="Long Term Rental")*($Y$2:$Y$209<>""),"")))} | AB82: =IF(AND(V82="Villa",X82<>"",AA82<>""),(AA82*12/X82)*100,"") | AC82: {=IFERROR(MEDIAN(_xlfn._xlws.FILTER($Q$2:$Q$209,($M$2:$M$209=U82)*($P$2:$P$209="Short Term Rental")*($Q$2:$Q$209<>""))),"")}
A83: K0082 | B83: 3BHK Farmhouse for weekend stay near Neral | C83: Neral | D83: Farmhouse | E83: 3BHK | H83: 6700 | I83: INR | J83: Per Night | K83: Active | L83: Forward 60-day availability calendar; not a confirmed-stay record. | M83: =_xlfn.XLOOKUP(TRIM(C83),MAPPING!A:A,MAPPING!B:B,"CHECK") -> Neral | N83: =_xlfn.XLOOKUP(D83,MAPPING!G:G,MAPPING!H:H,"CHECK") -> Villa | O83: =_xlfn.XLOOKUP(E83,MAPPING!J:J,MAPPING!K:K,"CHECK") -> 3 BHK | P83: =_xlfn.XLOOKUP(J83,MAPPING!M:M,MAPPING!N:N,"CHECK") -> Short Term Rental | Q83: =IF(I83="INR",H83,IF(I83="Lakh",H83*100000,IF(I83="Crore",H83*10000000,IF(I83="Thousand",H83*1000,"")))) -> 6700 | R83: =IF(G83="sqft",F83,IF(G83="sqyd",F83*9,IF(G83="acre",F83*43560,IF(G83="guntha",F83*1089,IF(G83="hectare",F83*107639.1,""))))) | S83: =IF(AND(P83="Resale",R83>0),Q83/R83,"") | W83: =COUNTIFS($M$2:$M$209,U83,$N$2:$N$209,V83,$P$2:$P$209,"Resale") -> 0 | X83: {=IFERROR(MEDIAN(_xlfn._xlws.FILTER($S$2:$S$209,($M$2:$M$209=U83)*($N$2:$N$209=V83)*($P$2:$P$209="Resale")*($S$2:$S$209<>""))),"")} | Y83: =IF(AND(P83="Long Term Rental",R83>0),Q83/R83,"") | Z83: =COUNTIFS($M$2:$M$209,U83,$P$2:$P$209,"Long Term Rental") -> 0 | AA83: {=IF(Z83=0,"",MEDIAN(_xlfn._xlws.FILTER($Y$2:$Y$209,($M$2:$M$209=U83)*($N$2:$N$209=V83)*($P$2:$P$209="Long Term Rental")*($Y$2:$Y$209<>""),"")))} | AB83: =IF(AND(V83="Villa",X83<>"",AA83<>""),(AA83*12/X83)*100,"") | AC83: {=IFERROR(MEDIAN(_xlfn._xlws.FILTER($Q$2:$Q$209,($M$2:$M$209=U83)*($P$2:$P$209="Short Term Rental")*($Q$2:$Q$209<>""))),"")}
A84: K0083 | B84: 3 BHK Farmhouse for weekend stay near Near Neral Station | C84: Near Neral Station | D84: Farmhouse | E84: 3 BHK | H84: 4700 | I84: INR | J84: Per Night | K84: Active | L84: Forward 60-day availability calendar; not a confirmed-stay record. | M84: =_xlfn.XLOOKUP(TRIM(C84),MAPPING!A:A,MAPPING!B:B,"CHECK") -> Neral | N84: =_xlfn.XLOOKUP(D84,MAPPING!G:G,MAPPING!H:H,"CHECK") -> Villa | O84: =_xlfn.XLOOKUP(E84,MAPPING!J:J,MAPPING!K:K,"CHECK") -> 3 BHK | P84: =_xlfn.XLOOKUP(J84,MAPPING!M:M,MAPPING!N:N,"CHECK") -> Short Term Rental | Q84: =IF(I84="INR",H84,IF(I84="Lakh",H84*100000,IF(I84="Crore",H84*10000000,IF(I84="Thousand",H84*1000,"")))) -> 4700 | R84: =IF(G84="sqft",F84,IF(G84="sqyd",F84*9,IF(G84="acre",F84*43560,IF(G84="guntha",F84*1089,IF(G84="hectare",F84*107639.1,""))))) | S84: =IF(AND(P84="Resale",R84>0),Q84/R84,"") | W84: =COUNTIFS($M$2:$M$209,U84,$N$2:$N$209,V84,$P$2:$P$209,"Resale") -> 0 | X84: {=IFERROR(MEDIAN(_xlfn._xlws.FILTER($S$2:$S$209,($M$2:$M$209=U84)*($N$2:$N$209=V84)*($P$2:$P$209="Resale")*($S$2:$S$209<>""))),"")} | Y84: =IF(AND(P84="Long Term Rental",R84>0),Q84/R84,"") | Z84: =COUNTIFS($M$2:$M$209,U84,$P$2:$P$209,"Long Term Rental") -> 0 | AA84: {=IF(Z84=0,"",MEDIAN(_xlfn._xlws.FILTER($Y$2:$Y$209,($M$2:$M$209=U84)*($N$2:$N$209=V84)*($P$2:$P$209="Long Term Rental")*($Y$2:$Y$209<>""),"")))} | AB84: =IF(AND(V84="Villa",X84<>"",AA84<>""),(AA84*12/X84)*100,"") | AC84: {=IFERROR(MEDIAN(_xlfn._xlws.FILTER($Q$2:$Q$209,($M$2:$M$209=U84)*($P$2:$P$209="Short Term Rental")*($Q$2:$Q$209<>""))),"")}
A85: K0084 | B85: Two BHK Villa for weekend stay near Near Neral Station | C85: Near Neral Station | D85: Villa | E85: Two BHK | H85: 5000 | I85: INR | J85: Per Night | K85: Active | L85: Forward 60-day availability calendar; not a confirmed-stay record. | M85: =_xlfn.XLOOKUP(TRIM(C85),MAPPING!A:A,MAPPING!B:B,"CHECK") -> Neral | N85: =_xlfn.XLOOKUP(D85,MAPPING!G:G,MAPPING!H:H,"CHECK") -> Villa | O85: =_xlfn.XLOOKUP(E85,MAPPING!J:J,MAPPING!K:K,"CHECK") -> 2 BHK | P85: =_xlfn.XLOOKUP(J85,MAPPING!M:M,MAPPING!N:N,"CHECK") -> Short Term Rental | Q85: =IF(I85="INR",H85,IF(I85="Lakh",H85*100000,IF(I85="Crore",H85*10000000,IF(I85="Thousand",H85*1000,"")))) -> 5000 | R85: =IF(G85="sqft",F85,IF(G85="sqyd",F85*9,IF(G85="acre",F85*43560,IF(G85="guntha",F85*1089,IF(G85="hectare",F85*107639.1,""))))) | S85: =IF(AND(P85="Resale",R85>0),Q85/R85,"") | W85: =COUNTIFS($M$2:$M$209,U85,$N$2:$N$209,V85,$P$2:$P$209,"Resale") -> 0 | X85: {=IFERROR(MEDIAN(_xlfn._xlws.FILTER($S$2:$S$209,($M$2:$M$209=U85)*($N$2:$N$209=V85)*($P$2:$P$209="Resale")*($S$2:$S$209<>""))),"")} | Y85: =IF(AND(P85="Long Term Rental",R85>0),Q85/R85,"") | Z85: =COUNTIFS($M$2:$M$209,U85,$P$2:$P$209,"Long Term Rental") -> 0 | AA85: {=IF(Z85=0,"",MEDIAN(_xlfn._xlws.FILTER($Y$2:$Y$209,($M$2:$M$209=U85)*($N$2:$N$209=V85)*($P$2:$P$209="Long Term Rental")*($Y$2:$Y$209<>""),"")))} | AB85: =IF(AND(V85="Villa",X85<>"",AA85<>""),(AA85*12/X85)*100,"") | AC85: {=IFERROR(MEDIAN(_xlfn._xlws.FILTER($Q$2:$Q$209,($M$2:$M$209=U85)*($P$2:$P$209="Short Term Rental")*($Q$2:$Q$209<>""))),"")}
A86: K0085 | B86: Two BHK Farmhouse for sale in Kasheli | C86: Kasheli | D86: Farmhouse | E86: Two BHK | F86: 1256 | G86: sqft | H86: 43.36 | I86: Lakh | J86: One-time | K86: Active | M86: =_xlfn.XLOOKUP(TRIM(C86),MAPPING!A:A,MAPPING!B:B,"CHECK") -> Kashele | N86: =_xlfn.XLOOKUP(D86,MAPPING!G:G,MAPPING!H:H,"CHECK") -> Villa | O86: =_xlfn.XLOOKUP(E86,MAPPING!J:J,MAPPING!K:K,"CHECK") -> 2 BHK | P86: =_xlfn.XLOOKUP(J86,MAPPING!M:M,MAPPING!N:N,"CHECK") -> Resale | Q86: =IF(I86="INR",H86,IF(I86="Lakh",H86*100000,IF(I86="Crore",H86*10000000,IF(I86="Thousand",H86*1000,"")))) -> 4336000 | R86: =IF(G86="sqft",F86,IF(G86="sqyd",F86*9,IF(G86="acre",F86*43560,IF(G86="guntha",F86*1089,IF(G86="hectare",F86*107639.1,""))))) -> 1256 | S86: =IF(AND(P86="Resale",R86>0),Q86/R86,"") -> 3452.2293 | W86: =COUNTIFS($M$2:$M$209,U86,$N$2:$N$209,V86,$P$2:$P$209,"Resale") -> 0 | X86: {=IFERROR(MEDIAN(_xlfn._xlws.FILTER($S$2:$S$209,($M$2:$M$209=U86)*($N$2:$N$209=V86)*($P$2:$P$209="Resale")*($S$2:$S$209<>""))),"")} | Y86: =IF(AND(P86="Long Term Rental",R86>0),Q86/R86,"") | Z86: =COUNTIFS($M$2:$M$209,U86,$P$2:$P$209,"Long Term Rental") -> 0 | AA86: {=IF(Z86=0,"",MEDIAN(_xlfn._xlws.FILTER($Y$2:$Y$209,($M$2:$M$209=U86)*($N$2:$N$209=V86)*($P$2:$P$209="Long Term Rental")*($Y$2:$Y$209<>""),"")))} | AB86: =IF(AND(V86="Villa",X86<>"",AA86<>""),(AA86*12/X86)*100,"") | AC86: {=IFERROR(MEDIAN(_xlfn._xlws.FILTER($Q$2:$Q$209,($M$2:$M$209=U86)*($P$2:$P$209="Short Term Rental")*($Q$2:$Q$209<>""))),"")}
A87: K0086 | B87: Farm Land for sale in Kashele Village | C87: Kashele Village | D87: Farm Land | E87: NA | F87: 2952 | G87: sqft | I87: Lakh | J87: One-time | K87: Price on Request | M87: =_xlfn.XLOOKUP(TRIM(C87),MAPPING!A:A,MAPPING!B:B,"CHECK") -> Kashele | N87: =_xlfn.XLOOKUP(D87,MAPPING!G:G,MAPPING!H:H,"CHECK") -> Farmland | O87: =_xlfn.XLOOKUP(E87,MAPPING!J:J,MAPPING!K:K,"CHECK") -> NA | P87: =_xlfn.XLOOKUP(J87,MAPPING!M:M,MAPPING!N:N,"CHECK") -> Resale | Q87: =IF(I87="INR",H87,IF(I87="Lakh",H87*100000,IF(I87="Crore",H87*10000000,IF(I87="Thousand",H87*1000,"")))) -> 0 | R87: =IF(G87="sqft",F87,IF(G87="sqyd",F87*9,IF(G87="acre",F87*43560,IF(G87="guntha",F87*1089,IF(G87="hectare",F87*107639.1,""))))) -> 2952 | S87: =IF(AND(P87="Resale",R87>0),Q87/R87,"") -> 0 | W87: =COUNTIFS($M$2:$M$209,U87,$N$2:$N$209,V87,$P$2:$P$209,"Resale") -> 0 | X87: {=IFERROR(MEDIAN(_xlfn._xlws.FILTER($S$2:$S$209,($M$2:$M$209=U87)*($N$2:$N$209=V87)*($P$2:$P$209="Resale")*($S$2:$S$209<>""))),"")} | Y87: =IF(AND(P87="Long Term Rental",R87>0),Q87/R87,"") | Z87: =COUNTIFS($M$2:$M$209,U87,$P$2:$P$209,"Long Term Rental") -> 0 | AA87: {=IF(Z87=0,"",MEDIAN(_xlfn._xlws.FILTER($Y$2:$Y$209,($M$2:$M$209=U87)*($N$2:$N$209=V87)*($P$2:$P$209="Long Term Rental")*($Y$2:$Y$209<>""),"")))} | AB87: =IF(AND(V87="Villa",X87<>"",AA87<>""),(AA87*12/X87)*100,"") | AC87: {=IFERROR(MEDIAN(_xlfn._xlws.FILTER($Q$2:$Q$209,($M$2:$M$209=U87)*($P$2:$P$209="Short Term Rental")*($Q$2:$Q$209<>""))),"")}
A88: K0087 | B88: 3BHK Row House for sale in Kashele | C88: Kashele | D88: Row House | E88: 3BHK | G88: sqft | H88: 81.02 | I88: Lakh | J88: One-time | K88: Active | M88: =_xlfn.XLOOKUP(TRIM(C88),MAPPING!A:A,MAPPING!B:B,"CHECK") -> Kashele | N88: =_xlfn.XLOOKUP(D88,MAPPING!G:G,MAPPING!H:H,"CHECK") -> Villa | O88: =_xlfn.XLOOKUP(E88,MAPPING!J:J,MAPPING!K:K,"CHECK") -> 3 BHK | P88: =_xlfn.XLOOKUP(J88,MAPPING!M:M,MAPPING!N:N,"CHECK") -> Resale | Q88: =IF(I88="INR",H88,IF(I88="Lakh",H88*100000,IF(I88="Crore",H88*10000000,IF(I88="Thousand",H88*1000,"")))) -> 8102000 | R88: =IF(G88="sqft",F88,IF(G88="sqyd",F88*9,IF(G88="acre",F88*43560,IF(G88="guntha",F88*1089,IF(G88="hectare",F88*107639.1,""))))) -> 0 | S88: =IF(AND(P88="Resale",R88>0),Q88/R88,"") | W88: =COUNTIFS($M$2:$M$209,U88,$N$2:$N$209,V88,$P$2:$P$209,"Resale") -> 0 | X88: {=IFERROR(MEDIAN(_xlfn._xlws.FILTER($S$2:$S$209,($M$2:$M$209=U88)*($N$2:$N$209=V88)*($P$2:$P$209="Resale")*($S$2:$S$209<>""))),"")} | Y88: =IF(AND(P88="Long Term Rental",R88>0),Q88/R88,"") | Z88: =COUNTIFS($M$2:$M$209,U88,$P$2:$P$209,"Long Term Rental") -> 0 | AA88: {=IF(Z88=0,"",MEDIAN(_xlfn._xlws.FILTER($Y$2:$Y$209,($M$2:$M$209=U88)*($N$2:$N$209=V88)*($P$2:$P$209="Long Term Rental")*($Y$2:$Y$209<>""),"")))} | AB88: =IF(AND(V88="Villa",X88<>"",AA88<>""),(AA88*12/X88)*100,"") | AC88: {=IFERROR(MEDIAN(_xlfn._xlws.FILTER($Q$2:$Q$209,($M$2:$M$209=U88)*($P$2:$P$209="Short Term Rental")*($Q$2:$Q$209<>""))),"")}
A89: K0088 | B89: 3BR Independent House for sale in Kashele Village | C89: Kashele Village | D89: Independent House | E89: 3BR | F89: 2660 | G89: sqft | H89: 87 | I89: Lakh | J89: One-time | K89: Sold | M89: =_xlfn.XLOOKUP(TRIM(C89),MAPPING!A:A,MAPPING!B:B,"CHECK") -> Kashele | N89: =_xlfn.XLOOKUP(D89,MAPPING!G:G,MAPPING!H:H,"CHECK") -> Villa | O89: =_xlfn.XLOOKUP(E89,MAPPING!J:J,MAPPING!K:K,"CHECK") -> 3 BHK | P89: =_xlfn.XLOOKUP(J89,MAPPING!M:M,MAPPING!N:N,"CHECK") -> Resale | Q89: =IF(I89="INR",H89,IF(I89="Lakh",H89*100000,IF(I89="Crore",H89*10000000,IF(I89="Thousand",H89*1000,"")))) -> 8700000 | R89: =IF(G89="sqft",F89,IF(G89="sqyd",F89*9,IF(G89="acre",F89*43560,IF(G89="guntha",F89*1089,IF(G89="hectare",F89*107639.1,""))))) -> 2660 | S89: =IF(AND(P89="Resale",R89>0),Q89/R89,"") -> 3270.6767 | W89: =COUNTIFS($M$2:$M$209,U89,$N$2:$N$209,V89,$P$2:$P$209,"Resale") -> 0 | X89: {=IFERROR(MEDIAN(_xlfn._xlws.FILTER($S$2:$S$209,($M$2:$M$209=U89)*($N$2:$N$209=V89)*($P$2:$P$209="Resale")*($S$2:$S$209<>""))),"")} | Y89: =IF(AND(P89="Long Term Rental",R89>0),Q89/R89,"") | Z89: =COUNTIFS($M$2:$M$209,U89,$P$2:$P$209,"Long Term Rental") -> 0 | AA89: {=IF(Z89=0,"",MEDIAN(_xlfn._xlws.FILTER($Y$2:$Y$209,($M$2:$M$209=U89)*($N$2:$N$209=V89)*($P$2:$P$209="Long Term Rental")*($Y$2:$Y$209<>""),"")))} | AB89: =IF(AND(V89="Villa",X89<>"",AA89<>""),(AA89*12/X89)*100,"") | AC89: {=IFERROR(MEDIAN(_xlfn._xlws.FILTER($Q$2:$Q$209,($M$2:$M$209=U89)*($P$2:$P$209="Short Term Rental")*($Q$2:$Q$209<>""))),"")}
A90: K0089 | B90: 3 BHK Bungalow for sale in Kashele Phata | C90: Kashele Phata | D90: Bungalow | E90: 3 BHK | F90: 2558 | G90: sqft | H90: 92.34 | I90: Lakh | J90: One-time | K90: Sold | M90: =_xlfn.XLOOKUP(TRIM(C90),MAPPING!A:A,MAPPING!B:B,"CHECK") -> Kashele | N90: =_xlfn.XLOOKUP(D90,MAPPING!G:G,MAPPING!H:H,"CHECK") -> Villa | O90: =_xlfn.XLOOKUP(E90,MAPPING!J:J,MAPPING!K:K,"CHECK") -> 3 BHK | P90: =_xlfn.XLOOKUP(J90,MAPPING!M:M,MAPPING!N:N,"CHECK") -> Resale | Q90: =IF(I90="INR",H90,IF(I90="Lakh",H90*100000,IF(I90="Crore",H90*10000000,IF(I90="Thousand",H90*1000,"")))) -> 9234000 | R90: =IF(G90="sqft",F90,IF(G90="sqyd",F90*9,IF(G90="acre",F90*43560,IF(G90="guntha",F90*1089,IF(G90="hectare",F90*107639.1,""))))) -> 2558 | S90: =IF(AND(P90="Resale",R90>0),Q90/R90,"") -> 3609.8514 | W90: =COUNTIFS($M$2:$M$209,U90,$N$2:$N$209,V90,$P$2:$P$209,"Resale") -> 0 | X90: {=IFERROR(MEDIAN(_xlfn._xlws.FILTER($S$2:$S$209,($M$2:$M$209=U90)*($N$2:$N$209=V90)*($P$2:$P$209="Resale")*($S$2:$S$209<>""))),"")} | Y90: =IF(AND(P90="Long Term Rental",R90>0),Q90/R90,"") | Z90: =COUNTIFS($M$2:$M$209,U90,$P$2:$P$209,"Long Term Rental") -> 0 | AA90: {=IF(Z90=0,"",MEDIAN(_xlfn._xlws.FILTER($Y$2:$Y$209,($M$2:$M$209=U90)*($N$2:$N$209=V90)*($P$2:$P$209="Long Term Rental")*($Y$2:$Y$209<>""),"")))} | AB90: =IF(AND(V90="Villa",X90<>"",AA90<>""),(AA90*12/X90)*100,"") | AC90: {=IFERROR(MEDIAN(_xlfn._xlws.FILTER($Q$2:$Q$209,($M$2:$M$209=U90)*($P$2:$P$209="Short Term Rental")*($Q$2:$Q$209<>""))),"")}
A91: K0090 | B91: 3 BHK Independent House for sale in Kashele | C91: Kashele | D91: Independent House | E91: 3 BHK | F91: 2373 | G91: sqft | H91: 96.35 | I91: Lakh | J91: One-time | K91: Active | M91: =_xlfn.XLOOKUP(TRIM(C91),MAPPING!A:A,MAPPING!B:B,"CHECK") -> Kashele | N91: =_xlfn.XLOOKUP(D91,MAPPING!G:G,MAPPING!H:H,"CHECK") -> Villa | O91: =_xlfn.XLOOKUP(E91,MAPPING!J:J,MAPPING!K:K,"CHECK") -> 3 BHK | P91: =_xlfn.XLOOKUP(J91,MAPPING!M:M,MAPPING!N:N,"CHECK") -> Resale | Q91: =IF(I91="INR",H91,IF(I91="Lakh",H91*100000,IF(I91="Crore",H91*10000000,IF(I91="Thousand",H91*1000,"")))) -> 9635000 | R91: =IF(G91="sqft",F91,IF(G91="sqyd",F91*9,IF(G91="acre",F91*43560,IF(G91="guntha",F91*1089,IF(G91="hectare",F91*107639.1,""))))) -> 2373 | S91: =IF(AND(P91="Resale",R91>0),Q91/R91,"") -> 4060.2613 | W91: =COUNTIFS($M$2:$M$209,U91,$N$2:$N$209,V91,$P$2:$P$209,"Resale") -> 0 | X91: {=IFERROR(MEDIAN(_xlfn._xlws.FILTER($S$2:$S$209,($M$2:$M$209=U91)*($N$2:$N$209=V91)*($P$2:$P$209="Resale")*($S$2:$S$209<>""))),"")} | Y91: =IF(AND(P91="Long Term Rental",R91>0),Q91/R91,"") | Z91: =COUNTIFS($M$2:$M$209,U91,$P$2:$P$209,"Long Term Rental") -> 0 | AA91: {=IF(Z91=0,"",MEDIAN(_xlfn._xlws.FILTER($Y$2:$Y$209,($M$2:$M$209=U91)*($N$2:$N$209=V91)*($P$2:$P$209="Long Term Rental")*($Y$2:$Y$209<>""),"")))} | AB91: =IF(AND(V91="Villa",X91<>"",AA91<>""),(AA91*12/X91)*100,"") | AC91: {=IFERROR(MEDIAN(_xlfn._xlws.FILTER($Q$2:$Q$209,($M$2:$M$209=U91)*($P$2:$P$209="Short Term Rental")*($Q$2:$Q$209<>""))),"")}
A92: K0091 | B92: Plot for sale in Kashele Village | C92: Kashele Village | D92: Plot | E92: NA | F92: 4253 | G92: sqft | H92: 34.89 | I92: Lakh | J92: One-time | K92: Active | M92: =_xlfn.XLOOKUP(TRIM(C92),MAPPING!A:A,MAPPING!B:B,"CHECK") -> Kashele | N92: =_xlfn.XLOOKUP(D92,MAPPING!G:G,MAPPING!H:H,"CHECK") -> Plot | O92: =_xlfn.XLOOKUP(E92,MAPPING!J:J,MAPPING!K:K,"CHECK") -> NA | P92: =_xlfn.XLOOKUP(J92,MAPPING!M:M,MAPPING!N:N,"CHECK") -> Resale | Q92: =IF(I92="INR",H92,IF(I92="Lakh",H92*100000,IF(I92="Crore",H92*10000000,IF(I92="Thousand",H92*1000,"")))) -> 3489000 | R92: =IF(G92="sqft",F92,IF(G92="sqyd",F92*9,IF(G92="acre",F92*43560,IF(G92="guntha",F92*1089,IF(G92="hectare",F92*107639.1,""))))) -> 4253 | S92: =IF(AND(P92="Resale",R92>0),Q92/R92,"") -> 820.3621 | W92: =COUNTIFS($M$2:$M$209,U92,$N$2:$N$209,V92,$P$2:$P$209,"Resale") -> 0 | X92: {=IFERROR(MEDIAN(_xlfn._xlws.FILTER($S$2:$S$209,($M$2:$M$209=U92)*($N$2:$N$209=V92)*($P$2:$P$209="Resale")*($S$2:$S$209<>""))),"")} | Y92: =IF(AND(P92="Long Term Rental",R92>0),Q92/R92,"") | Z92: =COUNTIFS($M$2:$M$209,U92,$P$2:$P$209,"Long Term Rental") -> 0 | AA92: {=IF(Z92=0,"",MEDIAN(_xlfn._xlws.FILTER($Y$2:$Y$209,($M$2:$M$209=U92)*($N$2:$N$209=V92)*($P$2:$P$209="Long Term Rental")*($Y$2:$Y$209<>""),"")))} | AB92: =IF(AND(V92="Villa",X92<>"",AA92<>""),(AA92*12/X92)*100,"") | AC92: {=IFERROR(MEDIAN(_xlfn._xlws.FILTER($Q$2:$Q$209,($M$2:$M$209=U92)*($P$2:$P$209="Short Term Rental")*($Q$2:$Q$209<>""))),"")}
A93: K0092 | B93: Plot for sale in Kashele Phata | C93: Kashele Phata | D93: Plot | E93: NA | F93: 1.56 | G93: acre | H93: 4.9 | I93: Crore | J93: One-time | K93: Price on Request | M93: =_xlfn.XLOOKUP(TRIM(C93),MAPPING!A:A,MAPPING!B:B,"CHECK") -> Kashele | N93: =_xlfn.XLOOKUP(D93,MAPPING!G:G,MAPPING!H:H,"CHECK") -> Plot | O93: =_xlfn.XLOOKUP(E93,MAPPING!J:J,MAPPING!K:K,"CHECK") -> NA | P93: =_xlfn.XLOOKUP(J93,MAPPING!M:M,MAPPING!N:N,"CHECK") -> Resale | Q93: =IF(I93="INR",H93,IF(I93="Lakh",H93*100000,IF(I93="Crore",H93*10000000,IF(I93="Thousand",H93*1000,"")))) -> 49000000 | R93: =IF(G93="sqft",F93,IF(G93="sqyd",F93*9,IF(G93="acre",F93*43560,IF(G93="guntha",F93*1089,IF(G93="hectare",F93*107639.1,""))))) -> 67953.6 | S93: =IF(AND(P93="Resale",R93>0),Q93/R93,"") -> 721.08027 | W93: =COUNTIFS($M$2:$M$209,U93,$N$2:$N$209,V93,$P$2:$P$209,"Resale") -> 0 | X93: {=IFERROR(MEDIAN(_xlfn._xlws.FILTER($S$2:$S$209,($M$2:$M$209=U93)*($N$2:$N$209=V93)*($P$2:$P$209="Resale")*($S$2:$S$209<>""))),"")} | Y93: =IF(AND(P93="Long Term Rental",R93>0),Q93/R93,"") | Z93: =COUNTIFS($M$2:$M$209,U93,$P$2:$P$209,"Long Term Rental") -> 0 | AA93: {=IF(Z93=0,"",MEDIAN(_xlfn._xlws.FILTER($Y$2:$Y$209,($M$2:$M$209=U93)*($N$2:$N$209=V93)*($P$2:$P$209="Long Term Rental")*($Y$2:$Y$209<>""),"")))} | AB93: =IF(AND(V93="Villa",X93<>"",AA93<>""),(AA93*12/X93)*100,"") | AC93: {=IFERROR(MEDIAN(_xlfn._xlws.FILTER($Q$2:$Q$209,($M$2:$M$209=U93)*($P$2:$P$209="Short Term Rental")*($Q$2:$Q$209<>""))),"")}
A94: K0093 | B94: 2BHK Villa for sale in Kasheli | C94: Kasheli | D94: Villa | E94: 2BHK | F94: 1726 | G94: sqft | I94: Lakh | J94: One-time | K94: Price on Request | M94: =_xlfn.XLOOKUP(TRIM(C94),MAPPING!A:A,MAPPING!B:B,"CHECK") -> Kashele | N94: =_xlfn.XLOOKUP(D94,MAPPING!G:G,MAPPING!H:H,"CHECK") -> Villa | O94: =_xlfn.XLOOKUP(E94,MAPPING!J:J,MAPPING!K:K,"CHECK") -> 2 BHK | P94: =_xlfn.XLOOKUP(J94,MAPPING!M:M,MAPPING!N:N,"CHECK") -> Resale | Q94: =IF(I94="INR",H94,IF(I94="Lakh",H94*100000,IF(I94="Crore",H94*10000000,IF(I94="Thousand",H94*1000,"")))) -> 0 | R94: =IF(G94="sqft",F94,IF(G94="sqyd",F94*9,IF(G94="acre",F94*43560,IF(G94="guntha",F94*1089,IF(G94="hectare",F94*107639.1,""))))) -> 1726 | S94: =IF(AND(P94="Resale",R94>0),Q94/R94,"") -> 0 | W94: =COUNTIFS($M$2:$M$209,U94,$N$2:$N$209,V94,$P$2:$P$209,"Resale") -> 0 | X94: {=IFERROR(MEDIAN(_xlfn._xlws.FILTER($S$2:$S$209,($M$2:$M$209=U94)*($N$2:$N$209=V94)*($P$2:$P$209="Resale")*($S$2:$S$209<>""))),"")} | Y94: =IF(AND(P94="Long Term Rental",R94>0),Q94/R94,"") | Z94: =COUNTIFS($M$2:$M$209,U94,$P$2:$P$209,"Long Term Rental") -> 0 | AA94: {=IF(Z94=0,"",MEDIAN(_xlfn._xlws.FILTER($Y$2:$Y$209,($M$2:$M$209=U94)*($N$2:$N$209=V94)*($P$2:$P$209="Long Term Rental")*($Y$2:$Y$209<>""),"")))} | AB94: =IF(AND(V94="Villa",X94<>"",AA94<>""),(AA94*12/X94)*100,"") | AC94: {=IFERROR(MEDIAN(_xlfn._xlws.FILTER($Q$2:$Q$209,($M$2:$M$209=U94)*($P$2:$P$209="Short Term Rental")*($Q$2:$Q$209<>""))),"")}
A95: K0094 | B95: Two BHK Independent House for sale in Kashele Village | C95: Kashele Village | D95: Independent House | E95: Two BHK | F95: 2342 | G95: sqft | H95: 94.58 | I95: Lakh | J95: One-time | K95: Active | M95: =_xlfn.XLOOKUP(TRIM(C95),MAPPING!A:A,MAPPING!B:B,"CHECK") -> Kashele | N95: =_xlfn.XLOOKUP(D95,MAPPING!G:G,MAPPING!H:H,"CHECK") -> Villa | O95: =_xlfn.XLOOKUP(E95,MAPPING!J:J,MAPPING!K:K,"CHECK") -> 2 BHK | P95: =_xlfn.XLOOKUP(J95,MAPPING!M:M,MAPPING!N:N,"CHECK") -> Resale | Q95: =IF(I95="INR",H95,IF(I95="Lakh",H95*100000,IF(I95="Crore",H95*10000000,IF(I95="Thousand",H95*1000,"")))) -> 9458000 | R95: =IF(G95="sqft",F95,IF(G95="sqyd",F95*9,IF(G95="acre",F95*43560,IF(G95="guntha",F95*1089,IF(G95="hectare",F95*107639.1,""))))) -> 2342 | S95: =IF(AND(P95="Resale",R95>0),Q95/R95,"") -> 4038.4287 | W95: =COUNTIFS($M$2:$M$209,U95,$N$2:$N$209,V95,$P$2:$P$209,"Resale") -> 0 | X95: {=IFERROR(MEDIAN(_xlfn._xlws.FILTER($S$2:$S$209,($M$2:$M$209=U95)*($N$2:$N$209=V95)*($P$2:$P$209="Resale")*($S$2:$S$209<>""))),"")} | Y95: =IF(AND(P95="Long Term Rental",R95>0),Q95/R95,"") | Z95: =COUNTIFS($M$2:$M$209,U95,$P$2:$P$209,"Long Term Rental") -> 0 | AA95: {=IF(Z95=0,"",MEDIAN(_xlfn._xlws.FILTER($Y$2:$Y$209,($M$2:$M$209=U95)*($N$2:$N$209=V95)*($P$2:$P$209="Long Term Rental")*($Y$2:$Y$209<>""),"")))} | AB95: =IF(AND(V95="Villa",X95<>"",AA95<>""),(AA95*12/X95)*100,"") | AC95: {=IFERROR(MEDIAN(_xlfn._xlws.FILTER($Q$2:$Q$209,($M$2:$M$209=U95)*($P$2:$P$209="Short Term Rental")*($Q$2:$Q$209<>""))),"")}
A96: K0095 | B96: Farm for sale in Kashele | C96: Kashele | D96: Farm | E96: NA | F96: 1.9 | G96: acre | H96: 1.05 | I96: Crore | J96: One-time | K96: Sold | M96: =_xlfn.XLOOKUP(TRIM(C96),MAPPING!A:A,MAPPING!B:B,"CHECK") -> Kashele | N96: =_xlfn.XLOOKUP(D96,MAPPING!G:G,MAPPING!H:H,"CHECK") -> Farmland | O96: =_xlfn.XLOOKUP(E96,MAPPING!J:J,MAPPING!K:K,"CHECK") -> NA | P96: =_xlfn.XLOOKUP(J96,MAPPING!M:M,MAPPING!N:N,"CHECK") -> Resale | Q96: =IF(I96="INR",H96,IF(I96="Lakh",H96*100000,IF(I96="Crore",H96*10000000,IF(I96="Thousand",H96*1000,"")))) -> 10500000 | R96: =IF(G96="sqft",F96,IF(G96="sqyd",F96*9,IF(G96="acre",F96*43560,IF(G96="guntha",F96*1089,IF(G96="hectare",F96*107639.1,""))))) -> 82764 | S96: =IF(AND(P96="Resale",R96>0),Q96/R96,"") -> 126.86675 | W96: =COUNTIFS($M$2:$M$209,U96,$N$2:$N$209,V96,$P$2:$P$209,"Resale") -> 0 | X96: {=IFERROR(MEDIAN(_xlfn._xlws.FILTER($S$2:$S$209,($M$2:$M$209=U96)*($N$2:$N$209=V96)*($P$2:$P$209="Resale")*($S$2:$S$209<>""))),"")} | Y96: =IF(AND(P96="Long Term Rental",R96>0),Q96/R96,"") | Z96: =COUNTIFS($M$2:$M$209,U96,$P$2:$P$209,"Long Term Rental") -> 0 | AA96: {=IF(Z96=0,"",MEDIAN(_xlfn._xlws.FILTER($Y$2:$Y$209,($M$2:$M$209=U96)*($N$2:$N$209=V96)*($P$2:$P$209="Long Term Rental")*($Y$2:$Y$209<>""),"")))} | AB96: =IF(AND(V96="Villa",X96<>"",AA96<>""),(AA96*12/X96)*100,"") | AC96: {=IFERROR(MEDIAN(_xlfn._xlws.FILTER($Q$2:$Q$209,($M$2:$M$209=U96)*($P$2:$P$209="Short Term Rental")*($Q$2:$Q$209<>""))),"")}
A97: K0096 | B97: Agricultural Land for sale in Kashele | C97: Kashele | D97: Agricultural Land | E97: NA | F97: 3.62 | G97: acre | H97: 2.11 | I97: Crore | J97: One-time | K97: Active | L97: Owner quoted 2.11 Crore verbally, listing price not updated on portal | M97: =_xlfn.XLOOKUP(TRIM(C97),MAPPING!A:A,MAPPING!B:B,"CHECK") -> Kashele | N97: =_xlfn.XLOOKUP(D97,MAPPING!G:G,MAPPING!H:H,"CHECK") -> Farmland | O97: =_xlfn.XLOOKUP(E97,MAPPING!J:J,MAPPING!K:K,"CHECK") -> NA | P97: =_xlfn.XLOOKUP(J97,MAPPING!M:M,MAPPING!N:N,"CHECK") -> Resale | Q97: =IF(I97="INR",H97,IF(I97="Lakh",H97*100000,IF(I97="Crore",H97*10000000,IF(I97="Thousand",H97*1000,"")))) -> 21100000 | R97: =IF(G97="sqft",F97,IF(G97="sqyd",F97*9,IF(G97="acre",F97*43560,IF(G97="guntha",F97*1089,IF(G97="hectare",F97*107639.1,""))))) -> 157687.2 | S97: =IF(AND(P97="Resale",R97>0),Q97/R97,"") -> 133.80921 | W97: =COUNTIFS($M$2:$M$209,U97,$N$2:$N$209,V97,$P$2:$P$209,"Resale") -> 0 | X97: {=IFERROR(MEDIAN(_xlfn._xlws.FILTER($S$2:$S$209,($M$2:$M$209=U97)*($N$2:$N$209=V97)*($P$2:$P$209="Resale")*($S$2:$S$209<>""))),"")} | Y97: =IF(AND(P97="Long Term Rental",R97>0),Q97/R97,"") | Z97: =COUNTIFS($M$2:$M$209,U97,$P$2:$P$209,"Long Term Rental") -> 0 | AA97: {=IF(Z97=0,"",MEDIAN(_xlfn._xlws.FILTER($Y$2:$Y$209,($M$2:$M$209=U97)*($N$2:$N$209=V97)*($P$2:$P$209="Long Term Rental")*($Y$2:$Y$209<>""),"")))} | AB97: =IF(AND(V97="Villa",X97<>"",AA97<>""),(AA97*12/X97)*100,"") | AC97: {=IFERROR(MEDIAN(_xlfn._xlws.FILTER($Q$2:$Q$209,($M$2:$M$209=U97)*($P$2:$P$209="Short Term Rental")*($Q$2:$Q$209<>""))),"")}
A98: K0097 | B98: Plot for sale in Kashele Phata | C98: Kashele Phata | D98: Plot | E98: NA | G98: guntha | H98: 75.48 | I98: Lakh | J98: One-time | K98: Active | M98: =_xlfn.XLOOKUP(TRIM(C98),MAPPING!A:A,MAPPING!B:B,"CHECK") -> Kashele | N98: =_xlfn.XLOOKUP(D98,MAPPING!G:G,MAPPING!H:H,"CHECK") -> Plot | O98: =_xlfn.XLOOKUP(E98,MAPPING!J:J,MAPPING!K:K,"CHECK") -> NA | P98: =_xlfn.XLOOKUP(J98,MAPPING!M:M,MAPPING!N:N,"CHECK") -> Resale | Q98: =IF(I98="INR",H98,IF(I98="Lakh",H98*100000,IF(I98="Crore",H98*10000000,IF(I98="Thousand",H98*1000,"")))) -> 7548000 | R98: =IF(G98="sqft",F98,IF(G98="sqyd",F98*9,IF(G98="acre",F98*43560,IF(G98="guntha",F98*1089,IF(G98="hectare",F98*107639.1,""))))) -> 0 | S98: =IF(AND(P98="Resale",R98>0),Q98/R98,"") | W98: =COUNTIFS($M$2:$M$209,U98,$N$2:$N$209,V98,$P$2:$P$209,"Resale") -> 0 | X98: {=IFERROR(MEDIAN(_xlfn._xlws.FILTER($S$2:$S$209,($M$2:$M$209=U98)*($N$2:$N$209=V98)*($P$2:$P$209="Resale")*($S$2:$S$209<>""))),"")} | Y98: =IF(AND(P98="Long Term Rental",R98>0),Q98/R98,"") | Z98: =COUNTIFS($M$2:$M$209,U98,$P$2:$P$209,"Long Term Rental") -> 0 | AA98: {=IF(Z98=0,"",MEDIAN(_xlfn._xlws.FILTER($Y$2:$Y$209,($M$2:$M$209=U98)*($N$2:$N$209=V98)*($P$2:$P$209="Long Term Rental")*($Y$2:$Y$209<>""),"")))} | AB98: =IF(AND(V98="Villa",X98<>"",AA98<>""),(AA98*12/X98)*100,"") | AC98: {=IFERROR(MEDIAN(_xlfn._xlws.FILTER($Q$2:$Q$209,($M$2:$M$209=U98)*($P$2:$P$209="Short Term Rental")*($Q$2:$Q$209<>""))),"")}
A99: K0098 | B99: 4BHK Villa for sale in Kashele Village | C99: Kashele | D99: Villa | E99: 4BHK | F99: 903 | G99: sqft | H99: 34.85 | I99: Lakh | J99: One-time | K99: Active | M99: =_xlfn.XLOOKUP(TRIM(C99),MAPPING!A:A,MAPPING!B:B,"CHECK") -> Kashele | N99: =_xlfn.XLOOKUP(D99,MAPPING!G:G,MAPPING!H:H,"CHECK") -> Villa | O99: =_xlfn.XLOOKUP(E99,MAPPING!J:J,MAPPING!K:K,"CHECK") -> 4 BHK | P99: =_xlfn.XLOOKUP(J99,MAPPING!M:M,MAPPING!N:N,"CHECK") -> Resale | Q99: =IF(I99="INR",H99,IF(I99="Lakh",H99*100000,IF(I99="Crore",H99*10000000,IF(I99="Thousand",H99*1000,"")))) -> 3485000 | R99: =IF(G99="sqft",F99,IF(G99="sqyd",F99*9,IF(G99="acre",F99*43560,IF(G99="guntha",F99*1089,IF(G99="hectare",F99*107639.1,""))))) -> 903 | S99: =IF(AND(P99="Resale",R99>0),Q99/R99,"") -> 3859.3577 | W99: =COUNTIFS($M$2:$M$209,U99,$N$2:$N$209,V99,$P$2:$P$209,"Resale") -> 0 | X99: {=IFERROR(MEDIAN(_xlfn._xlws.FILTER($S$2:$S$209,($M$2:$M$209=U99)*($N$2:$N$209=V99)*($P$2:$P$209="Resale")*($S$2:$S$209<>""))),"")} | Y99: =IF(AND(P99="Long Term Rental",R99>0),Q99/R99,"") | Z99: =COUNTIFS($M$2:$M$209,U99,$P$2:$P$209,"Long Term Rental") -> 0 | AA99: {=IF(Z99=0,"",MEDIAN(_xlfn._xlws.FILTER($Y$2:$Y$209,($M$2:$M$209=U99)*($N$2:$N$209=V99)*($P$2:$P$209="Long Term Rental")*($Y$2:$Y$209<>""),"")))} | AB99: =IF(AND(V99="Villa",X99<>"",AA99<>""),(AA99*12/X99)*100,"") | AC99: {=IFERROR(MEDIAN(_xlfn._xlws.FILTER($Q$2:$Q$209,($M$2:$M$209=U99)*($P$2:$P$209="Short Term Rental")*($Q$2:$Q$209<>""))),"")}
A100: K0099 | B100: Plot for sale in Kashele Phata | C100: Kashele Phata | D100: Plot | E100: NA | F100: 3.84 | G100: acre | H100: 13.54 | I100: Crore | J100: One-time | K100: Active | M100: =_xlfn.XLOOKUP(TRIM(C100),MAPPING!A:A,MAPPING!B:B,"CHECK") -> Kashele | N100: =_xlfn.XLOOKUP(D100,MAPPING!G:G,MAPPING!H:H,"CHECK") -> Plot | O100: =_xlfn.XLOOKUP(E100,MAPPING!J:J,MAPPING!K:K,"CHECK") -> NA | P100: =_xlfn.XLOOKUP(J100,MAPPING!M:M,MAPPING!N:N,"CHECK") -> Resale | Q100: =IF(I100="INR",H100,IF(I100="Lakh",H100*100000,IF(I100="Crore",H100*10000000,IF(I100="Thousand",H100*1000,"")))) -> 135400000 | R100: =IF(G100="sqft",F100,IF(G100="sqyd",F100*9,IF(G100="acre",F100*43560,IF(G100="guntha",F100*1089,IF(G100="hectare",F100*107639.1,""))))) -> 167270.4 | S100: =IF(AND(P100="Resale",R100>0),Q100/R100,"") -> 809.46778 | W100: =COUNTIFS($M$2:$M$209,U100,$N$2:$N$209,V100,$P$2:$P$209,"Resale") -> 0 | X100: {=IFERROR(MEDIAN(_xlfn._xlws.FILTER($S$2:$S$209,($M$2:$M$209=U100)*($N$2:$N$209=V100)*($P$2:$P$209="Resale")*($S$2:$S$209<>""))),"")} | Y100: =IF(AND(P100="Long Term Rental",R100>0),Q100/R100,"") | Z100: =COUNTIFS($M$2:$M$209,U100,$P$2:$P$209,"Long Term Rental") -> 0 | AA100: {=IF(Z100=0,"",MEDIAN(_xlfn._xlws.FILTER($Y$2:$Y$209,($M$2:$M$209=U100)*($N$2:$N$209=V100)*($P$2:$P$209="Long Term Rental")*($Y$2:$Y$209<>""),"")))} | AB100: =IF(AND(V100="Villa",X100<>"",AA100<>""),(AA100*12/X100)*100,"") | AC100: {=IFERROR(MEDIAN(_xlfn._xlws.FILTER($Q$2:$Q$209,($M$2:$M$209=U100)*($P$2:$P$209="Short Term Rental")*($Q$2:$Q$209<>""))),"")}
A101: K0100 | B101: 2 BHK Villa for sale in Kashele Phata | C101: Kashele Phata | D101: Villa | E101: 2 BHK | F101: 1850 | G101: sqft | H101: 56.88 | I101: Lakh | J101: One-time | K101: Price on Request | M101: =_xlfn.XLOOKUP(TRIM(C101),MAPPING!A:A,MAPPING!B:B,"CHECK") -> Kashele | N101: =_xlfn.XLOOKUP(D101,MAPPING!G:G,MAPPING!H:H,"CHECK") -> Villa | O101: =_xlfn.XLOOKUP(E101,MAPPING!J:J,MAPPING!K:K,"CHECK") -> 2 BHK | P101: =_xlfn.XLOOKUP(J101,MAPPING!M:M,MAPPING!N:N,"CHECK") -> Resale | Q101: =IF(I101="INR",H101,IF(I101="Lakh",H101*100000,IF(I101="Crore",H101*10000000,IF(I101="Thousand",H101*1000,"")))) -> 5688000 | R101: =IF(G101="sqft",F101,IF(G101="sqyd",F101*9,IF(G101="acre",F101*43560,IF(G101="guntha",F101*1089,IF(G101="hectare",F101*107639.1,""))))) -> 1850 | S101: =IF(AND(P101="Resale",R101>0),Q101/R101,"") -> 3074.5946 | W101: =COUNTIFS($M$2:$M$209,U101,$N$2:$N$209,V101,$P$2:$P$209,"Resale") -> 0 | X101: {=IFERROR(MEDIAN(_xlfn._xlws.FILTER($S$2:$S$209,($M$2:$M$209=U101)*($N$2:$N$209=V101)*($P$2:$P$209="Resale")*($S$2:$S$209<>""))),"")} | Y101: =IF(AND(P101="Long Term Rental",R101>0),Q101/R101,"") | Z101: =COUNTIFS($M$2:$M$209,U101,$P$2:$P$209,"Long Term Rental") -> 0 | AA101: {=IF(Z101=0,"",MEDIAN(_xlfn._xlws.FILTER($Y$2:$Y$209,($M$2:$M$209=U101)*($N$2:$N$209=V101)*($P$2:$P$209="Long Term Rental")*($Y$2:$Y$209<>""),"")))} | AB101: =IF(AND(V101="Villa",X101<>"",AA101<>""),(AA101*12/X101)*100,"") | AC101: {=IFERROR(MEDIAN(_xlfn._xlws.FILTER($Q$2:$Q$209,($M$2:$M$209=U101)*($P$2:$P$209="Short Term Rental")*($Q$2:$Q$209<>""))),"")}
A102: K0101 | B102: 3 BHK Villa for sale in Kasheli | C102: Kasheli | D102: Villa | E102: 3 BHK | F102: 1054 | G102: sqft | H102: 39.51 | I102: Lakh | J102: One-time | K102: Active | M102: =_xlfn.XLOOKUP(TRIM(C102),MAPPING!A:A,MAPPING!B:B,"CHECK") -> Kashele | N102: =_xlfn.XLOOKUP(D102,MAPPING!G:G,MAPPING!H:H,"CHECK") -> Villa | O102: =_xlfn.XLOOKUP(E102,MAPPING!J:J,MAPPING!K:K,"CHECK") -> 3 BHK | P102: =_xlfn.XLOOKUP(J102,MAPPING!M:M,MAPPING!N:N,"CHECK") -> Resale | Q102: =IF(I102="INR",H102,IF(I102="Lakh",H102*100000,IF(I102="Crore",H102*10000000,IF(I102="Thousand",H102*1000,"")))) -> 3951000 | R102: =IF(G102="sqft",F102,IF(G102="sqyd",F102*9,IF(G102="acre",F102*43560,IF(G102="guntha",F102*1089,IF(G102="hectare",F102*107639.1,""))))) -> 1054 | S102: =IF(AND(P102="Resale",R102>0),Q102/R102,"") -> 3748.5769 | W102: =COUNTIFS($M$2:$M$209,U102,$N$2:$N$209,V102,$P$2:$P$209,"Resale") -> 0 | X102: {=IFERROR(MEDIAN(_xlfn._xlws.FILTER($S$2:$S$209,($M$2:$M$209=U102)*($N$2:$N$209=V102)*($P$2:$P$209="Resale")*($S$2:$S$209<>""))),"")} | Y102: =IF(AND(P102="Long Term Rental",R102>0),Q102/R102,"") | Z102: =COUNTIFS($M$2:$M$209,U102,$P$2:$P$209,"Long Term Rental") -> 0 | AA102: {=IF(Z102=0,"",MEDIAN(_xlfn._xlws.FILTER($Y$2:$Y$209,($M$2:$M$209=U102)*($N$2:$N$209=V102)*($P$2:$P$209="Long Term Rental")*($Y$2:$Y$209<>""),"")))} | AB102: =IF(AND(V102="Villa",X102<>"",AA102<>""),(AA102*12/X102)*100,"") | AC102: {=IFERROR(MEDIAN(_xlfn._xlws.FILTER($Q$2:$Q$209,($M$2:$M$209=U102)*($P$2:$P$209="Short Term Rental")*($Q$2:$Q$209<>""))),"")}
A103: K0102 | B103: Plot for sale in Kashele Phata | C103: Kashele Phata | D103: Plot | E103: NA | G103: guntha | H103: 2.13 | I103: Crore | J103: One-time | K103: Active | M103: =_xlfn.XLOOKUP(TRIM(C103),MAPPING!A:A,MAPPING!B:B,"CHECK") -> Kashele | N103: =_xlfn.XLOOKUP(D103,MAPPING!G:G,MAPPING!H:H,"CHECK") -> Plot | O103: =_xlfn.XLOOKUP(E103,MAPPING!J:J,MAPPING!K:K,"CHECK") -> NA | P103: =_xlfn.XLOOKUP(J103,MAPPING!M:M,MAPPING!N:N,"CHECK") -> Resale | Q103: =IF(I103="INR",H103,IF(I103="Lakh",H103*100000,IF(I103="Crore",H103*10000000,IF(I103="Thousand",H103*1000,"")))) -> 21300000 | R103: =IF(G103="sqft",F103,IF(G103="sqyd",F103*9,IF(G103="acre",F103*43560,IF(G103="guntha",F103*1089,IF(G103="hectare",F103*107639.1,""))))) -> 0 | S103: =IF(AND(P103="Resale",R103>0),Q103/R103,"") | W103: =COUNTIFS($M$2:$M$209,U103,$N$2:$N$209,V103,$P$2:$P$209,"Resale") -> 0 | X103: {=IFERROR(MEDIAN(_xlfn._xlws.FILTER($S$2:$S$209,($M$2:$M$209=U103)*($N$2:$N$209=V103)*($P$2:$P$209="Resale")*($S$2:$S$209<>""))),"")} | Y103: =IF(AND(P103="Long Term Rental",R103>0),Q103/R103,"") | Z103: =COUNTIFS($M$2:$M$209,U103,$P$2:$P$209,"Long Term Rental") -> 0 | AA103: {=IF(Z103=0,"",MEDIAN(_xlfn._xlws.FILTER($Y$2:$Y$209,($M$2:$M$209=U103)*($N$2:$N$209=V103)*($P$2:$P$209="Long Term Rental")*($Y$2:$Y$209<>""),"")))} | AB103: =IF(AND(V103="Villa",X103<>"",AA103<>""),(AA103*12/X103)*100,"") | AC103: {=IFERROR(MEDIAN(_xlfn._xlws.FILTER($Q$2:$Q$209,($M$2:$M$209=U103)*($P$2:$P$209="Short Term Rental")*($Q$2:$Q$209<>""))),"")}
A104: K0103 | B104: Land Parcel for sale in Kashele Village | C104: Kashele Village | D104: Land Parcel | E104: NA | F104: 1.52 | G104: acre | H104: 5.68 | I104: Crore | J104: One-time | K104: Price on Request | M104: =_xlfn.XLOOKUP(TRIM(C104),MAPPING!A:A,MAPPING!B:B,"CHECK") -> Kashele | N104: =_xlfn.XLOOKUP(D104,MAPPING!G:G,MAPPING!H:H,"CHECK") -> Plot | O104: =_xlfn.XLOOKUP(E104,MAPPING!J:J,MAPPING!K:K,"CHECK") -> NA | P104: =_xlfn.XLOOKUP(J104,MAPPING!M:M,MAPPING!N:N,"CHECK") -> Resale | Q104: =IF(I104="INR",H104,IF(I104="Lakh",H104*100000,IF(I104="Crore",H104*10000000,IF(I104="Thousand",H104*1000,"")))) -> 56800000 | R104: =IF(G104="sqft",F104,IF(G104="sqyd",F104*9,IF(G104="acre",F104*43560,IF(G104="guntha",F104*1089,IF(G104="hectare",F104*107639.1,""))))) -> 66211.2 | S104: =IF(AND(P104="Resale",R104>0),Q104/R104,"") -> 857.86091 | W104: =COUNTIFS($M$2:$M$209,U104,$N$2:$N$209,V104,$P$2:$P$209,"Resale") -> 0 | X104: {=IFERROR(MEDIAN(_xlfn._xlws.FILTER($S$2:$S$209,($M$2:$M$209=U104)*($N$2:$N$209=V104)*($P$2:$P$209="Resale")*($S$2:$S$209<>""))),"")} | Y104: =IF(AND(P104="Long Term Rental",R104>0),Q104/R104,"") | Z104: =COUNTIFS($M$2:$M$209,U104,$P$2:$P$209,"Long Term Rental") -> 0 | AA104: {=IF(Z104=0,"",MEDIAN(_xlfn._xlws.FILTER($Y$2:$Y$209,($M$2:$M$209=U104)*($N$2:$N$209=V104)*($P$2:$P$209="Long Term Rental")*($Y$2:$Y$209<>""),"")))} | AB104: =IF(AND(V104="Villa",X104<>"",AA104<>""),(AA104*12/X104)*100,"") | AC104: {=IFERROR(MEDIAN(_xlfn._xlws.FILTER($Q$2:$Q$209,($M$2:$M$209=U104)*($P$2:$P$209="Short Term Rental")*($Q$2:$Q$209<>""))),"")}
A105: K0104 | B105: NA Plot for sale in Kashele Village | C105: Kashele Village | D105: NA Plot | E105: NA | F105: 2658 | G105: sqft | H105: 18.5 | I105: Lakh | J105: One-time | K105: Active | M105: =_xlfn.XLOOKUP(TRIM(C105),MAPPING!A:A,MAPPING!B:B,"CHECK") -> Kashele | N105: =_xlfn.XLOOKUP(D105,MAPPING!G:G,MAPPING!H:H,"CHECK") -> Plot | O105: =_xlfn.XLOOKUP(E105,MAPPING!J:J,MAPPING!K:K,"CHECK") -> NA | P105: =_xlfn.XLOOKUP(J105,MAPPING!M:M,MAPPING!N:N,"CHECK") -> Resale | Q105: =IF(I105="INR",H105,IF(I105="Lakh",H105*100000,IF(I105="Crore",H105*10000000,IF(I105="Thousand",H105*1000,"")))) -> 1850000 | R105: =IF(G105="sqft",F105,IF(G105="sqyd",F105*9,IF(G105="acre",F105*43560,IF(G105="guntha",F105*1089,IF(G105="hectare",F105*107639.1,""))))) -> 2658 | S105: =IF(AND(P105="Resale",R105>0),Q105/R105,"") -> 696.01204 | W105: =COUNTIFS($M$2:$M$209,U105,$N$2:$N$209,V105,$P$2:$P$209,"Resale") -> 0 | X105: {=IFERROR(MEDIAN(_xlfn._xlws.FILTER($S$2:$S$209,($M$2:$M$209=U105)*($N$2:$N$209=V105)*($P$2:$P$209="Resale")*($S$2:$S$209<>""))),"")} | Y105: =IF(AND(P105="Long Term Rental",R105>0),Q105/R105,"") | Z105: =COUNTIFS($M$2:$M$209,U105,$P$2:$P$209,"Long Term Rental") -> 0 | AA105: {=IF(Z105=0,"",MEDIAN(_xlfn._xlws.FILTER($Y$2:$Y$209,($M$2:$M$209=U105)*($N$2:$N$209=V105)*($P$2:$P$209="Long Term Rental")*($Y$2:$Y$209<>""),"")))} | AB105: =IF(AND(V105="Villa",X105<>"",AA105<>""),(AA105*12/X105)*100,"") | AC105: {=IFERROR(MEDIAN(_xlfn._xlws.FILTER($Q$2:$Q$209,($M$2:$M$209=U105)*($P$2:$P$209="Short Term Rental")*($Q$2:$Q$209<>""))),"")}
A106: K0105 | B106: NA Plot for sale in Kashele | C106: Kashele | D106: NA Plot | E106: NA | F106: 2566 | G106: sqft | H106: 17.29 | I106: Lakh | J106: One-time | K106: Active | M106: =_xlfn.XLOOKUP(TRIM(C106),MAPPING!A:A,MAPPING!B:B,"CHECK") -> Kashele | N106: =_xlfn.XLOOKUP(D106,MAPPING!G:G,MAPPING!H:H,"CHECK") -> Plot | O106: =_xlfn.XLOOKUP(E106,MAPPING!J:J,MAPPING!K:K,"CHECK") -> NA | P106: =_xlfn.XLOOKUP(J106,MAPPING!M:M,MAPPING!N:N,"CHECK") -> Resale | Q106: =IF(I106="INR",H106,IF(I106="Lakh",H106*100000,IF(I106="Crore",H106*10000000,IF(I106="Thousand",H106*1000,"")))) -> 1729000 | R106: =IF(G106="sqft",F106,IF(G106="sqyd",F106*9,IF(G106="acre",F106*43560,IF(G106="guntha",F106*1089,IF(G106="hectare",F106*107639.1,""))))) -> 2566 | S106: =IF(AND(P106="Resale",R106>0),Q106/R106,"") -> 673.81138 | W106: =COUNTIFS($M$2:$M$209,U106,$N$2:$N$209,V106,$P$2:$P$209,"Resale") -> 0 | X106: {=IFERROR(MEDIAN(_xlfn._xlws.FILTER($S$2:$S$209,($M$2:$M$209=U106)*($N$2:$N$209=V106)*($P$2:$P$209="Resale")*($S$2:$S$209<>""))),"")} | Y106: =IF(AND(P106="Long Term Rental",R106>0),Q106/R106,"") | Z106: =COUNTIFS($M$2:$M$209,U106,$P$2:$P$209,"Long Term Rental") -> 0 | AA106: {=IF(Z106=0,"",MEDIAN(_xlfn._xlws.FILTER($Y$2:$Y$209,($M$2:$M$209=U106)*($N$2:$N$209=V106)*($P$2:$P$209="Long Term Rental")*($Y$2:$Y$209<>""),"")))} | AB106: =IF(AND(V106="Villa",X106<>"",AA106<>""),(AA106*12/X106)*100,"") | AC106: {=IFERROR(MEDIAN(_xlfn._xlws.FILTER($Q$2:$Q$209,($M$2:$M$209=U106)*($P$2:$P$209="Short Term Rental")*($Q$2:$Q$209<>""))),"")}
A107: K0106 | B107: Farm for sale in Kashele | C107: Kashele | D107: Farm | E107: NA | F107: 1.05 | G107: acre | H107: 51.33 | I107: Lakh | J107: One-time | K107: Sold | M107: =_xlfn.XLOOKUP(TRIM(C107),MAPPING!A:A,MAPPING!B:B,"CHECK") -> Kashele | N107: =_xlfn.XLOOKUP(D107,MAPPING!G:G,MAPPING!H:H,"CHECK") -> Farmland | O107: =_xlfn.XLOOKUP(E107,MAPPING!J:J,MAPPING!K:K,"CHECK") -> NA | P107: =_xlfn.XLOOKUP(J107,MAPPING!M:M,MAPPING!N:N,"CHECK") -> Resale | Q107: =IF(I107="INR",H107,IF(I107="Lakh",H107*100000,IF(I107="Crore",H107*10000000,IF(I107="Thousand",H107*1000,"")))) -> 5133000 | R107: =IF(G107="sqft",F107,IF(G107="sqyd",F107*9,IF(G107="acre",F107*43560,IF(G107="guntha",F107*1089,IF(G107="hectare",F107*107639.1,""))))) -> 45738 | S107: =IF(AND(P107="Resale",R107>0),Q107/R107,"") -> 112.22616 | W107: =COUNTIFS($M$2:$M$209,U107,$N$2:$N$209,V107,$P$2:$P$209,"Resale") -> 0 | X107: {=IFERROR(MEDIAN(_xlfn._xlws.FILTER($S$2:$S$209,($M$2:$M$209=U107)*($N$2:$N$209=V107)*($P$2:$P$209="Resale")*($S$2:$S$209<>""))),"")} | Y107: =IF(AND(P107="Long Term Rental",R107>0),Q107/R107,"") | Z107: =COUNTIFS($M$2:$M$209,U107,$P$2:$P$209,"Long Term Rental") -> 0 | AA107: {=IF(Z107=0,"",MEDIAN(_xlfn._xlws.FILTER($Y$2:$Y$209,($M$2:$M$209=U107)*($N$2:$N$209=V107)*($P$2:$P$209="Long Term Rental")*($Y$2:$Y$209<>""),"")))} | AB107: =IF(AND(V107="Villa",X107<>"",AA107<>""),(AA107*12/X107)*100,"") | AC107: {=IFERROR(MEDIAN(_xlfn._xlws.FILTER($Q$2:$Q$209,($M$2:$M$209=U107)*($P$2:$P$209="Short Term Rental")*($Q$2:$Q$209<>""))),"")}
A108: K0107 | B108: Farm for sale in Kashele Village | C108: Kashele Village | D108: Farm | E108: NA | F108: 3.37 | G108: acre | H108: 1.95 | I108: Crore | J108: One-time | K108: Price on Request | M108: =_xlfn.XLOOKUP(TRIM(C108),MAPPING!A:A,MAPPING!B:B,"CHECK") -> Kashele | N108: =_xlfn.XLOOKUP(D108,MAPPING!G:G,MAPPING!H:H,"CHECK") -> Farmland | O108: =_xlfn.XLOOKUP(E108,MAPPING!J:J,MAPPING!K:K,"CHECK") -> NA | P108: =_xlfn.XLOOKUP(J108,MAPPING!M:M,MAPPING!N:N,"CHECK") -> Resale | Q108: =IF(I108="INR",H108,IF(I108="Lakh",H108*100000,IF(I108="Crore",H108*10000000,IF(I108="Thousand",H108*1000,"")))) -> 19500000 | R108: =IF(G108="sqft",F108,IF(G108="sqyd",F108*9,IF(G108="acre",F108*43560,IF(G108="guntha",F108*1089,IF(G108="hectare",F108*107639.1,""))))) -> 146797.2 | S108: =IF(AND(P108="Resale",R108>0),Q108/R108,"") -> 132.83632 | W108: =COUNTIFS($M$2:$M$209,U108,$N$2:$N$209,V108,$P$2:$P$209,"Resale") -> 0 | X108: {=IFERROR(MEDIAN(_xlfn._xlws.FILTER($S$2:$S$209,($M$2:$M$209=U108)*($N$2:$N$209=V108)*($P$2:$P$209="Resale")*($S$2:$S$209<>""))),"")} | Y108: =IF(AND(P108="Long Term Rental",R108>0),Q108/R108,"") | Z108: =COUNTIFS($M$2:$M$209,U108,$P$2:$P$209,"Long Term Rental") -> 0 | AA108: {=IF(Z108=0,"",MEDIAN(_xlfn._xlws.FILTER($Y$2:$Y$209,($M$2:$M$209=U108)*($N$2:$N$209=V108)*($P$2:$P$209="Long Term Rental")*($Y$2:$Y$209<>""),"")))} | AB108: =IF(AND(V108="Villa",X108<>"",AA108<>""),(AA108*12/X108)*100,"") | AC108: {=IFERROR(MEDIAN(_xlfn._xlws.FILTER($Q$2:$Q$209,($M$2:$M$209=U108)*($P$2:$P$209="Short Term Rental")*($Q$2:$Q$209<>""))),"")}
A109: K0108 | B109: Two BHK Farmhouse for sale in Kasheli | C109: Kasheli | D109: Farmhouse | E109: Two BHK | F109: 2419 | G109: sqft | H109: 93.86 | I109: Lakh | J109: One-time | K109: Active | M109: =_xlfn.XLOOKUP(TRIM(C109),MAPPING!A:A,MAPPING!B:B,"CHECK") -> Kashele | N109: =_xlfn.XLOOKUP(D109,MAPPING!G:G,MAPPING!H:H,"CHECK") -> Villa | O109: =_xlfn.XLOOKUP(E109,MAPPING!J:J,MAPPING!K:K,"CHECK") -> 2 BHK | P109: =_xlfn.XLOOKUP(J109,MAPPING!M:M,MAPPING!N:N,"CHECK") -> Resale | Q109: =IF(I109="INR",H109,IF(I109="Lakh",H109*100000,IF(I109="Crore",H109*10000000,IF(I109="Thousand",H109*1000,"")))) -> 9386000 | R109: =IF(G109="sqft",F109,IF(G109="sqyd",F109*9,IF(G109="acre",F109*43560,IF(G109="guntha",F109*1089,IF(G109="hectare",F109*107639.1,""))))) -> 2419 | S109: =IF(AND(P109="Resale",R109>0),Q109/R109,"") -> 3880.1158 | W109: =COUNTIFS($M$2:$M$209,U109,$N$2:$N$209,V109,$P$2:$P$209,"Resale") -> 0 | X109: {=IFERROR(MEDIAN(_xlfn._xlws.FILTER($S$2:$S$209,($M$2:$M$209=U109)*($N$2:$N$209=V109)*($P$2:$P$209="Resale")*($S$2:$S$209<>""))),"")} | Y109: =IF(AND(P109="Long Term Rental",R109>0),Q109/R109,"") | Z109: =COUNTIFS($M$2:$M$209,U109,$P$2:$P$209,"Long Term Rental") -> 0 | AA109: {=IF(Z109=0,"",MEDIAN(_xlfn._xlws.FILTER($Y$2:$Y$209,($M$2:$M$209=U109)*($N$2:$N$209=V109)*($P$2:$P$209="Long Term Rental")*($Y$2:$Y$209<>""),"")))} | AB109: =IF(AND(V109="Villa",X109<>"",AA109<>""),(AA109*12/X109)*100,"") | AC109: {=IFERROR(MEDIAN(_xlfn._xlws.FILTER($Q$2:$Q$209,($M$2:$M$209=U109)*($P$2:$P$209="Short Term Rental")*($Q$2:$Q$209<>""))),"")}
A110: K0109 | B110: 2BHK Row House for rent in Kashele Phata | C110: Kashele Phata | D110: Row House | E110: 2BHK | F110: 1892 | G110: sqft | H110: 21200 | I110: INR | J110: Monthly | K110: Active | M110: =_xlfn.XLOOKUP(TRIM(C110),MAPPING!A:A,MAPPING!B:B,"CHECK") -> Kashele | N110: =_xlfn.XLOOKUP(D110,MAPPING!G:G,MAPPING!H:H,"CHECK") -> Villa | O110: =_xlfn.XLOOKUP(E110,MAPPING!J:J,MAPPING!K:K,"CHECK") -> 2 BHK | P110: =_xlfn.XLOOKUP(J110,MAPPING!M:M,MAPPING!N:N,"CHECK") -> Long Term Rental | Q110: =IF(I110="INR",H110,IF(I110="Lakh",H110*100000,IF(I110="Crore",H110*10000000,IF(I110="Thousand",H110*1000,"")))) -> 21200 | R110: =IF(G110="sqft",F110,IF(G110="sqyd",F110*9,IF(G110="acre",F110*43560,IF(G110="guntha",F110*1089,IF(G110="hectare",F110*107639.1,""))))) -> 1892 | S110: =IF(AND(P110="Resale",R110>0),Q110/R110,"") | W110: =COUNTIFS($M$2:$M$209,U110,$N$2:$N$209,V110,$P$2:$P$209,"Resale") -> 0 | X110: {=IFERROR(MEDIAN(_xlfn._xlws.FILTER($S$2:$S$209,($M$2:$M$209=U110)*($N$2:$N$209=V110)*($P$2:$P$209="Resale")*($S$2:$S$209<>""))),"")} | Y110: =IF(AND(P110="Long Term Rental",R110>0),Q110/R110,"") -> 11.205074 | Z110: =COUNTIFS($M$2:$M$209,U110,$P$2:$P$209,"Long Term Rental") -> 0 | AA110: {=IF(Z110=0,"",MEDIAN(_xlfn._xlws.FILTER($Y$2:$Y$209,($M$2:$M$209=U110)*($N$2:$N$209=V110)*($P$2:$P$209="Long Term Rental")*($Y$2:$Y$209<>""),"")))} | AB110: =IF(AND(V110="Villa",X110<>"",AA110<>""),(AA110*12/X110)*100,"") | AC110: {=IFERROR(MEDIAN(_xlfn._xlws.FILTER($Q$2:$Q$209,($M$2:$M$209=U110)*($P$2:$P$209="Short Term Rental")*($Q$2:$Q$209<>""))),"")}
A111: K0110 | B111: Two BHK Bungalow for rent in Kasheli | C111: Kasheli | D111: Bungalow | E111: Two BHK | F111: 1862 | G111: sqft | H111: 21300 | I111: INR | J111: Monthly | K111: Active | M111: =_xlfn.XLOOKUP(TRIM(C111),MAPPING!A:A,MAPPING!B:B,"CHECK") -> Kashele | N111: =_xlfn.XLOOKUP(D111,MAPPING!G:G,MAPPING!H:H,"CHECK") -> Villa | O111: =_xlfn.XLOOKUP(E111,MAPPING!J:J,MAPPING!K:K,"CHECK") -> 2 BHK | P111: =_xlfn.XLOOKUP(J111,MAPPING!M:M,MAPPING!N:N,"CHECK") -> Long Term Rental | Q111: =IF(I111="INR",H111,IF(I111="Lakh",H111*100000,IF(I111="Crore",H111*10000000,IF(I111="Thousand",H111*1000,"")))) -> 21300 | R111: =IF(G111="sqft",F111,IF(G111="sqyd",F111*9,IF(G111="acre",F111*43560,IF(G111="guntha",F111*1089,IF(G111="hectare",F111*107639.1,""))))) -> 1862 | S111: =IF(AND(P111="Resale",R111>0),Q111/R111,"") | W111: =COUNTIFS($M$2:$M$209,U111,$N$2:$N$209,V111,$P$2:$P$209,"Resale") -> 0 | X111: {=IFERROR(MEDIAN(_xlfn._xlws.FILTER($S$2:$S$209,($M$2:$M$209=U111)*($N$2:$N$209=V111)*($P$2:$P$209="Resale")*($S$2:$S$209<>""))),"")} | Y111: =IF(AND(P111="Long Term Rental",R111>0),Q111/R111,"") -> 11.439313 | Z111: =COUNTIFS($M$2:$M$209,U111,$P$2:$P$209,"Long Term Rental") -> 0 | AA111: {=IF(Z111=0,"",MEDIAN(_xlfn._xlws.FILTER($Y$2:$Y$209,($M$2:$M$209=U111)*($N$2:$N$209=V111)*($P$2:$P$209="Long Term Rental")*($Y$2:$Y$209<>""),"")))} | AB111: =IF(AND(V111="Villa",X111<>"",AA111<>""),(AA111*12/X111)*100,"") | AC111: {=IFERROR(MEDIAN(_xlfn._xlws.FILTER($Q$2:$Q$209,($M$2:$M$209=U111)*($P$2:$P$209="Short Term Rental")*($Q$2:$Q$209<>""))),"")}
A112: K0111 | B112: 4BHK Farmhouse for rent in Kashele Village | C112: Kashele Village | D112: Farmhouse | E112: 4BHK | F112: 2141 | G112: sqft | H112: 28000 | I112: INR | J112: Monthly | K112: Active | M112: =_xlfn.XLOOKUP(TRIM(C112),MAPPING!A:A,MAPPING!B:B,"CHECK") -> Kashele | N112: =_xlfn.XLOOKUP(D112,MAPPING!G:G,MAPPING!H:H,"CHECK") -> Villa | O112: =_xlfn.XLOOKUP(E112,MAPPING!J:J,MAPPING!K:K,"CHECK") -> 4 BHK | P112: =_xlfn.XLOOKUP(J112,MAPPING!M:M,MAPPING!N:N,"CHECK") -> Long Term Rental | Q112: =IF(I112="INR",H112,IF(I112="Lakh",H112*100000,IF(I112="Crore",H112*10000000,IF(I112="Thousand",H112*1000,"")))) -> 28000 | R112: =IF(G112="sqft",F112,IF(G112="sqyd",F112*9,IF(G112="acre",F112*43560,IF(G112="guntha",F112*1089,IF(G112="hectare",F112*107639.1,""))))) -> 2141 | S112: =IF(AND(P112="Resale",R112>0),Q112/R112,"") | W112: =COUNTIFS($M$2:$M$209,U112,$N$2:$N$209,V112,$P$2:$P$209,"Resale") -> 0 | X112: {=IFERROR(MEDIAN(_xlfn._xlws.FILTER($S$2:$S$209,($M$2:$M$209=U112)*($N$2:$N$209=V112)*($P$2:$P$209="Resale")*($S$2:$S$209<>""))),"")} | Y112: =IF(AND(P112="Long Term Rental",R112>0),Q112/R112,"") -> 13.078001 | Z112: =COUNTIFS($M$2:$M$209,U112,$P$2:$P$209,"Long Term Rental") -> 0 | AA112: {=IF(Z112=0,"",MEDIAN(_xlfn._xlws.FILTER($Y$2:$Y$209,($M$2:$M$209=U112)*($N$2:$N$209=V112)*($P$2:$P$209="Long Term Rental")*($Y$2:$Y$209<>""),"")))} | AB112: =IF(AND(V112="Villa",X112<>"",AA112<>""),(AA112*12/X112)*100,"") | AC112: {=IFERROR(MEDIAN(_xlfn._xlws.FILTER($Q$2:$Q$209,($M$2:$M$209=U112)*($P$2:$P$209="Short Term Rental")*($Q$2:$Q$209<>""))),"")}
A113: K0112 | B113: 2 BHK Bungalow for rent in Kashele | C113: Kashele | D113: Bungalow | E113: 2 BHK | F113: 1391 | G113: sqft | H113: 16800 | I113: INR | J113: Monthly | K113: Active | M113: =_xlfn.XLOOKUP(TRIM(C113),MAPPING!A:A,MAPPING!B:B,"CHECK") -> Kashele | N113: =_xlfn.XLOOKUP(D113,MAPPING!G:G,MAPPING!H:H,"CHECK") -> Villa | O113: =_xlfn.XLOOKUP(E113,MAPPING!J:J,MAPPING!K:K,"CHECK") -> 2 BHK | P113: =_xlfn.XLOOKUP(J113,MAPPING!M:M,MAPPING!N:N,"CHECK") -> Long Term Rental | Q113: =IF(I113="INR",H113,IF(I113="Lakh",H113*100000,IF(I113="Crore",H113*10000000,IF(I113="Thousand",H113*1000,"")))) -> 16800 | R113: =IF(G113="sqft",F113,IF(G113="sqyd",F113*9,IF(G113="acre",F113*43560,IF(G113="guntha",F113*1089,IF(G113="hectare",F113*107639.1,""))))) -> 1391 | S113: =IF(AND(P113="Resale",R113>0),Q113/R113,"") | W113: =COUNTIFS($M$2:$M$209,U113,$N$2:$N$209,V113,$P$2:$P$209,"Resale") -> 0 | X113: {=IFERROR(MEDIAN(_xlfn._xlws.FILTER($S$2:$S$209,($M$2:$M$209=U113)*($N$2:$N$209=V113)*($P$2:$P$209="Resale")*($S$2:$S$209<>""))),"")} | Y113: =IF(AND(P113="Long Term Rental",R113>0),Q113/R113,"") -> 12.077642 | Z113: =COUNTIFS($M$2:$M$209,U113,$P$2:$P$209,"Long Term Rental") -> 0 | AA113: {=IF(Z113=0,"",MEDIAN(_xlfn._xlws.FILTER($Y$2:$Y$209,($M$2:$M$209=U113)*($N$2:$N$209=V113)*($P$2:$P$209="Long Term Rental")*($Y$2:$Y$209<>""),"")))} | AB113: =IF(AND(V113="Villa",X113<>"",AA113<>""),(AA113*12/X113)*100,"") | AC113: {=IFERROR(MEDIAN(_xlfn._xlws.FILTER($Q$2:$Q$209,($M$2:$M$209=U113)*($P$2:$P$209="Short Term Rental")*($Q$2:$Q$209<>""))),"")}
A114: K0113 | B114: 2BHK Row House for rent in Kashele Phata | C114: Kashele Phata | D114: Row House | E114: 2BHK | F114: 1724 | G114: sqft | H114: 21500 | I114: INR | J114: Monthly | K114: Active | M114: =_xlfn.XLOOKUP(TRIM(C114),MAPPING!A:A,MAPPING!B:B,"CHECK") -> Kashele | N114: =_xlfn.XLOOKUP(D114,MAPPING!G:G,MAPPING!H:H,"CHECK") -> Villa | O114: =_xlfn.XLOOKUP(E114,MAPPING!J:J,MAPPING!K:K,"CHECK") -> 2 BHK | P114: =_xlfn.XLOOKUP(J114,MAPPING!M:M,MAPPING!N:N,"CHECK") -> Long Term Rental | Q114: =IF(I114="INR",H114,IF(I114="Lakh",H114*100000,IF(I114="Crore",H114*10000000,IF(I114="Thousand",H114*1000,"")))) -> 21500 | R114: =IF(G114="sqft",F114,IF(G114="sqyd",F114*9,IF(G114="acre",F114*43560,IF(G114="guntha",F114*1089,IF(G114="hectare",F114*107639.1,""))))) -> 1724 | S114: =IF(AND(P114="Resale",R114>0),Q114/R114,"") | W114: =COUNTIFS($M$2:$M$209,U114,$N$2:$N$209,V114,$P$2:$P$209,"Resale") -> 0 | X114: {=IFERROR(MEDIAN(_xlfn._xlws.FILTER($S$2:$S$209,($M$2:$M$209=U114)*($N$2:$N$209=V114)*($P$2:$P$209="Resale")*($S$2:$S$209<>""))),"")} | Y114: =IF(AND(P114="Long Term Rental",R114>0),Q114/R114,"") -> 12.470998 | Z114: =COUNTIFS($M$2:$M$209,U114,$P$2:$P$209,"Long Term Rental") -> 0 | AA114: {=IF(Z114=0,"",MEDIAN(_xlfn._xlws.FILTER($Y$2:$Y$209,($M$2:$M$209=U114)*($N$2:$N$209=V114)*($P$2:$P$209="Long Term Rental")*($Y$2:$Y$209<>""),"")))} | AB114: =IF(AND(V114="Villa",X114<>"",AA114<>""),(AA114*12/X114)*100,"") | AC114: {=IFERROR(MEDIAN(_xlfn._xlws.FILTER($Q$2:$Q$209,($M$2:$M$209=U114)*($P$2:$P$209="Short Term Rental")*($Q$2:$Q$209<>""))),"")}
...

Sheet MAPPING
A1: Raw Locality | B1: Micro Market | D1: Unique Raw Localities | G1: Raw_Asset_Type | H1: Asset_Class | J1: Raw_Configuration | K1: BHK_Configuration | M1: Vertical Evidence | N1: Vertical | P1: Unique Status
A2: =D2 -> Central Karjat | B2: Karjat Town | D2: {=_xlfn.UNIQUE(TRIM(CLEAN(MAIN!C2:C209)))} -> Central Karjat | G2: {=_xlfn.UNIQUE(MAIN!D2:D209)} -> NA Plot | H2: Plot | J2: {=_xlfn.UNIQUE(MAIN!E2:E209)} -> NA | K2: NA | M2: {=_xlfn.UNIQUE(MAIN!J2:J209)} -> One-time | N2: Resale | P2: {=_xlfn.UNIQUE(MAIN!K2:K209)} -> Active
A3: =D3 -> Karjat | B3: Karjat Town | D3: Karjat | G3: Bungalow | H3: Villa | J3: 4BHK | K3: 4 BHK | M3: Monthly | N3: Long Term Rental | P3: Price on Request
A4: =D4 -> Karjat Station Road | B4: Karjat Town | D4: Karjat Station Road | G4: Plot | H4: Plot | J4: 2BHK | K4: 2 BHK | M4: Per Night | N4: Short Term Rental | P4: Sold
A5: =D5 -> Karjat Town | B5: Karjat Town | D5: Karjat Town | G5: Land Parcel | H5: Plot | J5: Two BHK | K5: 2 BHK
A6: =D6 -> Karjat West | B6: Karjat Town | D6: Karjat West | G6: Farm | H6: Farmland | J6: 3 BHK | K6: 3 BHK
A7: =D7 -> Neral Rd | B7: Neral | D7: Neral Rd | G7: Independent House | H7: Villa | J7: 3BHK | K7: 3 BHK
A8: =D8 -> Neral | B8: Neral | D8: Neral | G8: Farmhouse | H8: Villa | J8: 2 BHK | K8: 2 BHK
A9: =D9 -> Near Neral Station | B9: Neral | D9: Near Neral Station | G9: Farm Land | H9: Farmland | J9: 3BR | K9: 3 BHK
A10: =D10 -> Neral Village | B10: Neral | D10: Neral Village | G10: Row House | H10: Villa
A11: =D11 -> Kasheli | B11: Kashele | D11: Kasheli | G11: Villa | H11: Villa
A12: =D12 -> Kashele Village | B12: Kashele | D12: Kashele Village | G12: Agricultural Land | H12: Farmland
A13: =D13 -> Kashele | B13: Kashele | D13: Kashele
A14: =D14 -> Kashele Phata | B14: Kashele | D14: Kashele Phata
A15: =D15 -> Kondhwal Valley | B15: Kondhwal Valley | D15: Kondhwal Valley
A16: =D16 -> Kondhwal | B16: Kondhwal Valley | D16: Kondhwal
A17: =D17 -> Kondhwal-Palasdari belt | B17: Kondhwal Valley | D17: Kondhwal-Palasdari belt
A18: =D18 -> Palasdari (Kondhwal) | B18: Kondhwal Valley | D18: Palasdari (Kondhwal)
A19: =D19 -> Near Matheran Road | B19: Matheran Road | D19: Near Matheran Road
A20: =D20 -> Matheran Road | B20: Matheran Road | D20: Matheran Road
A21: =D21 -> Matheran Rd belt | B21: Matheran Road | D21: Matheran Rd belt
A22: =D22 -> Matheran Rd | B22: Matheran Road | D22: Matheran Rd
A23: =D23 -> Dolkhamb (Matheran Rd) | B23: Matheran Road | D23: Dolkhamb (Matheran Rd)

Sheet Submission_Template
A1: Section A - Segmentation Summary (the foundation)
A3: Before any analytics, establish structure. For every listing in Raw_Data, determine: which micro-market it belongs to, its standardized asset class (Villa / Plot / Farmland), its BHK configuration (where applicable), and its vertical (Resale / Long-Term Rental / Short-Term Rental). You can do this with helper columns in Raw_Data, a separate sheet, or a script - your choice. Then fill in the summary grid below: number of usable listings per Micro-Market x Asset Class x Vertical.
A5: Micro-Market | B5: Asset Class | C5: Resale (N) | D5: LTR (N) | E5: STR (N) | F5: Notes
A6: Karjat Town | B6: Villa | C6: =COUNTIFS(MAIN!$M$2:$M$209,$A6,MAIN!$N$2:$N$209,$B6,MAIN!$P$2:$P$209,"Resale") -> 11 | D6: =COUNTIFS(MAIN!$M$2:$M$209,$A6,MAIN!$N$2:$N$209,$B6,MAIN!$P$2:$P$209,"Long Term Rental") -> 8 | E6: =COUNTIFS(MAIN!$M$2:$M$209,$A6,MAIN!$N$2:$N$209,$B6,MAIN!$P$2:$P$209,"Short Term Rental") -> 10
A7: Karjat Town | B7: Plot | C7: =COUNTIFS(MAIN!$M$2:$M$209,$A7,MAIN!$N$2:$N$209,$B7,MAIN!$P$2:$P$209,"Resale") -> 8 | D7: =COUNTIFS(MAIN!$M$2:$M$209,$A7,MAIN!$N$2:$N$209,$B7,MAIN!$P$2:$P$209,"Long Term Rental") -> 0 | E7: =COUNTIFS(MAIN!$M$2:$M$209,$A7,MAIN!$N$2:$N$209,$B7,MAIN!$P$2:$P$209,"Short Term Rental") -> 0
A8: Karjat Town | B8: Farmland | C8: =COUNTIFS(MAIN!$M$2:$M$209,$A8,MAIN!$N$2:$N$209,$B8,MAIN!$P$2:$P$209,"Resale") -> 5 | D8: =COUNTIFS(MAIN!$M$2:$M$209,$A8,MAIN!$N$2:$N$209,$B8,MAIN!$P$2:$P$209,"Long Term Rental") -> 0 | E8: =COUNTIFS(MAIN!$M$2:$M$209,$A8,MAIN!$N$2:$N$209,$B8,MAIN!$P$2:$P$209,"Short Term Rental") -> 0
A9: Neral | B9: Villa | C9: =COUNTIFS(MAIN!$M$2:$M$209,$A9,MAIN!$N$2:$N$209,$B9,MAIN!$P$2:$P$209,"Resale") -> 15 | D9: =COUNTIFS(MAIN!$M$2:$M$209,$A9,MAIN!$N$2:$N$209,$B9,MAIN!$P$2:$P$209,"Long Term Rental") -> 9 | E9: =COUNTIFS(MAIN!$M$2:$M$209,$A9,MAIN!$N$2:$N$209,$B9,MAIN!$P$2:$P$209,"Short Term Rental") -> 9
A10: Neral | B10: Plot | C10: =COUNTIFS(MAIN!$M$2:$M$209,$A10,MAIN!$N$2:$N$209,$B10,MAIN!$P$2:$P$209,"Resale") -> 5 | D10: =COUNTIFS(MAIN!$M$2:$M$209,$A10,MAIN!$N$2:$N$209,$B10,MAIN!$P$2:$P$209,"Long Term Rental") -> 0 | E10: =COUNTIFS(MAIN!$M$2:$M$209,$A10,MAIN!$N$2:$N$209,$B10,MAIN!$P$2:$P$209,"Short Term Rental") -> 0
A11: Neral | B11: Farmland | C11: =COUNTIFS(MAIN!$M$2:$M$209,$A11,MAIN!$N$2:$N$209,$B11,MAIN!$P$2:$P$209,"Resale") -> 5 | D11: =COUNTIFS(MAIN!$M$2:$M$209,$A11,MAIN!$N$2:$N$209,$B11,MAIN!$P$2:$P$209,"Long Term Rental") -> 0 | E11: =COUNTIFS(MAIN!$M$2:$M$209,$A11,MAIN!$N$2:$N$209,$B11,MAIN!$P$2:$P$209,"Short Term Rental") -> 0
A12: Kashele | B12: Villa | C12: =COUNTIFS(MAIN!$M$2:$M$209,$A12,MAIN!$N$2:$N$209,$B12,MAIN!$P$2:$P$209,"Resale") -> 13 | D12: =COUNTIFS(MAIN!$M$2:$M$209,$A12,MAIN!$N$2:$N$209,$B12,MAIN!$P$2:$P$209,"Long Term Rental") -> 9 | E12: =COUNTIFS(MAIN!$M$2:$M$209,$A12,MAIN!$N$2:$N$209,$B12,MAIN!$P$2:$P$209,"Short Term Rental") -> 9
A13: Kashele | B13: Plot | C13: =COUNTIFS(MAIN!$M$2:$M$209,$A13,MAIN!$N$2:$N$209,$B13,MAIN!$P$2:$P$209,"Resale") -> 9 | D13: =COUNTIFS(MAIN!$M$2:$M$209,$A13,MAIN!$N$2:$N$209,$B13,MAIN!$P$2:$P$209,"Long Term Rental") -> 0 | E13: =COUNTIFS(MAIN!$M$2:$M$209,$A13,MAIN!$N$2:$N$209,$B13,MAIN!$P$2:$P$209,"Short Term Rental") -> 0
A14: Kashele | B14: Farmland | C14: =COUNTIFS(MAIN!$M$2:$M$209,$A14,MAIN!$N$2:$N$209,$B14,MAIN!$P$2:$P$209,"Resale") -> 5 | D14: =COUNTIFS(MAIN!$M$2:$M$209,$A14,MAIN!$N$2:$N$209,$B14,MAIN!$P$2:$P$209,"Long Term Rental") -> 0 | E14: =COUNTIFS(MAIN!$M$2:$M$209,$A14,MAIN!$N$2:$N$209,$B14,MAIN!$P$2:$P$209,"Short Term Rental") -> 0
A15: Kondhwal Valley | B15: Villa | C15: =COUNTIFS(MAIN!$M$2:$M$209,$A15,MAIN!$N$2:$N$209,$B15,MAIN!$P$2:$P$209,"Resale") -> 6 | D15: =COUNTIFS(MAIN!$M$2:$M$209,$A15,MAIN!$N$2:$N$209,$B15,MAIN!$P$2:$P$209,"Long Term Rental") -> 9 | E15: =COUNTIFS(MAIN!$M$2:$M$209,$A15,MAIN!$N$2:$N$209,$B15,MAIN!$P$2:$P$209,"Short Term Rental") -> 9
A16: Kondhwal Valley | B16: Plot | C16: =COUNTIFS(MAIN!$M$2:$M$209,$A16,MAIN!$N$2:$N$209,$B16,MAIN!$P$2:$P$209,"Resale") -> 8 | D16: =COUNTIFS(MAIN!$M$2:$M$209,$A16,MAIN!$N$2:$N$209,$B16,MAIN!$P$2:$P$209,"Long Term Rental") -> 0 | E16: =COUNTIFS(MAIN!$M$2:$M$209,$A16,MAIN!$N$2:$N$209,$B16,MAIN!$P$2:$P$209,"Short Term Rental") -> 0
A17: Kondhwal Valley | B17: Farmland | C17: =COUNTIFS(MAIN!$M$2:$M$209,$A17,MAIN!$N$2:$N$209,$B17,MAIN!$P$2:$P$209,"Resale") -> 5 | D17: =COUNTIFS(MAIN!$M$2:$M$209,$A17,MAIN!$N$2:$N$209,$B17,MAIN!$P$2:$P$209,"Long Term Rental") -> 0 | E17: =COUNTIFS(MAIN!$M$2:$M$209,$A17,MAIN!$N$2:$N$209,$B17,MAIN!$P$2:$P$209,"Short Term Rental") -> 0
... A20: Matheran Road | B20: Farmland | C20: =COUNTIFS(MAIN!$M$2:$M$209,$A20,MAIN!$N$2:$N$209,$B20,MAIN!$P$2:$P$209,"Resale") -> 10 | D20: =COUNTIFS(MAIN!$M$2:$M$209,$A20,MAIN!$N$2:$N$209,$B20,MAIN!$P$2:$P$209,"Long Term Rental") -> 0 | E20: =COUNTIFS(MAIN!$M$2:$M$209,$A20,MAIN!$N$2:$N$209,$B20,MAIN!$P$2:$P$209,"Short Term Rental") -> 0
A22: Section B - Karjat Analytics
A24: Using only cleaned, unit-normalized, de-duplicated data:
A26: Metric | B26: Value | C26: Basis (N, method) | D26: Caveat (if any)
A27: Resale PPSF - strongest micro-market/asset combo | B27: Matheran Road , Villa, 5,034.61rs/sq ft | C27: N = 10, Median resale PPSF | D27: based on available rescale listings
A28: Resale PPSF - weakest / too-thin-to-report combo(s) | B28: Kondhwal Valley , Farmland, 123.37rs/sq ft | C28: N = 5, Median resale PPSF
A29: LTR - median INR/sqft/month, best micro-market | B29: Matheran Road — ₹15.94/sqft | C29: N = 8, median LTR INR/sqft for Matheran Road Villa | D29: Based on 8 Long Term Rental records; LTR observations are available only for Villa in this dataset.
A30: Implied gross rental yield - best micro-market (Villa) | B30: Kondhwal Valley Villa — 4.37% | C30: N = 9; calculated as (median LTR INR/sqft/month × 12 ÷ median resale PPSF) × 100
A31: STR - median ADR, best micro-market | B31: Kondhwal Valley — ₹6,300/night | C31: Median of STR nightly prices for Kondhwal Valley
A32: STR - occupancy rate | B32: Not calculable from available data | D32: Status indicates listing status, not actual occupancy.
A34: One synthesis question: across all three verticals, which micro-market/asset-class combination would you flag to the business as the strongest current case for short-term-rental positioning over a straight resale play - and which would you flag as too data-thin to make any claim at all? Answer below.
A36: I would flag Kondhwal Valley Villa as the strongest current case for short term rental. It has the highest median short term rental price at ₹6,300 per night, along with a reasonable resale value and 4.37% implied rental yield from long term rental data.For a data thin combination, I would say Plot and Farmland, since there are very few short term rental listings to make a reliable comparison or conclusion.
A42: Section C - Decision Log
A44: At least 5 entries. Specific row(s), what you decided, and why - in your own words.
A46: # | B46: Row ID(s) | C46: Decision & Reasoning
A47: 1 | B47: Relevant rows | C47: I used median resale PPSF rather than average because a few unusually high or low priced listings could distort the comparison.
A48: 2 | B48: Relevant rows ( Also in dashboard ) | C48: I compared resale PPSF with implied rental yield to identify markets that combine a relatively lower entry price with stronger rental potential.
A49: 3 | B49: rows related to Plot and Farmland | C49: I did not make a strong STR recommendation for Plot and Farmland because the available STR observations were too limited to support a reliable conclusion.
A50: 4 | B50: K0096 | C50: I did not rely fully on the listed price because the remark says the owner quoted ₹2.11 crore verbally but the portal price was not updated. I treated this as a pricing reliability issue.
A51: 5 | B51: K0034 | C51: STR availability is not the same as confirmed bookings, so I kept the conclusion cautious.
A52: 6
A54: Section D - How Would You Present This to Sales?
A56: This is the part we care about most. Not a written summary of your numbers - an actual answer to how you'd put this in front of a sales team member before a client call. What format (one-pager, slide, dashboard, a table plus three spoken lines)? What's the headline you'd lead with? What would you deliberately leave out, footnote, or downgrade in confidence, and why?
A58: I would present this as a one page Power BI dashboard focused on where the strongest property opportunities currently appear. I would start with the key finding rather than walking through every chart. I would highlight the micro markets that combine attractive resale pricing with stronger rental yields, then use the asset level breakdown to show which property types are driving the opportunity. I would avoid presenting small sample results as strong conclusions and would clearly flag areas where the STR data is limited.I ahve created a PowerBI dashboard and added a scatter plot which clearly helps the user which can indicate a more attractive rental investment opportunity. From that chart we have got an important insight Kondhwal Valley stands out most clearly. It has the lowest resale PPSF among the five markets while also having the highest implied gross rental yield.Neral is also relatively attractive because its resale price is still lower than Kashele, Karjat Town and Matheran Road while its yield is relatively high.At the other end, Karjat Town and Matheran Road have higher resale prices but lower yields, so they look less attractive if the objective is specifically rental income.
A69: Section E - What Else Would You Do
A71: Optional, but we're genuinely interested. If you had one more day: what additional analysis, data, or presentation element would you add, and why?
A73: If I had more time I would do more detailed manual analysis since it has fewer rows , and also few reportings with the dashboard. Also I would go deeper with the pricing. More importantly I would focus more on the excel formulas which I used. These I would do because it will help me to deliver better insights and recommendations and also it would help the sales team member understand more clearly.
